{
  "header" : {
    "generated" : "2022-04-04T13:57:05",
    "vl_id" : 333,
    "nvv_id" : 352
  },
  "list" : [ {
    "maz" : "08",
    "taz" : "100",
    "sorsz" : "001",
    "feldar" : 100.0,
    "egyeni_jkv" : {
      "allapot" : "3",
      "vp_osszes" : 500,
      "szavazott_osszesen" : 381,
      "szavazott_osszesen_szaz" : 76.2,
      "vp_lakcim_szerint" : 500,
      "megjel_lakcim_szerint" : 381,
      "megjel_lakcim_szerint_szaz" : 76.2,
      "vp_atjel" : 2,
      "megjel_atjel" : 2,
      "megjel_atjel_szaz" : 100.0,
      "szl_belyegtlen_urna" : 0,
      "szl_belyegzett_urna" : 381,
      "szl_elteres" : 0,
      "szl_ervenytelen" : 12,
      "szl_ervenytelen_szaz" : 3.15,
      "szl_ervenyes" : 369,
      "szl_ervenyes_szaz" : 96.85,
      "tetelek" : [ {
        "sorsz" : 3,
        "ej_id" : 72111,
        "szavazat" : 252,
        "szavazat_szaz" : 68.29
      }, {
        "sorsz" : 6,
        "ej_id" : 72014,
        "szavazat" : 76,
        "szavazat_szaz" : 20.6
      }, {
        "sorsz" : 1,
        "ej_id" : 72435,
        "szavazat" : 22,
        "szavazat_szaz" : 5.96
      }, {
        "sorsz" : 2,
        "ej_id" : 72590,
        "szavazat" : 12,
        "szavazat_szaz" : 3.25
      }, {
        "sorsz" : 5,
        "ej_id" : 72386,
        "szavazat" : 4,
        "szavazat_szaz" : 1.08
      }, {
        "sorsz" : 4,
        "ej_id" : 72331,
        "szavazat" : 3,
        "szavazat_szaz" : 0.81
      } ]
    },
    "listas_jkv" : {
      "allapot" : "3",
      "vp_osszes" : 500,
      "szavazott_osszesen" : 381,
      "szavazott_osszesen_szaz" : 76.2,
      "vp_lakcim_szerint" : 500,
      "megjel_lakcim_szerint" : 381,
      "megjel_lakcim_szerint_szaz" : 76.2,
      "vp_atjel" : 2,
      "megjel_atjel" : 2,
      "megjel_atjel_szaz" : 100.0,
      "szl_belyegtlen_urna" : 0,
      "szl_belyegzett_urna" : 381,
      "szl_elteres" : 0,
      "szl_ervenytelen" : 2,
      "szl_ervenytelen_szaz" : 0.52,
      "szl_ervenyes" : 379,
      "szl_ervenyes_szaz" : 99.48,
      "partlistara" : {
        "vp_osszes" : 500,
        "megjelent" : 381,
        "szl_belyegtlen_urna" : 0,
        "szl_belyegzett_urna" : 381,
        "szl_elteres" : 0,
        "szl_ervenytelen" : 2,
        "szl_ervenyes" : 379
      },
      "tetelek" : [ {
        "sorsz" : 6,
        "tl_id" : 952,
        "szavazat" : 250,
        "szavazat_szaz" : 65.96
      }, {
        "sorsz" : 1,
        "tl_id" : 950,
        "szavazat" : 80,
        "szavazat_szaz" : 21.11
      }, {
        "sorsz" : 5,
        "tl_id" : 942,
        "szavazat" : 26,
        "szavazat_szaz" : 6.86
      }, {
        "sorsz" : 3,
        "tl_id" : 951,
        "szavazat" : 12,
        "szavazat_szaz" : 3.17
      }, {
        "sorsz" : 2,
        "tl_id" : 955,
        "szavazat" : 7,
        "szavazat_szaz" : 1.85
      }, {
        "sorsz" : 4,
        "tl_id" : 954,
        "szavazat" : 4,
        "szavazat_szaz" : 1.06
      } ]
    }
  } ]
}
