{
  "header" : {
    "generated" : "2022-04-04T13:57:05",
    "vl_id" : 333,
    "nvv_id" : 352
  },
  "list" : [ {
    "maz" : "15",
    "taz" : "016",
    "sorsz" : "001",
    "feldar" : 100.0,
    "egyeni_jkv" : {
      "allapot" : "3",
      "vp_osszes" : 861,
      "szavazott_osszesen" : 647,
      "szavazott_osszesen_szaz" : 75.15,
      "vp_lakcim_szerint" : 861,
      "megjel_lakcim_szerint" : 647,
      "megjel_lakcim_szerint_szaz" : 75.15,
      "vp_atjel" : 93,
      "megjel_atjel" : 91,
      "megjel_atjel_szaz" : 97.85,
      "szl_belyegtlen_urna" : 0,
      "szl_belyegzett_urna" : 644,
      "szl_elteres" : -3,
      "szl_ervenytelen" : 8,
      "szl_ervenytelen_szaz" : 1.24,
      "szl_ervenyes" : 636,
      "szl_ervenyes_szaz" : 98.76,
      "tetelek" : [ {
        "sorsz" : 2,
        "ej_id" : 71968,
        "szavazat" : 348,
        "szavazat_szaz" : 54.72
      }, {
        "sorsz" : 5,
        "ej_id" : 72048,
        "szavazat" : 270,
        "szavazat_szaz" : 42.45
      }, {
        "sorsz" : 4,
        "ej_id" : 72226,
        "szavazat" : 7,
        "szavazat_szaz" : 1.1
      }, {
        "sorsz" : 1,
        "ej_id" : 72669,
        "szavazat" : 6,
        "szavazat_szaz" : 0.94
      }, {
        "sorsz" : 3,
        "ej_id" : 72660,
        "szavazat" : 5,
        "szavazat_szaz" : 0.79
      } ]
    },
    "listas_jkv" : {
      "allapot" : "3",
      "vp_osszes" : 861,
      "szavazott_osszesen" : 647,
      "szavazott_osszesen_szaz" : 75.15,
      "vp_lakcim_szerint" : 861,
      "megjel_lakcim_szerint" : 647,
      "megjel_lakcim_szerint_szaz" : 75.15,
      "vp_atjel" : 93,
      "megjel_atjel" : 91,
      "megjel_atjel_szaz" : 97.85,
      "szl_belyegtlen_urna" : 0,
      "szl_belyegzett_urna" : 645,
      "szl_elteres" : 0,
      "szl_ervenytelen" : 5,
      "szl_ervenytelen_szaz" : 0.78,
      "szl_ervenyes" : 640,
      "szl_ervenyes_szaz" : 99.22,
      "partlistara" : {
        "vp_osszes" : 861,
        "megjelent" : 647,
        "szl_belyegtlen_urna" : 0,
        "szl_belyegzett_urna" : 645,
        "szl_elteres" : -2,
        "szl_ervenytelen" : 5,
        "szl_ervenyes" : 640
      },
      "tetelek" : [ {
        "sorsz" : 6,
        "tl_id" : 952,
        "szavazat" : 328,
        "szavazat_szaz" : 51.25
      }, {
        "sorsz" : 1,
        "tl_id" : 950,
        "szavazat" : 243,
        "szavazat_szaz" : 37.97
      }, {
        "sorsz" : 5,
        "tl_id" : 942,
        "szavazat" : 45,
        "szavazat_szaz" : 7.03
      }, {
        "sorsz" : 3,
        "tl_id" : 951,
        "szavazat" : 12,
        "szavazat_szaz" : 1.88
      }, {
        "sorsz" : 2,
        "tl_id" : 955,
        "szavazat" : 7,
        "szavazat_szaz" : 1.09
      }, {
        "sorsz" : 4,
        "tl_id" : 954,
        "szavazat" : 5,
        "szavazat_szaz" : 0.78
      } ]
    }
  }, {
    "maz" : "15",
    "taz" : "016",
    "sorsz" : "002",
    "feldar" : 100.0,
    "egyeni_jkv" : {
      "allapot" : "3",
      "vp_osszes" : 872,
      "szavazott_osszesen" : 650,
      "szavazott_osszesen_szaz" : 74.54,
      "vp_lakcim_szerint" : 872,
      "megjel_lakcim_szerint" : 650,
      "megjel_lakcim_szerint_szaz" : 74.54,
      "szl_belyegtlen_urna" : 0,
      "szl_belyegzett_urna" : 650,
      "szl_elteres" : 0,
      "szl_ervenytelen" : 3,
      "szl_ervenytelen_szaz" : 0.46,
      "szl_ervenyes" : 647,
      "szl_ervenyes_szaz" : 99.54,
      "tetelek" : [ {
        "sorsz" : 2,
        "ej_id" : 71968,
        "szavazat" : 367,
        "szavazat_szaz" : 56.72
      }, {
        "sorsz" : 5,
        "ej_id" : 72048,
        "szavazat" : 249,
        "szavazat_szaz" : 38.49
      }, {
        "sorsz" : 3,
        "ej_id" : 72660,
        "szavazat" : 15,
        "szavazat_szaz" : 2.32
      }, {
        "sorsz" : 4,
        "ej_id" : 72226,
        "szavazat" : 11,
        "szavazat_szaz" : 1.7
      }, {
        "sorsz" : 1,
        "ej_id" : 72669,
        "szavazat" : 5,
        "szavazat_szaz" : 0.77
      } ]
    },
    "listas_jkv" : {
      "allapot" : "3",
      "vp_osszes" : 872,
      "szavazott_osszesen" : 650,
      "szavazott_osszesen_szaz" : 74.54,
      "vp_lakcim_szerint" : 872,
      "megjel_lakcim_szerint" : 650,
      "megjel_lakcim_szerint_szaz" : 74.54,
      "szl_belyegtlen_urna" : 0,
      "szl_belyegzett_urna" : 650,
      "szl_elteres" : 0,
      "szl_ervenytelen" : 3,
      "szl_ervenytelen_szaz" : 0.46,
      "szl_ervenyes" : 647,
      "szl_ervenyes_szaz" : 99.54,
      "partlistara" : {
        "vp_osszes" : 872,
        "megjelent" : 650,
        "szl_belyegtlen_urna" : 0,
        "szl_belyegzett_urna" : 650,
        "szl_elteres" : 0,
        "szl_ervenytelen" : 3,
        "szl_ervenyes" : 647
      },
      "tetelek" : [ {
        "sorsz" : 6,
        "tl_id" : 952,
        "szavazat" : 333,
        "szavazat_szaz" : 51.47
      }, {
        "sorsz" : 1,
        "tl_id" : 950,
        "szavazat" : 242,
        "szavazat_szaz" : 37.4
      }, {
        "sorsz" : 5,
        "tl_id" : 942,
        "szavazat" : 37,
        "szavazat_szaz" : 5.72
      }, {
        "sorsz" : 3,
        "tl_id" : 951,
        "szavazat" : 22,
        "szavazat_szaz" : 3.4
      }, {
        "sorsz" : 2,
        "tl_id" : 955,
        "szavazat" : 7,
        "szavazat_szaz" : 1.08
      }, {
        "sorsz" : 4,
        "tl_id" : 954,
        "szavazat" : 6,
        "szavazat_szaz" : 0.93
      } ]
    }
  } ]
}
