<?xml version="1.0" encoding="ISO-8859-2"?>
<oevk>
<oevkr>
<maz>01</maz>
<evk>01</evk>
<szekh>Budapest</szekh>
<szekhk>05</szekhk>
</oevkr>
<oevkr>
<maz>01</maz>
<evk>02</evk>
<szekh>Budapest</szekh>
<szekhk>11</szekhk>
</oevkr>
<oevkr>
<maz>01</maz>
<evk>03</evk>
<szekh>Budapest</szekh>
<szekhk>12</szekhk>
</oevkr>
<oevkr>
<maz>01</maz>
<evk>04</evk>
<szekh>Budapest</szekh>
<szekhk>02</szekhk>
</oevkr>
<oevkr>
<maz>01</maz>
<evk>05</evk>
<szekh>Budapest</szekh>
<szekhk>07</szekhk>
</oevkr>
<oevkr>
<maz>01</maz>
<evk>06</evk>
<szekh>Budapest</szekh>
<szekhk>08</szekhk>
</oevkr>
<oevkr>
<maz>01</maz>
<evk>07</evk>
<szekh>Budapest</szekh>
<szekhk>13</szekhk>
</oevkr>
<oevkr>
<maz>01</maz>
<evk>08</evk>
<szekh>Budapest</szekh>
<szekhk>14</szekhk>
</oevkr>
<oevkr>
<maz>01</maz>
<evk>09</evk>
<szekh>Budapest</szekh>
<szekhk>10</szekhk>
</oevkr>
<oevkr>
<maz>01</maz>
<evk>10</evk>
<szekh>Budapest</szekh>
<szekhk>03</szekhk>
</oevkr>
<oevkr>
<maz>01</maz>
<evk>11</evk>
<szekh>Budapest</szekh>
<szekhk>04</szekhk>
</oevkr>
<oevkr>
<maz>01</maz>
<evk>12</evk>
<szekh>Budapest</szekh>
<szekhk>15</szekhk>
</oevkr>
<oevkr>
<maz>01</maz>
<evk>13</evk>
<szekh>Budapest</szekh>
<szekhk>16</szekhk>
</oevkr>
<oevkr>
<maz>01</maz>
<evk>14</evk>
<szekh>Budapest</szekh>
<szekhk>17</szekhk>
</oevkr>
<oevkr>
<maz>01</maz>
<evk>15</evk>
<szekh>Budapest</szekh>
<szekhk>18</szekhk>
</oevkr>
<oevkr>
<maz>01</maz>
<evk>16</evk>
<szekh>Budapest</szekh>
<szekhk>20</szekhk>
</oevkr>
<oevkr>
<maz>01</maz>
<evk>17</evk>
<szekh>Budapest</szekh>
<szekhk>21</szekhk>
</oevkr>
<oevkr>
<maz>01</maz>
<evk>18</evk>
<szekh>Budapest</szekh>
<szekhk>22</szekhk>
</oevkr>
<oevkr>
<maz>02</maz>
<evk>01</evk>
<szekh>Pécs</szekh>
<szekhk/>
</oevkr>
<oevkr>
<maz>02</maz>
<evk>02</evk>
<szekh>Pécs</szekh>
<szekhk/>
</oevkr>
<oevkr>
<maz>02</maz>
<evk>03</evk>
<szekh>Mohács</szekh>
<szekhk/>
</oevkr>
<oevkr>
<maz>02</maz>
<evk>04</evk>
<szekh>Szigetvár</szekh>
<szekhk/>
</oevkr>
<oevkr>
<maz>03</maz>
<evk>01</evk>
<szekh>Kecskemét</szekh>
<szekhk/>
</oevkr>
<oevkr>
<maz>03</maz>
<evk>02</evk>
<szekh>Kecskemét</szekh>
<szekhk/>
</oevkr>
<oevkr>
<maz>03</maz>
<evk>03</evk>
<szekh>Kalocsa</szekh>
<szekhk/>
</oevkr>
<oevkr>
<maz>03</maz>
<evk>04</evk>
<szekh>Kiskunfélegyháza</szekh>
<szekhk/>
</oevkr>
<oevkr>
<maz>03</maz>
<evk>05</evk>
<szekh>Kiskunhalas</szekh>
<szekhk/>
</oevkr>
<oevkr>
<maz>03</maz>
<evk>06</evk>
<szekh>Baja</szekh>
<szekhk/>
</oevkr>
<oevkr>
<maz>04</maz>
<evk>01</evk>
<szekh>Békéscsaba</szekh>
<szekhk/>
</oevkr>
<oevkr>
<maz>04</maz>
<evk>02</evk>
<szekh>Békés</szekh>
<szekhk/>
</oevkr>
<oevkr>
<maz>04</maz>
<evk>03</evk>
<szekh>Gyula</szekh>
<szekhk/>
</oevkr>
<oevkr>
<maz>04</maz>
<evk>04</evk>
<szekh>Orosháza</szekh>
<szekhk/>
</oevkr>
<oevkr>
<maz>05</maz>
<evk>01</evk>
<szekh>Miskolc</szekh>
<szekhk/>
</oevkr>
<oevkr>
<maz>05</maz>
<evk>02</evk>
<szekh>Miskolc</szekh>
<szekhk/>
</oevkr>
<oevkr>
<maz>05</maz>
<evk>03</evk>
<szekh>Ózd</szekh>
<szekhk/>
</oevkr>
<oevkr>
<maz>05</maz>
<evk>04</evk>
<szekh>Kazincbarcika</szekh>
<szekhk/>
</oevkr>
<oevkr>
<maz>05</maz>
<evk>05</evk>
<szekh>Sátoraljaújhely</szekh>
<szekhk/>
</oevkr>
<oevkr>
<maz>05</maz>
<evk>06</evk>
<szekh>Tiszaújváros</szekh>
<szekhk/>
</oevkr>
<oevkr>
<maz>05</maz>
<evk>07</evk>
<szekh>Mezõkövesd</szekh>
<szekhk/>
</oevkr>
<oevkr>
<maz>06</maz>
<evk>01</evk>
<szekh>Szeged</szekh>
<szekhk/>
</oevkr>
<oevkr>
<maz>06</maz>
<evk>02</evk>
<szekh>Szeged</szekh>
<szekhk/>
</oevkr>
<oevkr>
<maz>06</maz>
<evk>03</evk>
<szekh>Szentes</szekh>
<szekhk/>
</oevkr>
<oevkr>
<maz>06</maz>
<evk>04</evk>
<szekh>Hódmezõvásárhely</szekh>
<szekhk/>
</oevkr>
<oevkr>
<maz>07</maz>
<evk>01</evk>
<szekh>Székesfehérvár</szekh>
<szekhk/>
</oevkr>
<oevkr>
<maz>07</maz>
<evk>02</evk>
<szekh>Székesfehérvár</szekh>
<szekhk/>
</oevkr>
<oevkr>
<maz>07</maz>
<evk>03</evk>
<szekh>Bicske</szekh>
<szekhk/>
</oevkr>
<oevkr>
<maz>07</maz>
<evk>04</evk>
<szekh>Dunaújváros</szekh>
<szekhk/>
</oevkr>
<oevkr>
<maz>07</maz>
<evk>05</evk>
<szekh>Sárbogárd</szekh>
<szekhk/>
</oevkr>
<oevkr>
<maz>08</maz>
<evk>01</evk>
<szekh>Gyõr</szekh>
<szekhk/>
</oevkr>
<oevkr>
<maz>08</maz>
<evk>02</evk>
<szekh>Gyõr</szekh>
<szekhk/>
</oevkr>
<oevkr>
<maz>08</maz>
<evk>03</evk>
<szekh>Csorna</szekh>
<szekhk/>
</oevkr>
<oevkr>
<maz>08</maz>
<evk>04</evk>
<szekh>Sopron</szekh>
<szekhk/>
</oevkr>
<oevkr>
<maz>08</maz>
<evk>05</evk>
<szekh>Mosonmagyaróvár</szekh>
<szekhk/>
</oevkr>
<oevkr>
<maz>09</maz>
<evk>01</evk>
<szekh>Debrecen</szekh>
<szekhk/>
</oevkr>
<oevkr>
<maz>09</maz>
<evk>02</evk>
<szekh>Debrecen</szekh>
<szekhk/>
</oevkr>
<oevkr>
<maz>09</maz>
<evk>03</evk>
<szekh>Debrecen</szekh>
<szekhk/>
</oevkr>
<oevkr>
<maz>09</maz>
<evk>04</evk>
<szekh>Berettyóújfalu</szekh>
<szekhk/>
</oevkr>
<oevkr>
<maz>09</maz>
<evk>05</evk>
<szekh>Hajdúszoboszló</szekh>
<szekhk/>
</oevkr>
<oevkr>
<maz>09</maz>
<evk>06</evk>
<szekh>Hajdúböszörmény</szekh>
<szekhk/>
</oevkr>
<oevkr>
<maz>10</maz>
<evk>01</evk>
<szekh>Eger</szekh>
<szekhk/>
</oevkr>
<oevkr>
<maz>10</maz>
<evk>02</evk>
<szekh>Gyöngyös</szekh>
<szekhk/>
</oevkr>
<oevkr>
<maz>10</maz>
<evk>03</evk>
<szekh>Hatvan</szekh>
<szekhk/>
</oevkr>
<oevkr>
<maz>11</maz>
<evk>01</evk>
<szekh>Szolnok</szekh>
<szekhk/>
</oevkr>
<oevkr>
<maz>11</maz>
<evk>02</evk>
<szekh>Jászberény</szekh>
<szekhk/>
</oevkr>
<oevkr>
<maz>11</maz>
<evk>03</evk>
<szekh>Karcag</szekh>
<szekhk/>
</oevkr>
<oevkr>
<maz>11</maz>
<evk>04</evk>
<szekh>Törökszentmiklós</szekh>
<szekhk/>
</oevkr>
<oevkr>
<maz>12</maz>
<evk>01</evk>
<szekh>Tatabánya</szekh>
<szekhk/>
</oevkr>
<oevkr>
<maz>12</maz>
<evk>02</evk>
<szekh>Esztergom</szekh>
<szekhk/>
</oevkr>
<oevkr>
<maz>12</maz>
<evk>03</evk>
<szekh>Komárom</szekh>
<szekhk/>
</oevkr>
<oevkr>
<maz>13</maz>
<evk>01</evk>
<szekh>Salgótarján</szekh>
<szekhk/>
</oevkr>
<oevkr>
<maz>13</maz>
<evk>02</evk>
<szekh>Balassagyarmat</szekh>
<szekhk/>
</oevkr>
<oevkr>
<maz>14</maz>
<evk>01</evk>
<szekh>Érd</szekh>
<szekhk/>
</oevkr>
<oevkr>
<maz>14</maz>
<evk>02</evk>
<szekh>Budakeszi</szekh>
<szekhk/>
</oevkr>
<oevkr>
<maz>14</maz>
<evk>03</evk>
<szekh>Szentendre</szekh>
<szekhk/>
</oevkr>
<oevkr>
<maz>14</maz>
<evk>04</evk>
<szekh>Vác</szekh>
<szekhk/>
</oevkr>
<oevkr>
<maz>14</maz>
<evk>05</evk>
<szekh>Dunakeszi</szekh>
<szekhk/>
</oevkr>
<oevkr>
<maz>14</maz>
<evk>06</evk>
<szekh>Gödöllõ</szekh>
<szekhk/>
</oevkr>
<oevkr>
<maz>14</maz>
<evk>07</evk>
<szekh>Vecsés</szekh>
<szekhk/>
</oevkr>
<oevkr>
<maz>14</maz>
<evk>08</evk>
<szekh>Szigetszentmiklós</szekh>
<szekhk/>
</oevkr>
<oevkr>
<maz>14</maz>
<evk>09</evk>
<szekh>Nagykáta</szekh>
<szekhk/>
</oevkr>
<oevkr>
<maz>14</maz>
<evk>10</evk>
<szekh>Monor</szekh>
<szekhk/>
</oevkr>
<oevkr>
<maz>14</maz>
<evk>11</evk>
<szekh>Dabas</szekh>
<szekhk/>
</oevkr>
<oevkr>
<maz>14</maz>
<evk>12</evk>
<szekh>Cegléd</szekh>
<szekhk/>
</oevkr>
<oevkr>
<maz>15</maz>
<evk>01</evk>
<szekh>Kaposvár</szekh>
<szekhk/>
</oevkr>
<oevkr>
<maz>15</maz>
<evk>02</evk>
<szekh>Barcs</szekh>
<szekhk/>
</oevkr>
<oevkr>
<maz>15</maz>
<evk>03</evk>
<szekh>Marcali</szekh>
<szekhk/>
</oevkr>
<oevkr>
<maz>15</maz>
<evk>04</evk>
<szekh>Siófok</szekh>
<szekhk/>
</oevkr>
<oevkr>
<maz>16</maz>
<evk>01</evk>
<szekh>Nyíregyháza</szekh>
<szekhk/>
</oevkr>
<oevkr>
<maz>16</maz>
<evk>02</evk>
<szekh>Nyíregyháza</szekh>
<szekhk/>
</oevkr>
<oevkr>
<maz>16</maz>
<evk>03</evk>
<szekh>Kisvárda</szekh>
<szekhk/>
</oevkr>
<oevkr>
<maz>16</maz>
<evk>04</evk>
<szekh>Vásárosnamény</szekh>
<szekhk/>
</oevkr>
<oevkr>
<maz>16</maz>
<evk>05</evk>
<szekh>Mátészalka</szekh>
<szekhk/>
</oevkr>
<oevkr>
<maz>16</maz>
<evk>06</evk>
<szekh>Nyírbátor</szekh>
<szekhk/>
</oevkr>
<oevkr>
<maz>17</maz>
<evk>01</evk>
<szekh>Szekszárd</szekh>
<szekhk/>
</oevkr>
<oevkr>
<maz>17</maz>
<evk>02</evk>
<szekh>Dombóvár</szekh>
<szekhk/>
</oevkr>
<oevkr>
<maz>17</maz>
<evk>03</evk>
<szekh>Paks</szekh>
<szekhk/>
</oevkr>
<oevkr>
<maz>18</maz>
<evk>01</evk>
<szekh>Szombathely</szekh>
<szekhk/>
</oevkr>
<oevkr>
<maz>18</maz>
<evk>02</evk>
<szekh>Sárvár</szekh>
<szekhk/>
</oevkr>
<oevkr>
<maz>18</maz>
<evk>03</evk>
<szekh>Körmend</szekh>
<szekhk/>
</oevkr>
<oevkr>
<maz>19</maz>
<evk>01</evk>
<szekh>Veszprém</szekh>
<szekhk/>
</oevkr>
<oevkr>
<maz>19</maz>
<evk>02</evk>
<szekh>Balatonfüred</szekh>
<szekhk/>
</oevkr>
<oevkr>
<maz>19</maz>
<evk>03</evk>
<szekh>Tapolca</szekh>
<szekhk/>
</oevkr>
<oevkr>
<maz>19</maz>
<evk>04</evk>
<szekh>Pápa</szekh>
<szekhk/>
</oevkr>
<oevkr>
<maz>20</maz>
<evk>01</evk>
<szekh>Zalaegerszeg</szekh>
<szekhk/>
</oevkr>
<oevkr>
<maz>20</maz>
<evk>02</evk>
<szekh>Keszthely</szekh>
<szekhk/>
</oevkr>
<oevkr>
<maz>20</maz>
<evk>03</evk>
<szekh>Nagykanizsa</szekh>
<szekhk/>
</oevkr>
</oevk>
