{
  "header" : {
    "generated" : "2022-04-02T23:30:00",
    "vl_id" : 333,
    "nvv_id" : 352
  },
  "data" : {
    "maz" : "02",
    "taz" : "051",
    "szavazokorok" : [ {
      "sorszam" : "001",
      "szk_nev" : "Dencsháza, 001. számú szavazókör",
      "evk" : "04",
      "evk_nev" : "BARANYA megye, 04. számú OEVK",
      "cim" : " Dencsháza, Petőfi utca 42. (Művelődési Ház)",
      "akadaly" : "I",
      "szamlKijelolt" : "N",
      "atjKijelolt" : "I",
      "telepSzintu" : "I",
      "letszam" : {
        "indulo" : 453,
        "honos" : 446,
        "atjel" : 5,
        "atjelInnen" : 4,
        "osszesen" : 451
      }
    } ]
  }
}
