{
  "header" : {
    "generated" : "2022-04-02T23:30:00",
    "vl_id" : 333,
    "nvv_id" : 352
  },
  "data" : {
    "maz" : "15",
    "taz" : "078",
    "szavazokorok" : [ {
      "sorszam" : "001",
      "szk_nev" : "Inke, 001. számú szavazókör",
      "evk" : "02",
      "evk_nev" : "SOMOGY megye, 02. számú OEVK",
      "cim" : " Inke, Kanizsai u. 6. (Polgármesteri Hivatal)",
      "akadaly" : "I",
      "szamlKijelolt" : "N",
      "atjKijelolt" : "I",
      "telepSzintu" : "I",
      "letszam" : {
        "indulo" : 927,
        "honos" : 896,
        "atjel" : 10,
        "atjelInnen" : 16,
        "osszesen" : 906
      }
    } ]
  }
}
