{
  "header" : {
    "generated" : "2022-04-02T23:30:00",
    "vl_id" : 333,
    "nvv_id" : 352
  },
  "data" : {
    "maz" : "18",
    "taz" : "151",
    "szavazokorok" : [ {
      "sorszam" : "001",
      "szk_nev" : "Pósfa, 001. számú szavazókör",
      "evk" : "02",
      "evk_nev" : "VAS megye, 02. számú OEVK",
      "cim" : " Pósfa, Kossuth Lajos utca 28.",
      "akadaly" : "I",
      "szamlKijelolt" : "N",
      "atjKijelolt" : "I",
      "telepSzintu" : "I",
      "letszam" : {
        "indulo" : 219,
        "honos" : 212,
        "atjel" : 3,
        "atjelInnen" : 3,
        "osszesen" : 215
      }
    } ]
  }
}
