{
  "header" : {
    "generated" : "2022-04-02T23:30:00",
    "vl_id" : 333,
    "nvv_id" : 352
  },
  "data" : {
    "maz" : "05",
    "taz" : "308",
    "szavazokorok" : [ {
      "sorszam" : "001",
      "szk_nev" : "Taktaszada, 001. számú szavazókör",
      "evk" : "06",
      "evk_nev" : "BORSOD-ABAÚJ-ZEMPLÉN megye, 06. számú OEVK",
      "cim" : "3921 Taktaszada, Petőfi utca 35. (Művelődési Ház)",
      "akadaly" : "I",
      "szamlKijelolt" : "N",
      "atjKijelolt" : "I",
      "telepSzintu" : "I",
      "letszam" : {
        "indulo" : 683,
        "honos" : 667,
        "atjel" : 4,
        "atjelInnen" : 11,
        "osszesen" : 671
      }
    }, {
      "sorszam" : "002",
      "szk_nev" : "Taktaszada, 002. számú szavazókör",
      "evk" : "06",
      "evk_nev" : "BORSOD-ABAÚJ-ZEMPLÉN megye, 06. számú OEVK",
      "cim" : "3921 Taktaszada, Petőfi utca 17. (Könyvtár)",
      "akadaly" : "N",
      "szamlKijelolt" : "N",
      "atjKijelolt" : "N",
      "telepSzintu" : "N",
      "letszam" : {
        "indulo" : 704,
        "honos" : 695,
        "atjel" : 0,
        "atjelInnen" : 5,
        "osszesen" : 695
      }
    } ]
  }
}
