{
  "header" : {
    "generated" : "2022-04-04T13:57:05",
    "vl_id" : 333,
    "nvv_id" : 352
  },
  "list" : [ {
    "maz" : "14",
    "taz" : "034",
    "sorsz" : "001",
    "feldar" : 100.0,
    "egyeni_jkv" : {
      "allapot" : "3",
      "vp_osszes" : 1194,
      "szavazott_osszesen" : 985,
      "szavazott_osszesen_szaz" : 82.5,
      "vp_lakcim_szerint" : 1194,
      "megjel_lakcim_szerint" : 985,
      "megjel_lakcim_szerint_szaz" : 82.5,
      "szl_belyegtlen_urna" : 0,
      "szl_belyegzett_urna" : 984,
      "szl_elteres" : -1,
      "szl_ervenytelen" : 3,
      "szl_ervenytelen_szaz" : 0.3,
      "szl_ervenyes" : 981,
      "szl_ervenyes_szaz" : 99.7,
      "tetelek" : [ {
        "sorsz" : 5,
        "ej_id" : 71972,
        "szavazat" : 441,
        "szavazat_szaz" : 44.95
      }, {
        "sorsz" : 6,
        "ej_id" : 72007,
        "szavazat" : 424,
        "szavazat_szaz" : 43.22
      }, {
        "sorsz" : 4,
        "ej_id" : 72469,
        "szavazat" : 56,
        "szavazat_szaz" : 5.71
      }, {
        "sorsz" : 2,
        "ej_id" : 72384,
        "szavazat" : 36,
        "szavazat_szaz" : 3.67
      }, {
        "sorsz" : 7,
        "ej_id" : 72539,
        "szavazat" : 16,
        "szavazat_szaz" : 1.63
      }, {
        "sorsz" : 3,
        "ej_id" : 72513,
        "szavazat" : 6,
        "szavazat_szaz" : 0.61
      }, {
        "sorsz" : 1,
        "ej_id" : 72547,
        "szavazat" : 2,
        "szavazat_szaz" : 0.2
      } ]
    },
    "listas_jkv" : {
      "allapot" : "3",
      "vp_osszes" : 1194,
      "szavazott_osszesen" : 985,
      "szavazott_osszesen_szaz" : 82.5,
      "vp_lakcim_szerint" : 1194,
      "megjel_lakcim_szerint" : 985,
      "megjel_lakcim_szerint_szaz" : 82.5,
      "szl_belyegtlen_urna" : 0,
      "szl_belyegzett_urna" : 984,
      "szl_elteres" : 0,
      "szl_ervenytelen" : 7,
      "szl_ervenytelen_szaz" : 0.71,
      "szl_ervenyes" : 977,
      "szl_ervenyes_szaz" : 99.29,
      "partlistara" : {
        "vp_osszes" : 1192,
        "megjelent" : 983,
        "szl_belyegtlen_urna" : 0,
        "szl_belyegzett_urna" : 982,
        "szl_elteres" : -1,
        "szl_ervenytelen" : 7,
        "szl_ervenyes" : 975
      },
      "nemzetisegre" : {
        "vp_osszes" : 2,
        "megjelent" : 2,
        "szl_belyegtlen_urna" : 0,
        "szl_belyegzett_urna" : 2,
        "szl_elteres" : 0,
        "szl_ervenytelen" : 0,
        "szl_ervenyes" : 2
      },
      "tetelek" : [ {
        "sorsz" : 1,
        "tl_id" : 950,
        "szavazat" : 452,
        "szavazat_szaz" : 46.26
      }, {
        "sorsz" : 6,
        "tl_id" : 952,
        "szavazat" : 403,
        "szavazat_szaz" : 41.25
      }, {
        "sorsz" : 3,
        "tl_id" : 951,
        "szavazat" : 63,
        "szavazat_szaz" : 6.45
      }, {
        "sorsz" : 5,
        "tl_id" : 942,
        "szavazat" : 35,
        "szavazat_szaz" : 3.58
      }, {
        "sorsz" : 4,
        "tl_id" : 954,
        "szavazat" : 16,
        "szavazat_szaz" : 1.64
      }, {
        "sorsz" : 2,
        "tl_id" : 955,
        "szavazat" : 6,
        "szavazat_szaz" : 0.61
      }, {
        "tl_id" : 947,
        "nemzkod" : "5",
        "szavazat" : 2,
        "szavazat_szaz" : 0.2
      } ]
    }
  }, {
    "maz" : "14",
    "taz" : "034",
    "sorsz" : "002",
    "feldar" : 100.0,
    "egyeni_jkv" : {
      "allapot" : "3",
      "vp_osszes" : 1158,
      "szavazott_osszesen" : 919,
      "szavazott_osszesen_szaz" : 79.36,
      "vp_lakcim_szerint" : 1158,
      "megjel_lakcim_szerint" : 919,
      "megjel_lakcim_szerint_szaz" : 79.36,
      "szl_belyegtlen_urna" : 0,
      "szl_belyegzett_urna" : 921,
      "szl_elteres" : 2,
      "szl_ervenytelen" : 27,
      "szl_ervenytelen_szaz" : 2.93,
      "szl_ervenyes" : 894,
      "szl_ervenyes_szaz" : 97.07,
      "tetelek" : [ {
        "sorsz" : 5,
        "ej_id" : 71972,
        "szavazat" : 411,
        "szavazat_szaz" : 45.97
      }, {
        "sorsz" : 6,
        "ej_id" : 72007,
        "szavazat" : 403,
        "szavazat_szaz" : 45.08
      }, {
        "sorsz" : 4,
        "ej_id" : 72469,
        "szavazat" : 31,
        "szavazat_szaz" : 3.47
      }, {
        "sorsz" : 2,
        "ej_id" : 72384,
        "szavazat" : 30,
        "szavazat_szaz" : 3.36
      }, {
        "sorsz" : 7,
        "ej_id" : 72539,
        "szavazat" : 10,
        "szavazat_szaz" : 1.12
      }, {
        "sorsz" : 1,
        "ej_id" : 72547,
        "szavazat" : 6,
        "szavazat_szaz" : 0.67
      }, {
        "sorsz" : 3,
        "ej_id" : 72513,
        "szavazat" : 3,
        "szavazat_szaz" : 0.34
      } ]
    },
    "listas_jkv" : {
      "allapot" : "3",
      "vp_osszes" : 1158,
      "szavazott_osszesen" : 919,
      "szavazott_osszesen_szaz" : 79.36,
      "vp_lakcim_szerint" : 1158,
      "megjel_lakcim_szerint" : 919,
      "megjel_lakcim_szerint_szaz" : 79.36,
      "szl_belyegtlen_urna" : 1,
      "szl_belyegzett_urna" : 919,
      "szl_elteres" : 0,
      "szl_ervenytelen" : 14,
      "szl_ervenytelen_szaz" : 1.52,
      "szl_ervenyes" : 905,
      "szl_ervenyes_szaz" : 98.48,
      "partlistara" : {
        "vp_osszes" : 1154,
        "megjelent" : 915,
        "szl_belyegtlen_urna" : 1,
        "szl_belyegzett_urna" : 915,
        "szl_elteres" : 0,
        "szl_ervenytelen" : 13,
        "szl_ervenyes" : 902
      },
      "nemzetisegre" : {
        "vp_osszes" : 4,
        "megjelent" : 4,
        "szl_belyegtlen_urna" : 0,
        "szl_belyegzett_urna" : 4,
        "szl_elteres" : 0,
        "szl_ervenytelen" : 1,
        "szl_ervenyes" : 3
      },
      "tetelek" : [ {
        "sorsz" : 1,
        "tl_id" : 950,
        "szavazat" : 401,
        "szavazat_szaz" : 44.31
      }, {
        "sorsz" : 6,
        "tl_id" : 952,
        "szavazat" : 387,
        "szavazat_szaz" : 42.76
      }, {
        "sorsz" : 3,
        "tl_id" : 951,
        "szavazat" : 57,
        "szavazat_szaz" : 6.3
      }, {
        "sorsz" : 5,
        "tl_id" : 942,
        "szavazat" : 41,
        "szavazat_szaz" : 4.53
      }, {
        "sorsz" : 4,
        "tl_id" : 954,
        "szavazat" : 10,
        "szavazat_szaz" : 1.1
      }, {
        "sorsz" : 2,
        "tl_id" : 955,
        "szavazat" : 6,
        "szavazat_szaz" : 0.66
      }, {
        "tl_id" : 947,
        "nemzkod" : "5",
        "szavazat" : 3,
        "szavazat_szaz" : 0.33
      } ]
    }
  }, {
    "maz" : "14",
    "taz" : "034",
    "sorsz" : "003",
    "feldar" : 100.0,
    "egyeni_jkv" : {
      "allapot" : "3",
      "vp_osszes" : 1038,
      "szavazott_osszesen" : 829,
      "szavazott_osszesen_szaz" : 79.87,
      "vp_lakcim_szerint" : 1038,
      "megjel_lakcim_szerint" : 829,
      "megjel_lakcim_szerint_szaz" : 79.87,
      "szl_belyegtlen_urna" : 0,
      "szl_belyegzett_urna" : 829,
      "szl_elteres" : 0,
      "szl_ervenytelen" : 8,
      "szl_ervenytelen_szaz" : 0.97,
      "szl_ervenyes" : 821,
      "szl_ervenyes_szaz" : 99.03,
      "tetelek" : [ {
        "sorsz" : 5,
        "ej_id" : 71972,
        "szavazat" : 410,
        "szavazat_szaz" : 49.94
      }, {
        "sorsz" : 6,
        "ej_id" : 72007,
        "szavazat" : 321,
        "szavazat_szaz" : 39.1
      }, {
        "sorsz" : 2,
        "ej_id" : 72384,
        "szavazat" : 43,
        "szavazat_szaz" : 5.24
      }, {
        "sorsz" : 4,
        "ej_id" : 72469,
        "szavazat" : 24,
        "szavazat_szaz" : 2.92
      }, {
        "sorsz" : 7,
        "ej_id" : 72539,
        "szavazat" : 12,
        "szavazat_szaz" : 1.46
      }, {
        "sorsz" : 1,
        "ej_id" : 72547,
        "szavazat" : 8,
        "szavazat_szaz" : 0.97
      }, {
        "sorsz" : 3,
        "ej_id" : 72513,
        "szavazat" : 3,
        "szavazat_szaz" : 0.37
      } ]
    },
    "listas_jkv" : {
      "allapot" : "3",
      "vp_osszes" : 1038,
      "szavazott_osszesen" : 829,
      "szavazott_osszesen_szaz" : 79.87,
      "vp_lakcim_szerint" : 1038,
      "megjel_lakcim_szerint" : 829,
      "megjel_lakcim_szerint_szaz" : 79.87,
      "szl_belyegtlen_urna" : 1,
      "szl_belyegzett_urna" : 828,
      "szl_elteres" : 0,
      "szl_ervenytelen" : 3,
      "szl_ervenytelen_szaz" : 0.36,
      "szl_ervenyes" : 825,
      "szl_ervenyes_szaz" : 99.64,
      "partlistara" : {
        "vp_osszes" : 1037,
        "megjelent" : 828,
        "szl_belyegtlen_urna" : 1,
        "szl_belyegzett_urna" : 827,
        "szl_elteres" : -1,
        "szl_ervenytelen" : 3,
        "szl_ervenyes" : 824
      },
      "nemzetisegre" : {
        "vp_osszes" : 1,
        "megjelent" : 1,
        "szl_belyegtlen_urna" : 0,
        "szl_belyegzett_urna" : 1,
        "szl_elteres" : 0,
        "szl_ervenytelen" : 0,
        "szl_ervenyes" : 1
      },
      "tetelek" : [ {
        "sorsz" : 6,
        "tl_id" : 952,
        "szavazat" : 399,
        "szavazat_szaz" : 48.36
      }, {
        "sorsz" : 1,
        "tl_id" : 950,
        "szavazat" : 324,
        "szavazat_szaz" : 39.27
      }, {
        "sorsz" : 5,
        "tl_id" : 942,
        "szavazat" : 47,
        "szavazat_szaz" : 5.7
      }, {
        "sorsz" : 3,
        "tl_id" : 951,
        "szavazat" : 38,
        "szavazat_szaz" : 4.61
      }, {
        "sorsz" : 4,
        "tl_id" : 954,
        "szavazat" : 12,
        "szavazat_szaz" : 1.45
      }, {
        "sorsz" : 2,
        "tl_id" : 955,
        "szavazat" : 4,
        "szavazat_szaz" : 0.48
      }, {
        "tl_id" : 947,
        "nemzkod" : "5",
        "szavazat" : 1,
        "szavazat_szaz" : 0.12
      } ]
    }
  }, {
    "maz" : "14",
    "taz" : "034",
    "sorsz" : "004",
    "feldar" : 100.0,
    "egyeni_jkv" : {
      "allapot" : "3",
      "vp_osszes" : 998,
      "szavazott_osszesen" : 748,
      "szavazott_osszesen_szaz" : 74.95,
      "vp_lakcim_szerint" : 998,
      "megjel_lakcim_szerint" : 748,
      "megjel_lakcim_szerint_szaz" : 74.95,
      "szl_belyegtlen_urna" : 0,
      "szl_belyegzett_urna" : 749,
      "szl_elteres" : 1,
      "szl_ervenytelen" : 5,
      "szl_ervenytelen_szaz" : 0.67,
      "szl_ervenyes" : 744,
      "szl_ervenyes_szaz" : 99.33,
      "tetelek" : [ {
        "sorsz" : 5,
        "ej_id" : 71972,
        "szavazat" : 343,
        "szavazat_szaz" : 46.1
      }, {
        "sorsz" : 6,
        "ej_id" : 72007,
        "szavazat" : 323,
        "szavazat_szaz" : 43.41
      }, {
        "sorsz" : 2,
        "ej_id" : 72384,
        "szavazat" : 32,
        "szavazat_szaz" : 4.3
      }, {
        "sorsz" : 4,
        "ej_id" : 72469,
        "szavazat" : 26,
        "szavazat_szaz" : 3.49
      }, {
        "sorsz" : 7,
        "ej_id" : 72539,
        "szavazat" : 10,
        "szavazat_szaz" : 1.34
      }, {
        "sorsz" : 1,
        "ej_id" : 72547,
        "szavazat" : 7,
        "szavazat_szaz" : 0.94
      }, {
        "sorsz" : 3,
        "ej_id" : 72513,
        "szavazat" : 3,
        "szavazat_szaz" : 0.4
      } ]
    },
    "listas_jkv" : {
      "allapot" : "3",
      "vp_osszes" : 998,
      "szavazott_osszesen" : 748,
      "szavazott_osszesen_szaz" : 74.95,
      "vp_lakcim_szerint" : 998,
      "megjel_lakcim_szerint" : 748,
      "megjel_lakcim_szerint_szaz" : 74.95,
      "szl_belyegtlen_urna" : 0,
      "szl_belyegzett_urna" : 749,
      "szl_elteres" : 0,
      "szl_ervenytelen" : 4,
      "szl_ervenytelen_szaz" : 0.53,
      "szl_ervenyes" : 745,
      "szl_ervenyes_szaz" : 99.47,
      "partlistara" : {
        "vp_osszes" : 996,
        "megjelent" : 746,
        "szl_belyegtlen_urna" : 0,
        "szl_belyegzett_urna" : 747,
        "szl_elteres" : 1,
        "szl_ervenytelen" : 4,
        "szl_ervenyes" : 743
      },
      "nemzetisegre" : {
        "vp_osszes" : 2,
        "megjelent" : 2,
        "szl_belyegtlen_urna" : 0,
        "szl_belyegzett_urna" : 2,
        "szl_elteres" : 0,
        "szl_ervenytelen" : 0,
        "szl_ervenyes" : 2
      },
      "tetelek" : [ {
        "sorsz" : 1,
        "tl_id" : 950,
        "szavazat" : 332,
        "szavazat_szaz" : 44.56
      }, {
        "sorsz" : 6,
        "tl_id" : 952,
        "szavazat" : 322,
        "szavazat_szaz" : 43.22
      }, {
        "sorsz" : 3,
        "tl_id" : 951,
        "szavazat" : 37,
        "szavazat_szaz" : 4.97
      }, {
        "sorsz" : 5,
        "tl_id" : 942,
        "szavazat" : 37,
        "szavazat_szaz" : 4.97
      }, {
        "sorsz" : 4,
        "tl_id" : 954,
        "szavazat" : 10,
        "szavazat_szaz" : 1.34
      }, {
        "sorsz" : 2,
        "tl_id" : 955,
        "szavazat" : 5,
        "szavazat_szaz" : 0.67
      }, {
        "tl_id" : 947,
        "nemzkod" : "5",
        "szavazat" : 2,
        "szavazat_szaz" : 0.27
      } ]
    }
  }, {
    "maz" : "14",
    "taz" : "034",
    "sorsz" : "005",
    "feldar" : 100.0,
    "egyeni_jkv" : {
      "allapot" : "3",
      "vp_osszes" : 1002,
      "szavazott_osszesen" : 766,
      "szavazott_osszesen_szaz" : 76.45,
      "vp_lakcim_szerint" : 1002,
      "megjel_lakcim_szerint" : 766,
      "megjel_lakcim_szerint_szaz" : 76.45,
      "szl_belyegtlen_urna" : 0,
      "szl_belyegzett_urna" : 766,
      "szl_elteres" : 0,
      "szl_ervenytelen" : 8,
      "szl_ervenytelen_szaz" : 1.04,
      "szl_ervenyes" : 758,
      "szl_ervenyes_szaz" : 98.96,
      "tetelek" : [ {
        "sorsz" : 6,
        "ej_id" : 72007,
        "szavazat" : 357,
        "szavazat_szaz" : 47.1
      }, {
        "sorsz" : 5,
        "ej_id" : 71972,
        "szavazat" : 314,
        "szavazat_szaz" : 41.42
      }, {
        "sorsz" : 2,
        "ej_id" : 72384,
        "szavazat" : 34,
        "szavazat_szaz" : 4.49
      }, {
        "sorsz" : 4,
        "ej_id" : 72469,
        "szavazat" : 24,
        "szavazat_szaz" : 3.17
      }, {
        "sorsz" : 1,
        "ej_id" : 72547,
        "szavazat" : 17,
        "szavazat_szaz" : 2.24
      }, {
        "sorsz" : 7,
        "ej_id" : 72539,
        "szavazat" : 9,
        "szavazat_szaz" : 1.19
      }, {
        "sorsz" : 3,
        "ej_id" : 72513,
        "szavazat" : 3,
        "szavazat_szaz" : 0.4
      } ]
    },
    "listas_jkv" : {
      "allapot" : "3",
      "vp_osszes" : 1002,
      "szavazott_osszesen" : 766,
      "szavazott_osszesen_szaz" : 76.45,
      "vp_lakcim_szerint" : 1002,
      "megjel_lakcim_szerint" : 766,
      "megjel_lakcim_szerint_szaz" : 76.45,
      "szl_belyegtlen_urna" : 0,
      "szl_belyegzett_urna" : 766,
      "szl_elteres" : 0,
      "szl_ervenytelen" : 9,
      "szl_ervenytelen_szaz" : 1.17,
      "szl_ervenyes" : 757,
      "szl_ervenyes_szaz" : 98.83,
      "partlistara" : {
        "vp_osszes" : 999,
        "megjelent" : 764,
        "szl_belyegtlen_urna" : 0,
        "szl_belyegzett_urna" : 764,
        "szl_elteres" : 0,
        "szl_ervenytelen" : 9,
        "szl_ervenyes" : 755
      },
      "nemzetisegre" : {
        "vp_osszes" : 3,
        "megjelent" : 2,
        "szl_belyegtlen_urna" : 0,
        "szl_belyegzett_urna" : 2,
        "szl_elteres" : 0,
        "szl_ervenytelen" : 0,
        "szl_ervenyes" : 2
      },
      "tetelek" : [ {
        "sorsz" : 1,
        "tl_id" : 950,
        "szavazat" : 375,
        "szavazat_szaz" : 49.54
      }, {
        "sorsz" : 6,
        "tl_id" : 952,
        "szavazat" : 278,
        "szavazat_szaz" : 36.72
      }, {
        "sorsz" : 5,
        "tl_id" : 942,
        "szavazat" : 49,
        "szavazat_szaz" : 6.47
      }, {
        "sorsz" : 3,
        "tl_id" : 951,
        "szavazat" : 43,
        "szavazat_szaz" : 5.68
      }, {
        "sorsz" : 4,
        "tl_id" : 954,
        "szavazat" : 10,
        "szavazat_szaz" : 1.32
      }, {
        "sorsz" : 2,
        "tl_id" : 955,
        "szavazat" : 0,
        "szavazat_szaz" : 0.0
      }, {
        "tl_id" : 947,
        "nemzkod" : "5",
        "szavazat" : 2,
        "szavazat_szaz" : 0.26
      } ]
    }
  }, {
    "maz" : "14",
    "taz" : "034",
    "sorsz" : "006",
    "feldar" : 100.0,
    "egyeni_jkv" : {
      "allapot" : "3",
      "vp_osszes" : 911,
      "szavazott_osszesen" : 701,
      "szavazott_osszesen_szaz" : 76.95,
      "vp_lakcim_szerint" : 911,
      "megjel_lakcim_szerint" : 701,
      "megjel_lakcim_szerint_szaz" : 76.95,
      "szl_belyegtlen_urna" : 0,
      "szl_belyegzett_urna" : 700,
      "szl_elteres" : -1,
      "szl_ervenytelen" : 7,
      "szl_ervenytelen_szaz" : 1.0,
      "szl_ervenyes" : 693,
      "szl_ervenyes_szaz" : 99.0,
      "tetelek" : [ {
        "sorsz" : 5,
        "ej_id" : 71972,
        "szavazat" : 324,
        "szavazat_szaz" : 46.75
      }, {
        "sorsz" : 6,
        "ej_id" : 72007,
        "szavazat" : 292,
        "szavazat_szaz" : 42.14
      }, {
        "sorsz" : 2,
        "ej_id" : 72384,
        "szavazat" : 33,
        "szavazat_szaz" : 4.76
      }, {
        "sorsz" : 4,
        "ej_id" : 72469,
        "szavazat" : 23,
        "szavazat_szaz" : 3.32
      }, {
        "sorsz" : 7,
        "ej_id" : 72539,
        "szavazat" : 13,
        "szavazat_szaz" : 1.88
      }, {
        "sorsz" : 1,
        "ej_id" : 72547,
        "szavazat" : 5,
        "szavazat_szaz" : 0.72
      }, {
        "sorsz" : 3,
        "ej_id" : 72513,
        "szavazat" : 3,
        "szavazat_szaz" : 0.43
      } ]
    },
    "listas_jkv" : {
      "allapot" : "3",
      "vp_osszes" : 911,
      "szavazott_osszesen" : 701,
      "szavazott_osszesen_szaz" : 76.95,
      "vp_lakcim_szerint" : 911,
      "megjel_lakcim_szerint" : 701,
      "megjel_lakcim_szerint_szaz" : 76.95,
      "szl_belyegtlen_urna" : 1,
      "szl_belyegzett_urna" : 701,
      "szl_elteres" : 0,
      "szl_ervenytelen" : 5,
      "szl_ervenytelen_szaz" : 0.71,
      "szl_ervenyes" : 696,
      "szl_ervenyes_szaz" : 99.29,
      "partlistara" : {
        "vp_osszes" : 908,
        "megjelent" : 700,
        "szl_belyegtlen_urna" : 1,
        "szl_belyegzett_urna" : 700,
        "szl_elteres" : 0,
        "szl_ervenytelen" : 5,
        "szl_ervenyes" : 695
      },
      "nemzetisegre" : {
        "vp_osszes" : 3,
        "megjelent" : 1,
        "szl_belyegtlen_urna" : 0,
        "szl_belyegzett_urna" : 1,
        "szl_elteres" : 0,
        "szl_ervenytelen" : 0,
        "szl_ervenyes" : 1
      },
      "tetelek" : [ {
        "sorsz" : 1,
        "tl_id" : 950,
        "szavazat" : 307,
        "szavazat_szaz" : 44.11
      }, {
        "sorsz" : 6,
        "tl_id" : 952,
        "szavazat" : 306,
        "szavazat_szaz" : 43.97
      }, {
        "sorsz" : 5,
        "tl_id" : 942,
        "szavazat" : 36,
        "szavazat_szaz" : 5.17
      }, {
        "sorsz" : 3,
        "tl_id" : 951,
        "szavazat" : 32,
        "szavazat_szaz" : 4.6
      }, {
        "sorsz" : 4,
        "tl_id" : 954,
        "szavazat" : 13,
        "szavazat_szaz" : 1.87
      }, {
        "sorsz" : 2,
        "tl_id" : 955,
        "szavazat" : 1,
        "szavazat_szaz" : 0.14
      }, {
        "tl_id" : 943,
        "nemzkod" : "2",
        "szavazat" : 0,
        "szavazat_szaz" : 0.0
      }, {
        "tl_id" : 947,
        "nemzkod" : "5",
        "szavazat" : 1,
        "szavazat_szaz" : 0.14
      } ]
    }
  }, {
    "maz" : "14",
    "taz" : "034",
    "sorsz" : "007",
    "feldar" : 100.0,
    "egyeni_jkv" : {
      "allapot" : "3",
      "vp_osszes" : 1053,
      "szavazott_osszesen" : 818,
      "szavazott_osszesen_szaz" : 77.68,
      "vp_lakcim_szerint" : 1053,
      "megjel_lakcim_szerint" : 818,
      "megjel_lakcim_szerint_szaz" : 77.68,
      "szl_belyegtlen_urna" : 0,
      "szl_belyegzett_urna" : 818,
      "szl_elteres" : 0,
      "szl_ervenytelen" : 6,
      "szl_ervenytelen_szaz" : 0.73,
      "szl_ervenyes" : 812,
      "szl_ervenyes_szaz" : 99.27,
      "tetelek" : [ {
        "sorsz" : 5,
        "ej_id" : 71972,
        "szavazat" : 369,
        "szavazat_szaz" : 45.44
      }, {
        "sorsz" : 6,
        "ej_id" : 72007,
        "szavazat" : 341,
        "szavazat_szaz" : 42.0
      }, {
        "sorsz" : 2,
        "ej_id" : 72384,
        "szavazat" : 45,
        "szavazat_szaz" : 5.54
      }, {
        "sorsz" : 4,
        "ej_id" : 72469,
        "szavazat" : 29,
        "szavazat_szaz" : 3.57
      }, {
        "sorsz" : 7,
        "ej_id" : 72539,
        "szavazat" : 14,
        "szavazat_szaz" : 1.72
      }, {
        "sorsz" : 1,
        "ej_id" : 72547,
        "szavazat" : 11,
        "szavazat_szaz" : 1.35
      }, {
        "sorsz" : 3,
        "ej_id" : 72513,
        "szavazat" : 3,
        "szavazat_szaz" : 0.37
      } ]
    },
    "listas_jkv" : {
      "allapot" : "3",
      "vp_osszes" : 1053,
      "szavazott_osszesen" : 818,
      "szavazott_osszesen_szaz" : 77.68,
      "vp_lakcim_szerint" : 1053,
      "megjel_lakcim_szerint" : 818,
      "megjel_lakcim_szerint_szaz" : 77.68,
      "szl_belyegtlen_urna" : 0,
      "szl_belyegzett_urna" : 818,
      "szl_elteres" : 0,
      "szl_ervenytelen" : 9,
      "szl_ervenytelen_szaz" : 1.1,
      "szl_ervenyes" : 809,
      "szl_ervenyes_szaz" : 98.9,
      "partlistara" : {
        "vp_osszes" : 1050,
        "megjelent" : 816,
        "szl_belyegtlen_urna" : 0,
        "szl_belyegzett_urna" : 816,
        "szl_elteres" : 0,
        "szl_ervenytelen" : 9,
        "szl_ervenyes" : 807
      },
      "nemzetisegre" : {
        "vp_osszes" : 3,
        "megjelent" : 2,
        "szl_belyegtlen_urna" : 0,
        "szl_belyegzett_urna" : 2,
        "szl_elteres" : 0,
        "szl_ervenytelen" : 0,
        "szl_ervenyes" : 2
      },
      "tetelek" : [ {
        "sorsz" : 6,
        "tl_id" : 952,
        "szavazat" : 354,
        "szavazat_szaz" : 43.76
      }, {
        "sorsz" : 1,
        "tl_id" : 950,
        "szavazat" : 350,
        "szavazat_szaz" : 43.26
      }, {
        "sorsz" : 5,
        "tl_id" : 942,
        "szavazat" : 45,
        "szavazat_szaz" : 5.56
      }, {
        "sorsz" : 3,
        "tl_id" : 951,
        "szavazat" : 41,
        "szavazat_szaz" : 5.07
      }, {
        "sorsz" : 4,
        "tl_id" : 954,
        "szavazat" : 13,
        "szavazat_szaz" : 1.61
      }, {
        "sorsz" : 2,
        "tl_id" : 955,
        "szavazat" : 4,
        "szavazat_szaz" : 0.49
      }, {
        "tl_id" : 938,
        "nemzkod" : "10",
        "szavazat" : 1,
        "szavazat_szaz" : 0.12
      }, {
        "tl_id" : 947,
        "nemzkod" : "5",
        "szavazat" : 1,
        "szavazat_szaz" : 0.12
      } ]
    }
  }, {
    "maz" : "14",
    "taz" : "034",
    "sorsz" : "008",
    "feldar" : 100.0,
    "egyeni_jkv" : {
      "allapot" : "3",
      "vp_osszes" : 1135,
      "szavazott_osszesen" : 858,
      "szavazott_osszesen_szaz" : 75.59,
      "vp_lakcim_szerint" : 1135,
      "megjel_lakcim_szerint" : 858,
      "megjel_lakcim_szerint_szaz" : 75.59,
      "szl_belyegtlen_urna" : 0,
      "szl_belyegzett_urna" : 854,
      "szl_elteres" : -4,
      "szl_ervenytelen" : 12,
      "szl_ervenytelen_szaz" : 1.41,
      "szl_ervenyes" : 842,
      "szl_ervenyes_szaz" : 98.59,
      "tetelek" : [ {
        "sorsz" : 5,
        "ej_id" : 71972,
        "szavazat" : 387,
        "szavazat_szaz" : 45.96
      }, {
        "sorsz" : 6,
        "ej_id" : 72007,
        "szavazat" : 328,
        "szavazat_szaz" : 38.95
      }, {
        "sorsz" : 2,
        "ej_id" : 72384,
        "szavazat" : 50,
        "szavazat_szaz" : 5.94
      }, {
        "sorsz" : 4,
        "ej_id" : 72469,
        "szavazat" : 46,
        "szavazat_szaz" : 5.46
      }, {
        "sorsz" : 7,
        "ej_id" : 72539,
        "szavazat" : 18,
        "szavazat_szaz" : 2.14
      }, {
        "sorsz" : 1,
        "ej_id" : 72547,
        "szavazat" : 9,
        "szavazat_szaz" : 1.07
      }, {
        "sorsz" : 3,
        "ej_id" : 72513,
        "szavazat" : 4,
        "szavazat_szaz" : 0.48
      } ]
    },
    "listas_jkv" : {
      "allapot" : "3",
      "vp_osszes" : 1135,
      "szavazott_osszesen" : 858,
      "szavazott_osszesen_szaz" : 75.59,
      "vp_lakcim_szerint" : 1135,
      "megjel_lakcim_szerint" : 858,
      "megjel_lakcim_szerint_szaz" : 75.59,
      "szl_belyegtlen_urna" : 0,
      "szl_belyegzett_urna" : 861,
      "szl_elteres" : 0,
      "szl_ervenytelen" : 22,
      "szl_ervenytelen_szaz" : 2.56,
      "szl_ervenyes" : 839,
      "szl_ervenyes_szaz" : 97.44,
      "partlistara" : {
        "vp_osszes" : 1131,
        "megjelent" : 854,
        "szl_belyegtlen_urna" : 0,
        "szl_belyegzett_urna" : 857,
        "szl_elteres" : 3,
        "szl_ervenytelen" : 22,
        "szl_ervenyes" : 835
      },
      "nemzetisegre" : {
        "vp_osszes" : 4,
        "megjelent" : 4,
        "szl_belyegtlen_urna" : 0,
        "szl_belyegzett_urna" : 4,
        "szl_elteres" : 0,
        "szl_ervenytelen" : 0,
        "szl_ervenyes" : 4
      },
      "tetelek" : [ {
        "sorsz" : 6,
        "tl_id" : 952,
        "szavazat" : 378,
        "szavazat_szaz" : 45.05
      }, {
        "sorsz" : 1,
        "tl_id" : 950,
        "szavazat" : 344,
        "szavazat_szaz" : 41.0
      }, {
        "sorsz" : 3,
        "tl_id" : 951,
        "szavazat" : 54,
        "szavazat_szaz" : 6.44
      }, {
        "sorsz" : 5,
        "tl_id" : 942,
        "szavazat" : 53,
        "szavazat_szaz" : 6.32
      }, {
        "sorsz" : 4,
        "tl_id" : 954,
        "szavazat" : 6,
        "szavazat_szaz" : 0.72
      }, {
        "sorsz" : 2,
        "tl_id" : 955,
        "szavazat" : 0,
        "szavazat_szaz" : 0.0
      }, {
        "tl_id" : 947,
        "nemzkod" : "5",
        "szavazat" : 4,
        "szavazat_szaz" : 0.48
      } ]
    }
  }, {
    "maz" : "14",
    "taz" : "034",
    "sorsz" : "009",
    "feldar" : 100.0,
    "egyeni_jkv" : {
      "allapot" : "3",
      "vp_osszes" : 1114,
      "szavazott_osszesen" : 878,
      "szavazott_osszesen_szaz" : 78.82,
      "vp_lakcim_szerint" : 1114,
      "megjel_lakcim_szerint" : 878,
      "megjel_lakcim_szerint_szaz" : 78.82,
      "szl_belyegtlen_urna" : 0,
      "szl_belyegzett_urna" : 878,
      "szl_elteres" : 0,
      "szl_ervenytelen" : 4,
      "szl_ervenytelen_szaz" : 0.46,
      "szl_ervenyes" : 874,
      "szl_ervenyes_szaz" : 99.54,
      "tetelek" : [ {
        "sorsz" : 5,
        "ej_id" : 71972,
        "szavazat" : 431,
        "szavazat_szaz" : 49.31
      }, {
        "sorsz" : 6,
        "ej_id" : 72007,
        "szavazat" : 343,
        "szavazat_szaz" : 39.24
      }, {
        "sorsz" : 2,
        "ej_id" : 72384,
        "szavazat" : 46,
        "szavazat_szaz" : 5.26
      }, {
        "sorsz" : 4,
        "ej_id" : 72469,
        "szavazat" : 34,
        "szavazat_szaz" : 3.89
      }, {
        "sorsz" : 7,
        "ej_id" : 72539,
        "szavazat" : 13,
        "szavazat_szaz" : 1.49
      }, {
        "sorsz" : 3,
        "ej_id" : 72513,
        "szavazat" : 4,
        "szavazat_szaz" : 0.46
      }, {
        "sorsz" : 1,
        "ej_id" : 72547,
        "szavazat" : 3,
        "szavazat_szaz" : 0.34
      } ]
    },
    "listas_jkv" : {
      "allapot" : "3",
      "vp_osszes" : 1114,
      "szavazott_osszesen" : 878,
      "szavazott_osszesen_szaz" : 78.82,
      "vp_lakcim_szerint" : 1114,
      "megjel_lakcim_szerint" : 878,
      "megjel_lakcim_szerint_szaz" : 78.82,
      "szl_belyegtlen_urna" : 0,
      "szl_belyegzett_urna" : 878,
      "szl_elteres" : 0,
      "szl_ervenytelen" : 8,
      "szl_ervenytelen_szaz" : 0.91,
      "szl_ervenyes" : 870,
      "szl_ervenyes_szaz" : 99.09,
      "partlistara" : {
        "vp_osszes" : 1107,
        "megjelent" : 871,
        "szl_belyegtlen_urna" : 0,
        "szl_belyegzett_urna" : 871,
        "szl_elteres" : 0,
        "szl_ervenytelen" : 7,
        "szl_ervenyes" : 864
      },
      "nemzetisegre" : {
        "vp_osszes" : 7,
        "megjelent" : 7,
        "szl_belyegtlen_urna" : 0,
        "szl_belyegzett_urna" : 7,
        "szl_elteres" : 0,
        "szl_ervenytelen" : 1,
        "szl_ervenyes" : 6
      },
      "tetelek" : [ {
        "sorsz" : 6,
        "tl_id" : 952,
        "szavazat" : 402,
        "szavazat_szaz" : 46.21
      }, {
        "sorsz" : 1,
        "tl_id" : 950,
        "szavazat" : 349,
        "szavazat_szaz" : 40.11
      }, {
        "sorsz" : 3,
        "tl_id" : 951,
        "szavazat" : 48,
        "szavazat_szaz" : 5.52
      }, {
        "sorsz" : 5,
        "tl_id" : 942,
        "szavazat" : 40,
        "szavazat_szaz" : 4.6
      }, {
        "sorsz" : 4,
        "tl_id" : 954,
        "szavazat" : 16,
        "szavazat_szaz" : 1.84
      }, {
        "sorsz" : 2,
        "tl_id" : 955,
        "szavazat" : 9,
        "szavazat_szaz" : 1.03
      }, {
        "tl_id" : 947,
        "nemzkod" : "5",
        "szavazat" : 6,
        "szavazat_szaz" : 0.69
      } ]
    }
  }, {
    "maz" : "14",
    "taz" : "034",
    "sorsz" : "010",
    "feldar" : 0.0,
    "egyeni_jkv" : {
      "allapot" : "0",
      "vp_osszes" : 1100,
      "szavazott_osszesen" : 795,
      "szavazott_osszesen_szaz" : 72.27,
      "vp_lakcim_szerint" : 1100,
      "megjel_lakcim_szerint" : 795,
      "megjel_lakcim_szerint_szaz" : 72.27,
      "vp_atjel" : 1608,
      "vp_kulkepv" : 1044,
      "megjel_kuvi_atjel" : 0,
      "szl_belyegtlen_urna" : 0,
      "szl_belyegzett_urna" : 0,
      "szl_elteres" : 0,
      "szl_ervenytelen" : 0,
      "szl_ervenytelen_szaz" : 0.0,
      "szl_ervenyes" : 0,
      "szl_ervenyes_szaz" : 0.0,
      "tetelek" : [ {
        "sorsz" : 1,
        "ej_id" : 72547,
        "szavazat" : 0,
        "szavazat_szaz" : 0.0
      }, {
        "sorsz" : 2,
        "ej_id" : 72384,
        "szavazat" : 0,
        "szavazat_szaz" : 0.0
      }, {
        "sorsz" : 3,
        "ej_id" : 72513,
        "szavazat" : 0,
        "szavazat_szaz" : 0.0
      }, {
        "sorsz" : 4,
        "ej_id" : 72469,
        "szavazat" : 0,
        "szavazat_szaz" : 0.0
      }, {
        "sorsz" : 5,
        "ej_id" : 71972,
        "szavazat" : 0,
        "szavazat_szaz" : 0.0
      }, {
        "sorsz" : 6,
        "ej_id" : 72007,
        "szavazat" : 0,
        "szavazat_szaz" : 0.0
      }, {
        "sorsz" : 7,
        "ej_id" : 72539,
        "szavazat" : 0,
        "szavazat_szaz" : 0.0
      } ]
    },
    "listas_jkv" : {
      "allapot" : "0",
      "vp_osszes" : 1100,
      "szavazott_osszesen" : 796,
      "szavazott_osszesen_szaz" : 72.36,
      "vp_lakcim_szerint" : 1100,
      "megjel_lakcim_szerint" : 796,
      "megjel_lakcim_szerint_szaz" : 72.36,
      "vp_atjel" : 1608,
      "vp_kulkepv" : 1044,
      "megjel_kuvi_atjel" : 0,
      "szl_belyegtlen_urna" : 0,
      "szl_belyegzett_urna" : 0,
      "szl_elteres" : 0,
      "szl_ervenytelen" : 0,
      "szl_ervenytelen_szaz" : 0.0,
      "szl_ervenyes" : 0,
      "szl_ervenyes_szaz" : 0.0,
      "partlistara" : {
        "vp_osszes" : 3748,
        "megjelent" : 0,
        "szl_belyegtlen_urna" : 0,
        "szl_belyegzett_urna" : 0,
        "szl_elteres" : 0,
        "szl_ervenytelen" : 0,
        "szl_ervenyes" : 0
      },
      "nemzetisegre" : {
        "vp_osszes" : 4,
        "megjelent" : 0,
        "szl_belyegtlen_urna" : 0,
        "szl_belyegzett_urna" : 0,
        "szl_elteres" : 0,
        "szl_ervenytelen" : 0,
        "szl_ervenyes" : 0
      },
      "tetelek" : [ {
        "sorsz" : 1,
        "tl_id" : 950,
        "szavazat" : 0,
        "szavazat_szaz" : 0.0
      }, {
        "sorsz" : 2,
        "tl_id" : 955,
        "szavazat" : 0,
        "szavazat_szaz" : 0.0
      }, {
        "sorsz" : 3,
        "tl_id" : 951,
        "szavazat" : 0,
        "szavazat_szaz" : 0.0
      }, {
        "sorsz" : 4,
        "tl_id" : 954,
        "szavazat" : 0,
        "szavazat_szaz" : 0.0
      }, {
        "sorsz" : 5,
        "tl_id" : 942,
        "szavazat" : 0,
        "szavazat_szaz" : 0.0
      }, {
        "sorsz" : 6,
        "tl_id" : 952,
        "szavazat" : 0,
        "szavazat_szaz" : 0.0
      }, {
        "tl_id" : 949,
        "nemzkod" : "11",
        "szavazat" : 0,
        "szavazat_szaz" : 0.0
      }, {
        "tl_id" : 944,
        "nemzkod" : "13",
        "szavazat" : 0,
        "szavazat_szaz" : 0.0
      }, {
        "tl_id" : 947,
        "nemzkod" : "5",
        "szavazat" : 0,
        "szavazat_szaz" : 0.0
      } ]
    }
  }, {
    "maz" : "14",
    "taz" : "034",
    "sorsz" : "011",
    "feldar" : 100.0,
    "egyeni_jkv" : {
      "allapot" : "3",
      "vp_osszes" : 821,
      "szavazott_osszesen" : 562,
      "szavazott_osszesen_szaz" : 68.45,
      "vp_lakcim_szerint" : 821,
      "megjel_lakcim_szerint" : 562,
      "megjel_lakcim_szerint_szaz" : 68.45,
      "vp_atjel" : 904,
      "megjel_atjel" : 879,
      "megjel_atjel_szaz" : 97.23,
      "szl_belyegtlen_urna" : 0,
      "szl_belyegzett_urna" : 563,
      "szl_elteres" : 1,
      "szl_ervenytelen" : 12,
      "szl_ervenytelen_szaz" : 2.13,
      "szl_ervenyes" : 551,
      "szl_ervenyes_szaz" : 97.87,
      "tetelek" : [ {
        "sorsz" : 5,
        "ej_id" : 71972,
        "szavazat" : 295,
        "szavazat_szaz" : 53.54
      }, {
        "sorsz" : 6,
        "ej_id" : 72007,
        "szavazat" : 209,
        "szavazat_szaz" : 37.93
      }, {
        "sorsz" : 4,
        "ej_id" : 72469,
        "szavazat" : 16,
        "szavazat_szaz" : 2.9
      }, {
        "sorsz" : 2,
        "ej_id" : 72384,
        "szavazat" : 15,
        "szavazat_szaz" : 2.72
      }, {
        "sorsz" : 7,
        "ej_id" : 72539,
        "szavazat" : 7,
        "szavazat_szaz" : 1.27
      }, {
        "sorsz" : 1,
        "ej_id" : 72547,
        "szavazat" : 5,
        "szavazat_szaz" : 0.91
      }, {
        "sorsz" : 3,
        "ej_id" : 72513,
        "szavazat" : 4,
        "szavazat_szaz" : 0.73
      } ]
    },
    "listas_jkv" : {
      "allapot" : "3",
      "vp_osszes" : 821,
      "szavazott_osszesen" : 562,
      "szavazott_osszesen_szaz" : 68.45,
      "vp_lakcim_szerint" : 821,
      "megjel_lakcim_szerint" : 562,
      "megjel_lakcim_szerint_szaz" : 68.45,
      "vp_atjel" : 904,
      "megjel_atjel" : 879,
      "megjel_atjel_szaz" : 97.23,
      "szl_belyegtlen_urna" : 1,
      "szl_belyegzett_urna" : 563,
      "szl_elteres" : 0,
      "szl_ervenytelen" : 15,
      "szl_ervenytelen_szaz" : 2.66,
      "szl_ervenyes" : 548,
      "szl_ervenyes_szaz" : 97.34,
      "partlistara" : {
        "vp_osszes" : 820,
        "megjelent" : 561,
        "szl_belyegtlen_urna" : 1,
        "szl_belyegzett_urna" : 562,
        "szl_elteres" : 1,
        "szl_ervenytelen" : 15,
        "szl_ervenyes" : 547
      },
      "nemzetisegre" : {
        "vp_osszes" : 1,
        "megjelent" : 1,
        "szl_belyegtlen_urna" : 0,
        "szl_belyegzett_urna" : 1,
        "szl_elteres" : 0,
        "szl_ervenytelen" : 0,
        "szl_ervenyes" : 1
      },
      "tetelek" : [ {
        "sorsz" : 6,
        "tl_id" : 952,
        "szavazat" : 284,
        "szavazat_szaz" : 51.82
      }, {
        "sorsz" : 1,
        "tl_id" : 950,
        "szavazat" : 204,
        "szavazat_szaz" : 37.23
      }, {
        "sorsz" : 3,
        "tl_id" : 951,
        "szavazat" : 23,
        "szavazat_szaz" : 4.2
      }, {
        "sorsz" : 5,
        "tl_id" : 942,
        "szavazat" : 22,
        "szavazat_szaz" : 4.01
      }, {
        "sorsz" : 4,
        "tl_id" : 954,
        "szavazat" : 8,
        "szavazat_szaz" : 1.46
      }, {
        "sorsz" : 2,
        "tl_id" : 955,
        "szavazat" : 6,
        "szavazat_szaz" : 1.09
      }, {
        "tl_id" : 947,
        "nemzkod" : "5",
        "szavazat" : 1,
        "szavazat_szaz" : 0.18
      } ]
    }
  }, {
    "maz" : "14",
    "taz" : "034",
    "sorsz" : "012",
    "feldar" : 100.0,
    "egyeni_jkv" : {
      "allapot" : "3",
      "vp_osszes" : 1086,
      "szavazott_osszesen" : 772,
      "szavazott_osszesen_szaz" : 71.09,
      "vp_lakcim_szerint" : 1086,
      "megjel_lakcim_szerint" : 772,
      "megjel_lakcim_szerint_szaz" : 71.09,
      "szl_belyegtlen_urna" : 0,
      "szl_belyegzett_urna" : 772,
      "szl_elteres" : 0,
      "szl_ervenytelen" : 6,
      "szl_ervenytelen_szaz" : 0.78,
      "szl_ervenyes" : 766,
      "szl_ervenyes_szaz" : 99.22,
      "tetelek" : [ {
        "sorsz" : 5,
        "ej_id" : 71972,
        "szavazat" : 382,
        "szavazat_szaz" : 49.87
      }, {
        "sorsz" : 6,
        "ej_id" : 72007,
        "szavazat" : 292,
        "szavazat_szaz" : 38.12
      }, {
        "sorsz" : 2,
        "ej_id" : 72384,
        "szavazat" : 37,
        "szavazat_szaz" : 4.83
      }, {
        "sorsz" : 4,
        "ej_id" : 72469,
        "szavazat" : 24,
        "szavazat_szaz" : 3.13
      }, {
        "sorsz" : 7,
        "ej_id" : 72539,
        "szavazat" : 15,
        "szavazat_szaz" : 1.96
      }, {
        "sorsz" : 1,
        "ej_id" : 72547,
        "szavazat" : 11,
        "szavazat_szaz" : 1.44
      }, {
        "sorsz" : 3,
        "ej_id" : 72513,
        "szavazat" : 5,
        "szavazat_szaz" : 0.65
      } ]
    },
    "listas_jkv" : {
      "allapot" : "3",
      "vp_osszes" : 1086,
      "szavazott_osszesen" : 772,
      "szavazott_osszesen_szaz" : 71.09,
      "vp_lakcim_szerint" : 1086,
      "megjel_lakcim_szerint" : 772,
      "megjel_lakcim_szerint_szaz" : 71.09,
      "szl_belyegtlen_urna" : 0,
      "szl_belyegzett_urna" : 772,
      "szl_elteres" : 0,
      "szl_ervenytelen" : 5,
      "szl_ervenytelen_szaz" : 0.65,
      "szl_ervenyes" : 767,
      "szl_ervenyes_szaz" : 99.35,
      "partlistara" : {
        "vp_osszes" : 1084,
        "megjelent" : 771,
        "szl_belyegtlen_urna" : 0,
        "szl_belyegzett_urna" : 771,
        "szl_elteres" : 0,
        "szl_ervenytelen" : 5,
        "szl_ervenyes" : 766
      },
      "nemzetisegre" : {
        "vp_osszes" : 2,
        "megjelent" : 1,
        "szl_belyegtlen_urna" : 0,
        "szl_belyegzett_urna" : 1,
        "szl_elteres" : 0,
        "szl_ervenytelen" : 0,
        "szl_ervenyes" : 1
      },
      "tetelek" : [ {
        "sorsz" : 6,
        "tl_id" : 952,
        "szavazat" : 364,
        "szavazat_szaz" : 47.46
      }, {
        "sorsz" : 1,
        "tl_id" : 950,
        "szavazat" : 314,
        "szavazat_szaz" : 40.94
      }, {
        "sorsz" : 5,
        "tl_id" : 942,
        "szavazat" : 43,
        "szavazat_szaz" : 5.61
      }, {
        "sorsz" : 3,
        "tl_id" : 951,
        "szavazat" : 30,
        "szavazat_szaz" : 3.91
      }, {
        "sorsz" : 4,
        "tl_id" : 954,
        "szavazat" : 10,
        "szavazat_szaz" : 1.3
      }, {
        "sorsz" : 2,
        "tl_id" : 955,
        "szavazat" : 5,
        "szavazat_szaz" : 0.65
      }, {
        "tl_id" : 947,
        "nemzkod" : "5",
        "szavazat" : 1,
        "szavazat_szaz" : 0.13
      } ]
    }
  }, {
    "maz" : "14",
    "taz" : "034",
    "sorsz" : "013",
    "feldar" : 100.0,
    "egyeni_jkv" : {
      "allapot" : "3",
      "vp_osszes" : 957,
      "szavazott_osszesen" : 821,
      "szavazott_osszesen_szaz" : 85.79,
      "vp_lakcim_szerint" : 957,
      "megjel_lakcim_szerint" : 821,
      "megjel_lakcim_szerint_szaz" : 85.79,
      "szl_belyegtlen_urna" : 0,
      "szl_belyegzett_urna" : 821,
      "szl_elteres" : 0,
      "szl_ervenytelen" : 3,
      "szl_ervenytelen_szaz" : 0.37,
      "szl_ervenyes" : 818,
      "szl_ervenyes_szaz" : 99.63,
      "tetelek" : [ {
        "sorsz" : 6,
        "ej_id" : 72007,
        "szavazat" : 396,
        "szavazat_szaz" : 48.41
      }, {
        "sorsz" : 5,
        "ej_id" : 71972,
        "szavazat" : 340,
        "szavazat_szaz" : 41.56
      }, {
        "sorsz" : 2,
        "ej_id" : 72384,
        "szavazat" : 36,
        "szavazat_szaz" : 4.4
      }, {
        "sorsz" : 4,
        "ej_id" : 72469,
        "szavazat" : 36,
        "szavazat_szaz" : 4.4
      }, {
        "sorsz" : 7,
        "ej_id" : 72539,
        "szavazat" : 5,
        "szavazat_szaz" : 0.61
      }, {
        "sorsz" : 3,
        "ej_id" : 72513,
        "szavazat" : 3,
        "szavazat_szaz" : 0.37
      }, {
        "sorsz" : 1,
        "ej_id" : 72547,
        "szavazat" : 2,
        "szavazat_szaz" : 0.24
      } ]
    },
    "listas_jkv" : {
      "allapot" : "3",
      "vp_osszes" : 957,
      "szavazott_osszesen" : 821,
      "szavazott_osszesen_szaz" : 85.79,
      "vp_lakcim_szerint" : 957,
      "megjel_lakcim_szerint" : 821,
      "megjel_lakcim_szerint_szaz" : 85.79,
      "szl_belyegtlen_urna" : 0,
      "szl_belyegzett_urna" : 821,
      "szl_elteres" : 0,
      "szl_ervenytelen" : 3,
      "szl_ervenytelen_szaz" : 0.37,
      "szl_ervenyes" : 818,
      "szl_ervenyes_szaz" : 99.63,
      "partlistara" : {
        "vp_osszes" : 948,
        "megjelent" : 813,
        "szl_belyegtlen_urna" : 0,
        "szl_belyegzett_urna" : 813,
        "szl_elteres" : 0,
        "szl_ervenytelen" : 3,
        "szl_ervenyes" : 810
      },
      "nemzetisegre" : {
        "vp_osszes" : 9,
        "megjelent" : 8,
        "szl_belyegtlen_urna" : 0,
        "szl_belyegzett_urna" : 8,
        "szl_elteres" : 0,
        "szl_ervenytelen" : 0,
        "szl_ervenyes" : 8
      },
      "tetelek" : [ {
        "sorsz" : 1,
        "tl_id" : 950,
        "szavazat" : 408,
        "szavazat_szaz" : 49.88
      }, {
        "sorsz" : 6,
        "tl_id" : 952,
        "szavazat" : 309,
        "szavazat_szaz" : 37.78
      }, {
        "sorsz" : 5,
        "tl_id" : 942,
        "szavazat" : 45,
        "szavazat_szaz" : 5.5
      }, {
        "sorsz" : 3,
        "tl_id" : 951,
        "szavazat" : 42,
        "szavazat_szaz" : 5.13
      }, {
        "sorsz" : 2,
        "tl_id" : 955,
        "szavazat" : 4,
        "szavazat_szaz" : 0.49
      }, {
        "sorsz" : 4,
        "tl_id" : 954,
        "szavazat" : 2,
        "szavazat_szaz" : 0.24
      }, {
        "tl_id" : 947,
        "nemzkod" : "5",
        "szavazat" : 7,
        "szavazat_szaz" : 0.86
      }, {
        "tl_id" : 945,
        "nemzkod" : "6",
        "szavazat" : 1,
        "szavazat_szaz" : 0.12
      } ]
    }
  }, {
    "maz" : "14",
    "taz" : "034",
    "sorsz" : "014",
    "feldar" : 100.0,
    "egyeni_jkv" : {
      "allapot" : "3",
      "vp_osszes" : 951,
      "szavazott_osszesen" : 770,
      "szavazott_osszesen_szaz" : 80.97,
      "vp_lakcim_szerint" : 951,
      "megjel_lakcim_szerint" : 770,
      "megjel_lakcim_szerint_szaz" : 80.97,
      "szl_belyegtlen_urna" : 0,
      "szl_belyegzett_urna" : 770,
      "szl_elteres" : 0,
      "szl_ervenytelen" : 7,
      "szl_ervenytelen_szaz" : 0.91,
      "szl_ervenyes" : 763,
      "szl_ervenyes_szaz" : 99.09,
      "tetelek" : [ {
        "sorsz" : 6,
        "ej_id" : 72007,
        "szavazat" : 399,
        "szavazat_szaz" : 52.29
      }, {
        "sorsz" : 5,
        "ej_id" : 71972,
        "szavazat" : 268,
        "szavazat_szaz" : 35.12
      }, {
        "sorsz" : 4,
        "ej_id" : 72469,
        "szavazat" : 32,
        "szavazat_szaz" : 4.19
      }, {
        "sorsz" : 2,
        "ej_id" : 72384,
        "szavazat" : 31,
        "szavazat_szaz" : 4.06
      }, {
        "sorsz" : 7,
        "ej_id" : 72539,
        "szavazat" : 15,
        "szavazat_szaz" : 1.97
      }, {
        "sorsz" : 1,
        "ej_id" : 72547,
        "szavazat" : 14,
        "szavazat_szaz" : 1.83
      }, {
        "sorsz" : 3,
        "ej_id" : 72513,
        "szavazat" : 4,
        "szavazat_szaz" : 0.52
      } ]
    },
    "listas_jkv" : {
      "allapot" : "3",
      "vp_osszes" : 951,
      "szavazott_osszesen" : 770,
      "szavazott_osszesen_szaz" : 80.97,
      "vp_lakcim_szerint" : 951,
      "megjel_lakcim_szerint" : 770,
      "megjel_lakcim_szerint_szaz" : 80.97,
      "szl_belyegtlen_urna" : 0,
      "szl_belyegzett_urna" : 770,
      "szl_elteres" : 0,
      "szl_ervenytelen" : 5,
      "szl_ervenytelen_szaz" : 0.65,
      "szl_ervenyes" : 765,
      "szl_ervenyes_szaz" : 99.35,
      "partlistara" : {
        "vp_osszes" : 944,
        "megjelent" : 764,
        "szl_belyegtlen_urna" : 0,
        "szl_belyegzett_urna" : 764,
        "szl_elteres" : 0,
        "szl_ervenytelen" : 5,
        "szl_ervenyes" : 759
      },
      "nemzetisegre" : {
        "vp_osszes" : 7,
        "megjelent" : 6,
        "szl_belyegtlen_urna" : 0,
        "szl_belyegzett_urna" : 6,
        "szl_elteres" : 0,
        "szl_ervenytelen" : 0,
        "szl_ervenyes" : 6
      },
      "tetelek" : [ {
        "sorsz" : 1,
        "tl_id" : 950,
        "szavazat" : 417,
        "szavazat_szaz" : 54.51
      }, {
        "sorsz" : 6,
        "tl_id" : 952,
        "szavazat" : 230,
        "szavazat_szaz" : 30.07
      }, {
        "sorsz" : 3,
        "tl_id" : 951,
        "szavazat" : 53,
        "szavazat_szaz" : 6.93
      }, {
        "sorsz" : 5,
        "tl_id" : 942,
        "szavazat" : 32,
        "szavazat_szaz" : 4.18
      }, {
        "sorsz" : 4,
        "tl_id" : 954,
        "szavazat" : 21,
        "szavazat_szaz" : 2.75
      }, {
        "sorsz" : 2,
        "tl_id" : 955,
        "szavazat" : 6,
        "szavazat_szaz" : 0.78
      }, {
        "tl_id" : 938,
        "nemzkod" : "10",
        "szavazat" : 1,
        "szavazat_szaz" : 0.13
      }, {
        "tl_id" : 947,
        "nemzkod" : "5",
        "szavazat" : 5,
        "szavazat_szaz" : 0.65
      }, {
        "tl_id" : 937,
        "nemzkod" : "9",
        "szavazat" : 0,
        "szavazat_szaz" : 0.0
      } ]
    }
  }, {
    "maz" : "14",
    "taz" : "034",
    "sorsz" : "015",
    "feldar" : 100.0,
    "egyeni_jkv" : {
      "allapot" : "3",
      "vp_osszes" : 1011,
      "szavazott_osszesen" : 837,
      "szavazott_osszesen_szaz" : 82.79,
      "vp_lakcim_szerint" : 1011,
      "megjel_lakcim_szerint" : 837,
      "megjel_lakcim_szerint_szaz" : 82.79,
      "szl_belyegtlen_urna" : 0,
      "szl_belyegzett_urna" : 820,
      "szl_elteres" : -17,
      "szl_ervenytelen" : 4,
      "szl_ervenytelen_szaz" : 0.49,
      "szl_ervenyes" : 816,
      "szl_ervenyes_szaz" : 99.51,
      "tetelek" : [ {
        "sorsz" : 5,
        "ej_id" : 71972,
        "szavazat" : 414,
        "szavazat_szaz" : 50.74
      }, {
        "sorsz" : 6,
        "ej_id" : 72007,
        "szavazat" : 335,
        "szavazat_szaz" : 41.05
      }, {
        "sorsz" : 2,
        "ej_id" : 72384,
        "szavazat" : 24,
        "szavazat_szaz" : 2.94
      }, {
        "sorsz" : 4,
        "ej_id" : 72469,
        "szavazat" : 19,
        "szavazat_szaz" : 2.33
      }, {
        "sorsz" : 1,
        "ej_id" : 72547,
        "szavazat" : 14,
        "szavazat_szaz" : 1.72
      }, {
        "sorsz" : 7,
        "ej_id" : 72539,
        "szavazat" : 7,
        "szavazat_szaz" : 0.86
      }, {
        "sorsz" : 3,
        "ej_id" : 72513,
        "szavazat" : 3,
        "szavazat_szaz" : 0.37
      } ]
    },
    "listas_jkv" : {
      "allapot" : "3",
      "vp_osszes" : 1011,
      "szavazott_osszesen" : 837,
      "szavazott_osszesen_szaz" : 82.79,
      "vp_lakcim_szerint" : 1011,
      "megjel_lakcim_szerint" : 837,
      "megjel_lakcim_szerint_szaz" : 82.79,
      "szl_belyegtlen_urna" : 0,
      "szl_belyegzett_urna" : 824,
      "szl_elteres" : 0,
      "szl_ervenytelen" : 9,
      "szl_ervenytelen_szaz" : 1.09,
      "szl_ervenyes" : 815,
      "szl_ervenyes_szaz" : 98.91,
      "partlistara" : {
        "vp_osszes" : 998,
        "megjelent" : 827,
        "szl_belyegtlen_urna" : 0,
        "szl_belyegzett_urna" : 814,
        "szl_elteres" : -13,
        "szl_ervenytelen" : 8,
        "szl_ervenyes" : 806
      },
      "nemzetisegre" : {
        "vp_osszes" : 13,
        "megjelent" : 10,
        "szl_belyegtlen_urna" : 0,
        "szl_belyegzett_urna" : 10,
        "szl_elteres" : 0,
        "szl_ervenytelen" : 1,
        "szl_ervenyes" : 9
      },
      "tetelek" : [ {
        "sorsz" : 6,
        "tl_id" : 952,
        "szavazat" : 381,
        "szavazat_szaz" : 46.75
      }, {
        "sorsz" : 1,
        "tl_id" : 950,
        "szavazat" : 346,
        "szavazat_szaz" : 42.45
      }, {
        "sorsz" : 3,
        "tl_id" : 951,
        "szavazat" : 35,
        "szavazat_szaz" : 4.29
      }, {
        "sorsz" : 5,
        "tl_id" : 942,
        "szavazat" : 31,
        "szavazat_szaz" : 3.8
      }, {
        "sorsz" : 4,
        "tl_id" : 954,
        "szavazat" : 9,
        "szavazat_szaz" : 1.1
      }, {
        "sorsz" : 2,
        "tl_id" : 955,
        "szavazat" : 4,
        "szavazat_szaz" : 0.49
      }, {
        "tl_id" : 943,
        "nemzkod" : "2",
        "szavazat" : 1,
        "szavazat_szaz" : 0.12
      }, {
        "tl_id" : 947,
        "nemzkod" : "5",
        "szavazat" : 8,
        "szavazat_szaz" : 0.98
      } ]
    }
  }, {
    "maz" : "14",
    "taz" : "034",
    "sorsz" : "016",
    "feldar" : 100.0,
    "egyeni_jkv" : {
      "allapot" : "3",
      "vp_osszes" : 1115,
      "szavazott_osszesen" : 892,
      "szavazott_osszesen_szaz" : 80.0,
      "vp_lakcim_szerint" : 1115,
      "megjel_lakcim_szerint" : 892,
      "megjel_lakcim_szerint_szaz" : 80.0,
      "szl_belyegtlen_urna" : 0,
      "szl_belyegzett_urna" : 894,
      "szl_elteres" : 2,
      "szl_ervenytelen" : 21,
      "szl_ervenytelen_szaz" : 2.35,
      "szl_ervenyes" : 873,
      "szl_ervenyes_szaz" : 97.65,
      "tetelek" : [ {
        "sorsz" : 5,
        "ej_id" : 71972,
        "szavazat" : 423,
        "szavazat_szaz" : 48.45
      }, {
        "sorsz" : 6,
        "ej_id" : 72007,
        "szavazat" : 375,
        "szavazat_szaz" : 42.96
      }, {
        "sorsz" : 4,
        "ej_id" : 72469,
        "szavazat" : 32,
        "szavazat_szaz" : 3.67
      }, {
        "sorsz" : 2,
        "ej_id" : 72384,
        "szavazat" : 28,
        "szavazat_szaz" : 3.21
      }, {
        "sorsz" : 1,
        "ej_id" : 72547,
        "szavazat" : 10,
        "szavazat_szaz" : 1.15
      }, {
        "sorsz" : 7,
        "ej_id" : 72539,
        "szavazat" : 5,
        "szavazat_szaz" : 0.57
      }, {
        "sorsz" : 3,
        "ej_id" : 72513,
        "szavazat" : 0,
        "szavazat_szaz" : 0.0
      } ]
    },
    "listas_jkv" : {
      "allapot" : "3",
      "vp_osszes" : 1115,
      "szavazott_osszesen" : 892,
      "szavazott_osszesen_szaz" : 80.0,
      "vp_lakcim_szerint" : 1115,
      "megjel_lakcim_szerint" : 892,
      "megjel_lakcim_szerint_szaz" : 80.0,
      "szl_belyegtlen_urna" : 0,
      "szl_belyegzett_urna" : 890,
      "szl_elteres" : 0,
      "szl_ervenytelen" : 9,
      "szl_ervenytelen_szaz" : 1.01,
      "szl_ervenyes" : 881,
      "szl_ervenyes_szaz" : 98.99,
      "partlistara" : {
        "vp_osszes" : 1102,
        "megjelent" : 880,
        "szl_belyegtlen_urna" : 0,
        "szl_belyegzett_urna" : 879,
        "szl_elteres" : -1,
        "szl_ervenytelen" : 8,
        "szl_ervenyes" : 871
      },
      "nemzetisegre" : {
        "vp_osszes" : 13,
        "megjelent" : 12,
        "szl_belyegtlen_urna" : 0,
        "szl_belyegzett_urna" : 11,
        "szl_elteres" : 0,
        "szl_ervenytelen" : 1,
        "szl_ervenyes" : 10
      },
      "tetelek" : [ {
        "sorsz" : 6,
        "tl_id" : 952,
        "szavazat" : 393,
        "szavazat_szaz" : 44.61
      }, {
        "sorsz" : 1,
        "tl_id" : 950,
        "szavazat" : 387,
        "szavazat_szaz" : 43.93
      }, {
        "sorsz" : 3,
        "tl_id" : 951,
        "szavazat" : 42,
        "szavazat_szaz" : 4.77
      }, {
        "sorsz" : 5,
        "tl_id" : 942,
        "szavazat" : 36,
        "szavazat_szaz" : 4.09
      }, {
        "sorsz" : 4,
        "tl_id" : 954,
        "szavazat" : 10,
        "szavazat_szaz" : 1.14
      }, {
        "sorsz" : 2,
        "tl_id" : 955,
        "szavazat" : 3,
        "szavazat_szaz" : 0.34
      }, {
        "tl_id" : 947,
        "nemzkod" : "5",
        "szavazat" : 10,
        "szavazat_szaz" : 1.14
      } ]
    }
  }, {
    "maz" : "14",
    "taz" : "034",
    "sorsz" : "017",
    "feldar" : 100.0,
    "egyeni_jkv" : {
      "allapot" : "3",
      "vp_osszes" : 978,
      "szavazott_osszesen" : 766,
      "szavazott_osszesen_szaz" : 78.32,
      "vp_lakcim_szerint" : 978,
      "megjel_lakcim_szerint" : 766,
      "megjel_lakcim_szerint_szaz" : 78.32,
      "szl_belyegtlen_urna" : 1,
      "szl_belyegzett_urna" : 764,
      "szl_elteres" : -2,
      "szl_ervenytelen" : 7,
      "szl_ervenytelen_szaz" : 0.92,
      "szl_ervenyes" : 757,
      "szl_ervenyes_szaz" : 99.08,
      "tetelek" : [ {
        "sorsz" : 5,
        "ej_id" : 71972,
        "szavazat" : 394,
        "szavazat_szaz" : 52.05
      }, {
        "sorsz" : 6,
        "ej_id" : 72007,
        "szavazat" : 274,
        "szavazat_szaz" : 36.2
      }, {
        "sorsz" : 2,
        "ej_id" : 72384,
        "szavazat" : 31,
        "szavazat_szaz" : 4.1
      }, {
        "sorsz" : 4,
        "ej_id" : 72469,
        "szavazat" : 29,
        "szavazat_szaz" : 3.83
      }, {
        "sorsz" : 1,
        "ej_id" : 72547,
        "szavazat" : 15,
        "szavazat_szaz" : 1.98
      }, {
        "sorsz" : 7,
        "ej_id" : 72539,
        "szavazat" : 13,
        "szavazat_szaz" : 1.72
      }, {
        "sorsz" : 3,
        "ej_id" : 72513,
        "szavazat" : 1,
        "szavazat_szaz" : 0.13
      } ]
    },
    "listas_jkv" : {
      "allapot" : "3",
      "vp_osszes" : 978,
      "szavazott_osszesen" : 766,
      "szavazott_osszesen_szaz" : 78.32,
      "vp_lakcim_szerint" : 978,
      "megjel_lakcim_szerint" : 766,
      "megjel_lakcim_szerint_szaz" : 78.32,
      "szl_belyegtlen_urna" : 0,
      "szl_belyegzett_urna" : 767,
      "szl_elteres" : 0,
      "szl_ervenytelen" : 11,
      "szl_ervenytelen_szaz" : 1.43,
      "szl_ervenyes" : 756,
      "szl_ervenyes_szaz" : 98.57,
      "partlistara" : {
        "vp_osszes" : 974,
        "megjelent" : 763,
        "szl_belyegtlen_urna" : 0,
        "szl_belyegzett_urna" : 764,
        "szl_elteres" : 1,
        "szl_ervenytelen" : 11,
        "szl_ervenyes" : 753
      },
      "nemzetisegre" : {
        "vp_osszes" : 4,
        "megjelent" : 3,
        "szl_belyegtlen_urna" : 0,
        "szl_belyegzett_urna" : 3,
        "szl_elteres" : 0,
        "szl_ervenytelen" : 0,
        "szl_ervenyes" : 3
      },
      "tetelek" : [ {
        "sorsz" : 6,
        "tl_id" : 952,
        "szavazat" : 373,
        "szavazat_szaz" : 49.34
      }, {
        "sorsz" : 1,
        "tl_id" : 950,
        "szavazat" : 289,
        "szavazat_szaz" : 38.23
      }, {
        "sorsz" : 5,
        "tl_id" : 942,
        "szavazat" : 41,
        "szavazat_szaz" : 5.42
      }, {
        "sorsz" : 3,
        "tl_id" : 951,
        "szavazat" : 34,
        "szavazat_szaz" : 4.5
      }, {
        "sorsz" : 4,
        "tl_id" : 954,
        "szavazat" : 14,
        "szavazat_szaz" : 1.85
      }, {
        "sorsz" : 2,
        "tl_id" : 955,
        "szavazat" : 2,
        "szavazat_szaz" : 0.26
      }, {
        "tl_id" : 947,
        "nemzkod" : "5",
        "szavazat" : 3,
        "szavazat_szaz" : 0.4
      } ]
    }
  }, {
    "maz" : "14",
    "taz" : "034",
    "sorsz" : "018",
    "feldar" : 100.0,
    "egyeni_jkv" : {
      "allapot" : "3",
      "vp_osszes" : 912,
      "szavazott_osszesen" : 685,
      "szavazott_osszesen_szaz" : 75.11,
      "vp_lakcim_szerint" : 912,
      "megjel_lakcim_szerint" : 685,
      "megjel_lakcim_szerint_szaz" : 75.11,
      "szl_belyegtlen_urna" : 2,
      "szl_belyegzett_urna" : 684,
      "szl_elteres" : -1,
      "szl_ervenytelen" : 8,
      "szl_ervenytelen_szaz" : 1.17,
      "szl_ervenyes" : 676,
      "szl_ervenyes_szaz" : 98.83,
      "tetelek" : [ {
        "sorsz" : 6,
        "ej_id" : 72007,
        "szavazat" : 302,
        "szavazat_szaz" : 44.67
      }, {
        "sorsz" : 5,
        "ej_id" : 71972,
        "szavazat" : 295,
        "szavazat_szaz" : 43.64
      }, {
        "sorsz" : 2,
        "ej_id" : 72384,
        "szavazat" : 34,
        "szavazat_szaz" : 5.03
      }, {
        "sorsz" : 4,
        "ej_id" : 72469,
        "szavazat" : 27,
        "szavazat_szaz" : 3.99
      }, {
        "sorsz" : 7,
        "ej_id" : 72539,
        "szavazat" : 10,
        "szavazat_szaz" : 1.48
      }, {
        "sorsz" : 1,
        "ej_id" : 72547,
        "szavazat" : 4,
        "szavazat_szaz" : 0.59
      }, {
        "sorsz" : 3,
        "ej_id" : 72513,
        "szavazat" : 4,
        "szavazat_szaz" : 0.59
      } ]
    },
    "listas_jkv" : {
      "allapot" : "3",
      "vp_osszes" : 912,
      "szavazott_osszesen" : 685,
      "szavazott_osszesen_szaz" : 75.11,
      "vp_lakcim_szerint" : 912,
      "megjel_lakcim_szerint" : 685,
      "megjel_lakcim_szerint_szaz" : 75.11,
      "szl_belyegtlen_urna" : 0,
      "szl_belyegzett_urna" : 685,
      "szl_elteres" : 0,
      "szl_ervenytelen" : 6,
      "szl_ervenytelen_szaz" : 0.88,
      "szl_ervenyes" : 679,
      "szl_ervenyes_szaz" : 99.12,
      "partlistara" : {
        "vp_osszes" : 905,
        "megjelent" : 679,
        "szl_belyegtlen_urna" : 0,
        "szl_belyegzett_urna" : 679,
        "szl_elteres" : 0,
        "szl_ervenytelen" : 6,
        "szl_ervenyes" : 673
      },
      "nemzetisegre" : {
        "vp_osszes" : 7,
        "megjelent" : 6,
        "szl_belyegtlen_urna" : 0,
        "szl_belyegzett_urna" : 6,
        "szl_elteres" : 0,
        "szl_ervenytelen" : 0,
        "szl_ervenyes" : 6
      },
      "tetelek" : [ {
        "sorsz" : 1,
        "tl_id" : 950,
        "szavazat" : 315,
        "szavazat_szaz" : 46.39
      }, {
        "sorsz" : 6,
        "tl_id" : 952,
        "szavazat" : 265,
        "szavazat_szaz" : 39.03
      }, {
        "sorsz" : 5,
        "tl_id" : 942,
        "szavazat" : 41,
        "szavazat_szaz" : 6.04
      }, {
        "sorsz" : 3,
        "tl_id" : 951,
        "szavazat" : 40,
        "szavazat_szaz" : 5.89
      }, {
        "sorsz" : 4,
        "tl_id" : 954,
        "szavazat" : 9,
        "szavazat_szaz" : 1.33
      }, {
        "sorsz" : 2,
        "tl_id" : 955,
        "szavazat" : 3,
        "szavazat_szaz" : 0.44
      }, {
        "tl_id" : 947,
        "nemzkod" : "5",
        "szavazat" : 6,
        "szavazat_szaz" : 0.88
      } ]
    }
  }, {
    "maz" : "14",
    "taz" : "034",
    "sorsz" : "019",
    "feldar" : 100.0,
    "egyeni_jkv" : {
      "allapot" : "3",
      "vp_osszes" : 1204,
      "szavazott_osszesen" : 906,
      "szavazott_osszesen_szaz" : 75.25,
      "vp_lakcim_szerint" : 1204,
      "megjel_lakcim_szerint" : 906,
      "megjel_lakcim_szerint_szaz" : 75.25,
      "szl_belyegtlen_urna" : 0,
      "szl_belyegzett_urna" : 909,
      "szl_elteres" : 3,
      "szl_ervenytelen" : 25,
      "szl_ervenytelen_szaz" : 2.75,
      "szl_ervenyes" : 884,
      "szl_ervenyes_szaz" : 97.25,
      "tetelek" : [ {
        "sorsz" : 5,
        "ej_id" : 71972,
        "szavazat" : 439,
        "szavazat_szaz" : 49.66
      }, {
        "sorsz" : 6,
        "ej_id" : 72007,
        "szavazat" : 358,
        "szavazat_szaz" : 40.5
      }, {
        "sorsz" : 2,
        "ej_id" : 72384,
        "szavazat" : 36,
        "szavazat_szaz" : 4.07
      }, {
        "sorsz" : 4,
        "ej_id" : 72469,
        "szavazat" : 31,
        "szavazat_szaz" : 3.51
      }, {
        "sorsz" : 7,
        "ej_id" : 72539,
        "szavazat" : 15,
        "szavazat_szaz" : 1.7
      }, {
        "sorsz" : 1,
        "ej_id" : 72547,
        "szavazat" : 5,
        "szavazat_szaz" : 0.57
      }, {
        "sorsz" : 3,
        "ej_id" : 72513,
        "szavazat" : 0,
        "szavazat_szaz" : 0.0
      } ]
    },
    "listas_jkv" : {
      "allapot" : "3",
      "vp_osszes" : 1204,
      "szavazott_osszesen" : 911,
      "szavazott_osszesen_szaz" : 75.66,
      "vp_lakcim_szerint" : 1204,
      "megjel_lakcim_szerint" : 911,
      "megjel_lakcim_szerint_szaz" : 75.66,
      "szl_belyegtlen_urna" : 0,
      "szl_belyegzett_urna" : 910,
      "szl_elteres" : 0,
      "szl_ervenytelen" : 6,
      "szl_ervenytelen_szaz" : 0.66,
      "szl_ervenyes" : 904,
      "szl_ervenyes_szaz" : 99.34,
      "partlistara" : {
        "vp_osszes" : 1198,
        "megjelent" : 906,
        "szl_belyegtlen_urna" : 0,
        "szl_belyegzett_urna" : 905,
        "szl_elteres" : -1,
        "szl_ervenytelen" : 6,
        "szl_ervenyes" : 899
      },
      "nemzetisegre" : {
        "vp_osszes" : 6,
        "megjelent" : 5,
        "szl_belyegtlen_urna" : 0,
        "szl_belyegzett_urna" : 5,
        "szl_elteres" : 0,
        "szl_ervenytelen" : 0,
        "szl_ervenyes" : 5
      },
      "tetelek" : [ {
        "sorsz" : 6,
        "tl_id" : 952,
        "szavazat" : 423,
        "szavazat_szaz" : 46.79
      }, {
        "sorsz" : 1,
        "tl_id" : 950,
        "szavazat" : 362,
        "szavazat_szaz" : 40.04
      }, {
        "sorsz" : 3,
        "tl_id" : 951,
        "szavazat" : 59,
        "szavazat_szaz" : 6.53
      }, {
        "sorsz" : 5,
        "tl_id" : 942,
        "szavazat" : 41,
        "szavazat_szaz" : 4.54
      }, {
        "sorsz" : 4,
        "tl_id" : 954,
        "szavazat" : 10,
        "szavazat_szaz" : 1.11
      }, {
        "sorsz" : 2,
        "tl_id" : 955,
        "szavazat" : 4,
        "szavazat_szaz" : 0.44
      }, {
        "tl_id" : 947,
        "nemzkod" : "5",
        "szavazat" : 5,
        "szavazat_szaz" : 0.55
      } ]
    }
  }, {
    "maz" : "14",
    "taz" : "034",
    "sorsz" : "020",
    "feldar" : 100.0,
    "egyeni_jkv" : {
      "allapot" : "3",
      "vp_osszes" : 992,
      "szavazott_osszesen" : 793,
      "szavazott_osszesen_szaz" : 79.94,
      "vp_lakcim_szerint" : 992,
      "megjel_lakcim_szerint" : 793,
      "megjel_lakcim_szerint_szaz" : 79.94,
      "szl_belyegtlen_urna" : 0,
      "szl_belyegzett_urna" : 793,
      "szl_elteres" : 0,
      "szl_ervenytelen" : 6,
      "szl_ervenytelen_szaz" : 0.76,
      "szl_ervenyes" : 787,
      "szl_ervenyes_szaz" : 99.24,
      "tetelek" : [ {
        "sorsz" : 6,
        "ej_id" : 72007,
        "szavazat" : 368,
        "szavazat_szaz" : 46.76
      }, {
        "sorsz" : 5,
        "ej_id" : 71972,
        "szavazat" : 331,
        "szavazat_szaz" : 42.06
      }, {
        "sorsz" : 2,
        "ej_id" : 72384,
        "szavazat" : 42,
        "szavazat_szaz" : 5.34
      }, {
        "sorsz" : 4,
        "ej_id" : 72469,
        "szavazat" : 26,
        "szavazat_szaz" : 3.3
      }, {
        "sorsz" : 7,
        "ej_id" : 72539,
        "szavazat" : 13,
        "szavazat_szaz" : 1.65
      }, {
        "sorsz" : 3,
        "ej_id" : 72513,
        "szavazat" : 4,
        "szavazat_szaz" : 0.51
      }, {
        "sorsz" : 1,
        "ej_id" : 72547,
        "szavazat" : 3,
        "szavazat_szaz" : 0.38
      } ]
    },
    "listas_jkv" : {
      "allapot" : "3",
      "vp_osszes" : 992,
      "szavazott_osszesen" : 793,
      "szavazott_osszesen_szaz" : 79.94,
      "vp_lakcim_szerint" : 992,
      "megjel_lakcim_szerint" : 793,
      "megjel_lakcim_szerint_szaz" : 79.94,
      "szl_belyegtlen_urna" : 0,
      "szl_belyegzett_urna" : 793,
      "szl_elteres" : 0,
      "szl_ervenytelen" : 6,
      "szl_ervenytelen_szaz" : 0.76,
      "szl_ervenyes" : 787,
      "szl_ervenyes_szaz" : 99.24,
      "partlistara" : {
        "vp_osszes" : 989,
        "megjelent" : 791,
        "szl_belyegtlen_urna" : 0,
        "szl_belyegzett_urna" : 791,
        "szl_elteres" : 0,
        "szl_ervenytelen" : 6,
        "szl_ervenyes" : 785
      },
      "nemzetisegre" : {
        "vp_osszes" : 3,
        "megjelent" : 2,
        "szl_belyegtlen_urna" : 0,
        "szl_belyegzett_urna" : 2,
        "szl_elteres" : 0,
        "szl_ervenytelen" : 0,
        "szl_ervenyes" : 2
      },
      "tetelek" : [ {
        "sorsz" : 1,
        "tl_id" : 950,
        "szavazat" : 380,
        "szavazat_szaz" : 48.28
      }, {
        "sorsz" : 6,
        "tl_id" : 952,
        "szavazat" : 302,
        "szavazat_szaz" : 38.37
      }, {
        "sorsz" : 5,
        "tl_id" : 942,
        "szavazat" : 47,
        "szavazat_szaz" : 5.97
      }, {
        "sorsz" : 3,
        "tl_id" : 951,
        "szavazat" : 38,
        "szavazat_szaz" : 4.83
      }, {
        "sorsz" : 4,
        "tl_id" : 954,
        "szavazat" : 12,
        "szavazat_szaz" : 1.52
      }, {
        "sorsz" : 2,
        "tl_id" : 955,
        "szavazat" : 6,
        "szavazat_szaz" : 0.76
      }, {
        "tl_id" : 949,
        "nemzkod" : "11",
        "szavazat" : 1,
        "szavazat_szaz" : 0.13
      }, {
        "tl_id" : 947,
        "nemzkod" : "5",
        "szavazat" : 1,
        "szavazat_szaz" : 0.13
      } ]
    }
  }, {
    "maz" : "14",
    "taz" : "034",
    "sorsz" : "021",
    "feldar" : 100.0,
    "egyeni_jkv" : {
      "allapot" : "3",
      "vp_osszes" : 1115,
      "szavazott_osszesen" : 774,
      "szavazott_osszesen_szaz" : 69.42,
      "vp_lakcim_szerint" : 1115,
      "megjel_lakcim_szerint" : 774,
      "megjel_lakcim_szerint_szaz" : 69.42,
      "szl_belyegtlen_urna" : 0,
      "szl_belyegzett_urna" : 773,
      "szl_elteres" : -1,
      "szl_ervenytelen" : 7,
      "szl_ervenytelen_szaz" : 0.91,
      "szl_ervenyes" : 766,
      "szl_ervenyes_szaz" : 99.09,
      "tetelek" : [ {
        "sorsz" : 6,
        "ej_id" : 72007,
        "szavazat" : 362,
        "szavazat_szaz" : 47.26
      }, {
        "sorsz" : 5,
        "ej_id" : 71972,
        "szavazat" : 326,
        "szavazat_szaz" : 42.56
      }, {
        "sorsz" : 2,
        "ej_id" : 72384,
        "szavazat" : 39,
        "szavazat_szaz" : 5.09
      }, {
        "sorsz" : 4,
        "ej_id" : 72469,
        "szavazat" : 18,
        "szavazat_szaz" : 2.35
      }, {
        "sorsz" : 1,
        "ej_id" : 72547,
        "szavazat" : 12,
        "szavazat_szaz" : 1.57
      }, {
        "sorsz" : 7,
        "ej_id" : 72539,
        "szavazat" : 7,
        "szavazat_szaz" : 0.91
      }, {
        "sorsz" : 3,
        "ej_id" : 72513,
        "szavazat" : 2,
        "szavazat_szaz" : 0.26
      } ]
    },
    "listas_jkv" : {
      "allapot" : "3",
      "vp_osszes" : 1115,
      "szavazott_osszesen" : 774,
      "szavazott_osszesen_szaz" : 69.42,
      "vp_lakcim_szerint" : 1115,
      "megjel_lakcim_szerint" : 774,
      "megjel_lakcim_szerint_szaz" : 69.42,
      "szl_belyegtlen_urna" : 0,
      "szl_belyegzett_urna" : 774,
      "szl_elteres" : 0,
      "szl_ervenytelen" : 3,
      "szl_ervenytelen_szaz" : 0.39,
      "szl_ervenyes" : 771,
      "szl_ervenyes_szaz" : 99.61,
      "partlistara" : {
        "vp_osszes" : 1112,
        "megjelent" : 772,
        "szl_belyegtlen_urna" : 0,
        "szl_belyegzett_urna" : 772,
        "szl_elteres" : 0,
        "szl_ervenytelen" : 2,
        "szl_ervenyes" : 770
      },
      "nemzetisegre" : {
        "vp_osszes" : 3,
        "megjelent" : 2,
        "szl_belyegtlen_urna" : 0,
        "szl_belyegzett_urna" : 2,
        "szl_elteres" : 0,
        "szl_ervenytelen" : 1,
        "szl_ervenyes" : 1
      },
      "tetelek" : [ {
        "sorsz" : 1,
        "tl_id" : 950,
        "szavazat" : 376,
        "szavazat_szaz" : 48.77
      }, {
        "sorsz" : 6,
        "tl_id" : 952,
        "szavazat" : 303,
        "szavazat_szaz" : 39.3
      }, {
        "sorsz" : 5,
        "tl_id" : 942,
        "szavazat" : 44,
        "szavazat_szaz" : 5.71
      }, {
        "sorsz" : 3,
        "tl_id" : 951,
        "szavazat" : 32,
        "szavazat_szaz" : 4.15
      }, {
        "sorsz" : 4,
        "tl_id" : 954,
        "szavazat" : 10,
        "szavazat_szaz" : 1.3
      }, {
        "sorsz" : 2,
        "tl_id" : 955,
        "szavazat" : 5,
        "szavazat_szaz" : 0.65
      }, {
        "tl_id" : 947,
        "nemzkod" : "5",
        "szavazat" : 1,
        "szavazat_szaz" : 0.13
      } ]
    }
  }, {
    "maz" : "14",
    "taz" : "034",
    "sorsz" : "022",
    "feldar" : 100.0,
    "egyeni_jkv" : {
      "allapot" : "3",
      "vp_osszes" : 1121,
      "szavazott_osszesen" : 827,
      "szavazott_osszesen_szaz" : 73.77,
      "vp_lakcim_szerint" : 1121,
      "megjel_lakcim_szerint" : 827,
      "megjel_lakcim_szerint_szaz" : 73.77,
      "szl_belyegtlen_urna" : 1,
      "szl_belyegzett_urna" : 826,
      "szl_elteres" : -1,
      "szl_ervenytelen" : 4,
      "szl_ervenytelen_szaz" : 0.48,
      "szl_ervenyes" : 822,
      "szl_ervenyes_szaz" : 99.52,
      "tetelek" : [ {
        "sorsz" : 5,
        "ej_id" : 71972,
        "szavazat" : 420,
        "szavazat_szaz" : 51.09
      }, {
        "sorsz" : 6,
        "ej_id" : 72007,
        "szavazat" : 318,
        "szavazat_szaz" : 38.69
      }, {
        "sorsz" : 2,
        "ej_id" : 72384,
        "szavazat" : 36,
        "szavazat_szaz" : 4.38
      }, {
        "sorsz" : 4,
        "ej_id" : 72469,
        "szavazat" : 28,
        "szavazat_szaz" : 3.41
      }, {
        "sorsz" : 7,
        "ej_id" : 72539,
        "szavazat" : 11,
        "szavazat_szaz" : 1.34
      }, {
        "sorsz" : 3,
        "ej_id" : 72513,
        "szavazat" : 5,
        "szavazat_szaz" : 0.61
      }, {
        "sorsz" : 1,
        "ej_id" : 72547,
        "szavazat" : 4,
        "szavazat_szaz" : 0.49
      } ]
    },
    "listas_jkv" : {
      "allapot" : "3",
      "vp_osszes" : 1121,
      "szavazott_osszesen" : 827,
      "szavazott_osszesen_szaz" : 73.77,
      "vp_lakcim_szerint" : 1121,
      "megjel_lakcim_szerint" : 827,
      "megjel_lakcim_szerint_szaz" : 73.77,
      "szl_belyegtlen_urna" : 0,
      "szl_belyegzett_urna" : 827,
      "szl_elteres" : 0,
      "szl_ervenytelen" : 7,
      "szl_ervenytelen_szaz" : 0.85,
      "szl_ervenyes" : 820,
      "szl_ervenyes_szaz" : 99.15,
      "partlistara" : {
        "vp_osszes" : 1117,
        "megjelent" : 824,
        "szl_belyegtlen_urna" : 0,
        "szl_belyegzett_urna" : 824,
        "szl_elteres" : 0,
        "szl_ervenytelen" : 7,
        "szl_ervenyes" : 817
      },
      "nemzetisegre" : {
        "vp_osszes" : 4,
        "megjelent" : 3,
        "szl_belyegtlen_urna" : 0,
        "szl_belyegzett_urna" : 3,
        "szl_elteres" : 0,
        "szl_ervenytelen" : 0,
        "szl_ervenyes" : 3
      },
      "tetelek" : [ {
        "sorsz" : 6,
        "tl_id" : 952,
        "szavazat" : 391,
        "szavazat_szaz" : 47.68
      }, {
        "sorsz" : 1,
        "tl_id" : 950,
        "szavazat" : 327,
        "szavazat_szaz" : 39.88
      }, {
        "sorsz" : 3,
        "tl_id" : 951,
        "szavazat" : 45,
        "szavazat_szaz" : 5.49
      }, {
        "sorsz" : 5,
        "tl_id" : 942,
        "szavazat" : 34,
        "szavazat_szaz" : 4.15
      }, {
        "sorsz" : 4,
        "tl_id" : 954,
        "szavazat" : 14,
        "szavazat_szaz" : 1.71
      }, {
        "sorsz" : 2,
        "tl_id" : 955,
        "szavazat" : 6,
        "szavazat_szaz" : 0.73
      }, {
        "tl_id" : 947,
        "nemzkod" : "5",
        "szavazat" : 3,
        "szavazat_szaz" : 0.37
      } ]
    }
  }, {
    "maz" : "14",
    "taz" : "034",
    "sorsz" : "023",
    "feldar" : 100.0,
    "egyeni_jkv" : {
      "allapot" : "3",
      "vp_osszes" : 1134,
      "szavazott_osszesen" : 864,
      "szavazott_osszesen_szaz" : 76.19,
      "vp_lakcim_szerint" : 1134,
      "megjel_lakcim_szerint" : 864,
      "megjel_lakcim_szerint_szaz" : 76.19,
      "szl_belyegtlen_urna" : 0,
      "szl_belyegzett_urna" : 864,
      "szl_elteres" : 0,
      "szl_ervenytelen" : 4,
      "szl_ervenytelen_szaz" : 0.46,
      "szl_ervenyes" : 860,
      "szl_ervenyes_szaz" : 99.54,
      "tetelek" : [ {
        "sorsz" : 5,
        "ej_id" : 71972,
        "szavazat" : 407,
        "szavazat_szaz" : 47.33
      }, {
        "sorsz" : 6,
        "ej_id" : 72007,
        "szavazat" : 359,
        "szavazat_szaz" : 41.74
      }, {
        "sorsz" : 2,
        "ej_id" : 72384,
        "szavazat" : 41,
        "szavazat_szaz" : 4.77
      }, {
        "sorsz" : 4,
        "ej_id" : 72469,
        "szavazat" : 23,
        "szavazat_szaz" : 2.67
      }, {
        "sorsz" : 7,
        "ej_id" : 72539,
        "szavazat" : 19,
        "szavazat_szaz" : 2.21
      }, {
        "sorsz" : 3,
        "ej_id" : 72513,
        "szavazat" : 6,
        "szavazat_szaz" : 0.7
      }, {
        "sorsz" : 1,
        "ej_id" : 72547,
        "szavazat" : 5,
        "szavazat_szaz" : 0.58
      } ]
    },
    "listas_jkv" : {
      "allapot" : "3",
      "vp_osszes" : 1134,
      "szavazott_osszesen" : 865,
      "szavazott_osszesen_szaz" : 76.28,
      "vp_lakcim_szerint" : 1134,
      "megjel_lakcim_szerint" : 865,
      "megjel_lakcim_szerint_szaz" : 76.28,
      "szl_belyegtlen_urna" : 0,
      "szl_belyegzett_urna" : 865,
      "szl_elteres" : 0,
      "szl_ervenytelen" : 1,
      "szl_ervenytelen_szaz" : 0.12,
      "szl_ervenyes" : 864,
      "szl_ervenyes_szaz" : 99.88,
      "partlistara" : {
        "vp_osszes" : 1128,
        "megjelent" : 860,
        "szl_belyegtlen_urna" : 0,
        "szl_belyegzett_urna" : 860,
        "szl_elteres" : 0,
        "szl_ervenytelen" : 0,
        "szl_ervenyes" : 860
      },
      "nemzetisegre" : {
        "vp_osszes" : 6,
        "megjelent" : 5,
        "szl_belyegtlen_urna" : 0,
        "szl_belyegzett_urna" : 5,
        "szl_elteres" : 0,
        "szl_ervenytelen" : 1,
        "szl_ervenyes" : 4
      },
      "tetelek" : [ {
        "sorsz" : 1,
        "tl_id" : 950,
        "szavazat" : 378,
        "szavazat_szaz" : 43.75
      }, {
        "sorsz" : 6,
        "tl_id" : 952,
        "szavazat" : 356,
        "szavazat_szaz" : 41.2
      }, {
        "sorsz" : 5,
        "tl_id" : 942,
        "szavazat" : 60,
        "szavazat_szaz" : 6.94
      }, {
        "sorsz" : 3,
        "tl_id" : 951,
        "szavazat" : 34,
        "szavazat_szaz" : 3.94
      }, {
        "sorsz" : 4,
        "tl_id" : 954,
        "szavazat" : 23,
        "szavazat_szaz" : 2.66
      }, {
        "sorsz" : 2,
        "tl_id" : 955,
        "szavazat" : 9,
        "szavazat_szaz" : 1.04
      }, {
        "tl_id" : 949,
        "nemzkod" : "11",
        "szavazat" : 1,
        "szavazat_szaz" : 0.12
      }, {
        "tl_id" : 947,
        "nemzkod" : "5",
        "szavazat" : 3,
        "szavazat_szaz" : 0.35
      } ]
    }
  }, {
    "maz" : "14",
    "taz" : "034",
    "sorsz" : "024",
    "feldar" : 100.0,
    "egyeni_jkv" : {
      "allapot" : "3",
      "vp_osszes" : 1042,
      "szavazott_osszesen" : 812,
      "szavazott_osszesen_szaz" : 77.93,
      "vp_lakcim_szerint" : 1042,
      "megjel_lakcim_szerint" : 812,
      "megjel_lakcim_szerint_szaz" : 77.93,
      "szl_belyegtlen_urna" : 0,
      "szl_belyegzett_urna" : 812,
      "szl_elteres" : 0,
      "szl_ervenytelen" : 8,
      "szl_ervenytelen_szaz" : 0.99,
      "szl_ervenyes" : 804,
      "szl_ervenyes_szaz" : 99.01,
      "tetelek" : [ {
        "sorsz" : 5,
        "ej_id" : 71972,
        "szavazat" : 385,
        "szavazat_szaz" : 47.89
      }, {
        "sorsz" : 6,
        "ej_id" : 72007,
        "szavazat" : 327,
        "szavazat_szaz" : 40.67
      }, {
        "sorsz" : 2,
        "ej_id" : 72384,
        "szavazat" : 42,
        "szavazat_szaz" : 5.22
      }, {
        "sorsz" : 4,
        "ej_id" : 72469,
        "szavazat" : 22,
        "szavazat_szaz" : 2.74
      }, {
        "sorsz" : 7,
        "ej_id" : 72539,
        "szavazat" : 17,
        "szavazat_szaz" : 2.11
      }, {
        "sorsz" : 1,
        "ej_id" : 72547,
        "szavazat" : 10,
        "szavazat_szaz" : 1.24
      }, {
        "sorsz" : 3,
        "ej_id" : 72513,
        "szavazat" : 1,
        "szavazat_szaz" : 0.12
      } ]
    },
    "listas_jkv" : {
      "allapot" : "3",
      "vp_osszes" : 1042,
      "szavazott_osszesen" : 812,
      "szavazott_osszesen_szaz" : 77.93,
      "vp_lakcim_szerint" : 1042,
      "megjel_lakcim_szerint" : 812,
      "megjel_lakcim_szerint_szaz" : 77.93,
      "szl_belyegtlen_urna" : 0,
      "szl_belyegzett_urna" : 811,
      "szl_elteres" : 0,
      "szl_ervenytelen" : 4,
      "szl_ervenytelen_szaz" : 0.49,
      "szl_ervenyes" : 807,
      "szl_ervenyes_szaz" : 99.51,
      "partlistara" : {
        "vp_osszes" : 1037,
        "megjelent" : 807,
        "szl_belyegtlen_urna" : 0,
        "szl_belyegzett_urna" : 806,
        "szl_elteres" : -1,
        "szl_ervenytelen" : 4,
        "szl_ervenyes" : 802
      },
      "nemzetisegre" : {
        "vp_osszes" : 5,
        "megjelent" : 5,
        "szl_belyegtlen_urna" : 0,
        "szl_belyegzett_urna" : 5,
        "szl_elteres" : 0,
        "szl_ervenytelen" : 0,
        "szl_ervenyes" : 5
      },
      "tetelek" : [ {
        "sorsz" : 1,
        "tl_id" : 950,
        "szavazat" : 350,
        "szavazat_szaz" : 43.37
      }, {
        "sorsz" : 6,
        "tl_id" : 952,
        "szavazat" : 348,
        "szavazat_szaz" : 43.12
      }, {
        "sorsz" : 5,
        "tl_id" : 942,
        "szavazat" : 58,
        "szavazat_szaz" : 7.19
      }, {
        "sorsz" : 3,
        "tl_id" : 951,
        "szavazat" : 29,
        "szavazat_szaz" : 3.59
      }, {
        "sorsz" : 4,
        "tl_id" : 954,
        "szavazat" : 12,
        "szavazat_szaz" : 1.49
      }, {
        "sorsz" : 2,
        "tl_id" : 955,
        "szavazat" : 5,
        "szavazat_szaz" : 0.62
      }, {
        "tl_id" : 947,
        "nemzkod" : "5",
        "szavazat" : 5,
        "szavazat_szaz" : 0.62
      } ]
    }
  }, {
    "maz" : "14",
    "taz" : "034",
    "sorsz" : "025",
    "feldar" : 100.0,
    "egyeni_jkv" : {
      "allapot" : "3",
      "vp_osszes" : 1074,
      "szavazott_osszesen" : 874,
      "szavazott_osszesen_szaz" : 81.38,
      "vp_lakcim_szerint" : 1074,
      "megjel_lakcim_szerint" : 874,
      "megjel_lakcim_szerint_szaz" : 81.38,
      "szl_belyegtlen_urna" : 0,
      "szl_belyegzett_urna" : 873,
      "szl_elteres" : -1,
      "szl_ervenytelen" : 7,
      "szl_ervenytelen_szaz" : 0.8,
      "szl_ervenyes" : 866,
      "szl_ervenyes_szaz" : 99.2,
      "tetelek" : [ {
        "sorsz" : 6,
        "ej_id" : 72007,
        "szavazat" : 398,
        "szavazat_szaz" : 45.96
      }, {
        "sorsz" : 5,
        "ej_id" : 71972,
        "szavazat" : 378,
        "szavazat_szaz" : 43.65
      }, {
        "sorsz" : 4,
        "ej_id" : 72469,
        "szavazat" : 36,
        "szavazat_szaz" : 4.16
      }, {
        "sorsz" : 2,
        "ej_id" : 72384,
        "szavazat" : 26,
        "szavazat_szaz" : 3.0
      }, {
        "sorsz" : 7,
        "ej_id" : 72539,
        "szavazat" : 18,
        "szavazat_szaz" : 2.08
      }, {
        "sorsz" : 1,
        "ej_id" : 72547,
        "szavazat" : 10,
        "szavazat_szaz" : 1.15
      }, {
        "sorsz" : 3,
        "ej_id" : 72513,
        "szavazat" : 0,
        "szavazat_szaz" : 0.0
      } ]
    },
    "listas_jkv" : {
      "allapot" : "3",
      "vp_osszes" : 1074,
      "szavazott_osszesen" : 874,
      "szavazott_osszesen_szaz" : 81.38,
      "vp_lakcim_szerint" : 1074,
      "megjel_lakcim_szerint" : 874,
      "megjel_lakcim_szerint_szaz" : 81.38,
      "szl_belyegtlen_urna" : 0,
      "szl_belyegzett_urna" : 876,
      "szl_elteres" : 0,
      "szl_ervenytelen" : 15,
      "szl_ervenytelen_szaz" : 1.71,
      "szl_ervenyes" : 861,
      "szl_ervenyes_szaz" : 98.29,
      "partlistara" : {
        "vp_osszes" : 1062,
        "megjelent" : 863,
        "szl_belyegtlen_urna" : 0,
        "szl_belyegzett_urna" : 865,
        "szl_elteres" : 2,
        "szl_ervenytelen" : 14,
        "szl_ervenyes" : 851
      },
      "nemzetisegre" : {
        "vp_osszes" : 12,
        "megjelent" : 11,
        "szl_belyegtlen_urna" : 0,
        "szl_belyegzett_urna" : 11,
        "szl_elteres" : 0,
        "szl_ervenytelen" : 1,
        "szl_ervenyes" : 10
      },
      "tetelek" : [ {
        "sorsz" : 1,
        "tl_id" : 950,
        "szavazat" : 422,
        "szavazat_szaz" : 49.01
      }, {
        "sorsz" : 6,
        "tl_id" : 952,
        "szavazat" : 339,
        "szavazat_szaz" : 39.37
      }, {
        "sorsz" : 3,
        "tl_id" : 951,
        "szavazat" : 41,
        "szavazat_szaz" : 4.76
      }, {
        "sorsz" : 5,
        "tl_id" : 942,
        "szavazat" : 33,
        "szavazat_szaz" : 3.83
      }, {
        "sorsz" : 4,
        "tl_id" : 954,
        "szavazat" : 15,
        "szavazat_szaz" : 1.74
      }, {
        "sorsz" : 2,
        "tl_id" : 955,
        "szavazat" : 1,
        "szavazat_szaz" : 0.12
      }, {
        "tl_id" : 947,
        "nemzkod" : "5",
        "szavazat" : 10,
        "szavazat_szaz" : 1.16
      } ]
    }
  }, {
    "maz" : "14",
    "taz" : "034",
    "sorsz" : "026",
    "feldar" : 100.0,
    "egyeni_jkv" : {
      "allapot" : "3",
      "vp_osszes" : 1352,
      "szavazott_osszesen" : 1057,
      "szavazott_osszesen_szaz" : 78.18,
      "vp_lakcim_szerint" : 1352,
      "megjel_lakcim_szerint" : 1057,
      "megjel_lakcim_szerint_szaz" : 78.18,
      "szl_belyegtlen_urna" : 0,
      "szl_belyegzett_urna" : 1057,
      "szl_elteres" : 0,
      "szl_ervenytelen" : 6,
      "szl_ervenytelen_szaz" : 0.57,
      "szl_ervenyes" : 1051,
      "szl_ervenyes_szaz" : 99.43,
      "tetelek" : [ {
        "sorsz" : 6,
        "ej_id" : 72007,
        "szavazat" : 486,
        "szavazat_szaz" : 46.24
      }, {
        "sorsz" : 5,
        "ej_id" : 71972,
        "szavazat" : 457,
        "szavazat_szaz" : 43.48
      }, {
        "sorsz" : 4,
        "ej_id" : 72469,
        "szavazat" : 50,
        "szavazat_szaz" : 4.76
      }, {
        "sorsz" : 2,
        "ej_id" : 72384,
        "szavazat" : 25,
        "szavazat_szaz" : 2.38
      }, {
        "sorsz" : 7,
        "ej_id" : 72539,
        "szavazat" : 20,
        "szavazat_szaz" : 1.9
      }, {
        "sorsz" : 1,
        "ej_id" : 72547,
        "szavazat" : 7,
        "szavazat_szaz" : 0.67
      }, {
        "sorsz" : 3,
        "ej_id" : 72513,
        "szavazat" : 6,
        "szavazat_szaz" : 0.57
      } ]
    },
    "listas_jkv" : {
      "allapot" : "3",
      "vp_osszes" : 1352,
      "szavazott_osszesen" : 1057,
      "szavazott_osszesen_szaz" : 78.18,
      "vp_lakcim_szerint" : 1352,
      "megjel_lakcim_szerint" : 1057,
      "megjel_lakcim_szerint_szaz" : 78.18,
      "szl_belyegtlen_urna" : 0,
      "szl_belyegzett_urna" : 1056,
      "szl_elteres" : 0,
      "szl_ervenytelen" : 10,
      "szl_ervenytelen_szaz" : 0.95,
      "szl_ervenyes" : 1046,
      "szl_ervenyes_szaz" : 99.05,
      "partlistara" : {
        "vp_osszes" : 1322,
        "megjelent" : 1029,
        "szl_belyegtlen_urna" : 0,
        "szl_belyegzett_urna" : 1029,
        "szl_elteres" : 0,
        "szl_ervenytelen" : 8,
        "szl_ervenyes" : 1021
      },
      "nemzetisegre" : {
        "vp_osszes" : 30,
        "megjelent" : 28,
        "szl_belyegtlen_urna" : 0,
        "szl_belyegzett_urna" : 27,
        "szl_elteres" : 0,
        "szl_ervenytelen" : 2,
        "szl_ervenyes" : 25
      },
      "tetelek" : [ {
        "sorsz" : 1,
        "tl_id" : 950,
        "szavazat" : 487,
        "szavazat_szaz" : 46.56
      }, {
        "sorsz" : 6,
        "tl_id" : 952,
        "szavazat" : 418,
        "szavazat_szaz" : 39.96
      }, {
        "sorsz" : 3,
        "tl_id" : 951,
        "szavazat" : 56,
        "szavazat_szaz" : 5.35
      }, {
        "sorsz" : 5,
        "tl_id" : 942,
        "szavazat" : 29,
        "szavazat_szaz" : 2.77
      }, {
        "sorsz" : 4,
        "tl_id" : 954,
        "szavazat" : 26,
        "szavazat_szaz" : 2.49
      }, {
        "sorsz" : 2,
        "tl_id" : 955,
        "szavazat" : 5,
        "szavazat_szaz" : 0.48
      }, {
        "tl_id" : 944,
        "nemzkod" : "13",
        "szavazat" : 0,
        "szavazat_szaz" : 0.0
      }, {
        "tl_id" : 947,
        "nemzkod" : "5",
        "szavazat" : 25,
        "szavazat_szaz" : 2.39
      } ]
    }
  }, {
    "maz" : "14",
    "taz" : "034",
    "sorsz" : "027",
    "feldar" : 100.0,
    "egyeni_jkv" : {
      "allapot" : "3",
      "vp_osszes" : 1180,
      "szavazott_osszesen" : 971,
      "szavazott_osszesen_szaz" : 82.29,
      "vp_lakcim_szerint" : 1180,
      "megjel_lakcim_szerint" : 971,
      "megjel_lakcim_szerint_szaz" : 82.29,
      "szl_belyegtlen_urna" : 0,
      "szl_belyegzett_urna" : 971,
      "szl_elteres" : 0,
      "szl_ervenytelen" : 4,
      "szl_ervenytelen_szaz" : 0.41,
      "szl_ervenyes" : 967,
      "szl_ervenyes_szaz" : 99.59,
      "tetelek" : [ {
        "sorsz" : 5,
        "ej_id" : 71972,
        "szavazat" : 443,
        "szavazat_szaz" : 45.81
      }, {
        "sorsz" : 6,
        "ej_id" : 72007,
        "szavazat" : 435,
        "szavazat_szaz" : 44.98
      }, {
        "sorsz" : 4,
        "ej_id" : 72469,
        "szavazat" : 29,
        "szavazat_szaz" : 3.0
      }, {
        "sorsz" : 2,
        "ej_id" : 72384,
        "szavazat" : 26,
        "szavazat_szaz" : 2.69
      }, {
        "sorsz" : 7,
        "ej_id" : 72539,
        "szavazat" : 18,
        "szavazat_szaz" : 1.86
      }, {
        "sorsz" : 1,
        "ej_id" : 72547,
        "szavazat" : 9,
        "szavazat_szaz" : 0.93
      }, {
        "sorsz" : 3,
        "ej_id" : 72513,
        "szavazat" : 7,
        "szavazat_szaz" : 0.72
      } ]
    },
    "listas_jkv" : {
      "allapot" : "3",
      "vp_osszes" : 1180,
      "szavazott_osszesen" : 971,
      "szavazott_osszesen_szaz" : 82.29,
      "vp_lakcim_szerint" : 1180,
      "megjel_lakcim_szerint" : 971,
      "megjel_lakcim_szerint_szaz" : 82.29,
      "szl_belyegtlen_urna" : 0,
      "szl_belyegzett_urna" : 971,
      "szl_elteres" : 0,
      "szl_ervenytelen" : 3,
      "szl_ervenytelen_szaz" : 0.31,
      "szl_ervenyes" : 968,
      "szl_ervenyes_szaz" : 99.69,
      "partlistara" : {
        "vp_osszes" : 1167,
        "megjelent" : 958,
        "szl_belyegtlen_urna" : 0,
        "szl_belyegzett_urna" : 958,
        "szl_elteres" : 0,
        "szl_ervenytelen" : 2,
        "szl_ervenyes" : 956
      },
      "nemzetisegre" : {
        "vp_osszes" : 13,
        "megjelent" : 13,
        "szl_belyegtlen_urna" : 0,
        "szl_belyegzett_urna" : 13,
        "szl_elteres" : 0,
        "szl_ervenytelen" : 1,
        "szl_ervenyes" : 12
      },
      "tetelek" : [ {
        "sorsz" : 1,
        "tl_id" : 950,
        "szavazat" : 464,
        "szavazat_szaz" : 47.93
      }, {
        "sorsz" : 6,
        "tl_id" : 952,
        "szavazat" : 391,
        "szavazat_szaz" : 40.39
      }, {
        "sorsz" : 3,
        "tl_id" : 951,
        "szavazat" : 47,
        "szavazat_szaz" : 4.86
      }, {
        "sorsz" : 5,
        "tl_id" : 942,
        "szavazat" : 28,
        "szavazat_szaz" : 2.89
      }, {
        "sorsz" : 4,
        "tl_id" : 954,
        "szavazat" : 19,
        "szavazat_szaz" : 1.96
      }, {
        "sorsz" : 2,
        "tl_id" : 955,
        "szavazat" : 7,
        "szavazat_szaz" : 0.72
      }, {
        "tl_id" : 947,
        "nemzkod" : "5",
        "szavazat" : 12,
        "szavazat_szaz" : 1.24
      } ]
    }
  }, {
    "maz" : "14",
    "taz" : "034",
    "sorsz" : "028",
    "feldar" : 100.0,
    "egyeni_jkv" : {
      "allapot" : "3",
      "vp_osszes" : 1212,
      "szavazott_osszesen" : 867,
      "szavazott_osszesen_szaz" : 71.53,
      "vp_lakcim_szerint" : 1212,
      "megjel_lakcim_szerint" : 867,
      "megjel_lakcim_szerint_szaz" : 71.53,
      "szl_belyegtlen_urna" : 0,
      "szl_belyegzett_urna" : 865,
      "szl_elteres" : -2,
      "szl_ervenytelen" : 10,
      "szl_ervenytelen_szaz" : 1.16,
      "szl_ervenyes" : 855,
      "szl_ervenyes_szaz" : 98.84,
      "tetelek" : [ {
        "sorsz" : 5,
        "ej_id" : 71972,
        "szavazat" : 441,
        "szavazat_szaz" : 51.58
      }, {
        "sorsz" : 6,
        "ej_id" : 72007,
        "szavazat" : 324,
        "szavazat_szaz" : 37.89
      }, {
        "sorsz" : 2,
        "ej_id" : 72384,
        "szavazat" : 42,
        "szavazat_szaz" : 4.91
      }, {
        "sorsz" : 4,
        "ej_id" : 72469,
        "szavazat" : 28,
        "szavazat_szaz" : 3.27
      }, {
        "sorsz" : 7,
        "ej_id" : 72539,
        "szavazat" : 11,
        "szavazat_szaz" : 1.29
      }, {
        "sorsz" : 1,
        "ej_id" : 72547,
        "szavazat" : 5,
        "szavazat_szaz" : 0.58
      }, {
        "sorsz" : 3,
        "ej_id" : 72513,
        "szavazat" : 4,
        "szavazat_szaz" : 0.47
      } ]
    },
    "listas_jkv" : {
      "allapot" : "3",
      "vp_osszes" : 1212,
      "szavazott_osszesen" : 865,
      "szavazott_osszesen_szaz" : 71.37,
      "vp_lakcim_szerint" : 1212,
      "megjel_lakcim_szerint" : 865,
      "megjel_lakcim_szerint_szaz" : 71.37,
      "szl_belyegtlen_urna" : 0,
      "szl_belyegzett_urna" : 865,
      "szl_elteres" : 0,
      "szl_ervenytelen" : 7,
      "szl_ervenytelen_szaz" : 0.81,
      "szl_ervenyes" : 858,
      "szl_ervenyes_szaz" : 99.19,
      "partlistara" : {
        "vp_osszes" : 1206,
        "megjelent" : 861,
        "szl_belyegtlen_urna" : 0,
        "szl_belyegzett_urna" : 861,
        "szl_elteres" : 0,
        "szl_ervenytelen" : 6,
        "szl_ervenyes" : 855
      },
      "nemzetisegre" : {
        "vp_osszes" : 6,
        "megjelent" : 4,
        "szl_belyegtlen_urna" : 0,
        "szl_belyegzett_urna" : 4,
        "szl_elteres" : 0,
        "szl_ervenytelen" : 1,
        "szl_ervenyes" : 3
      },
      "tetelek" : [ {
        "sorsz" : 6,
        "tl_id" : 952,
        "szavazat" : 422,
        "szavazat_szaz" : 49.18
      }, {
        "sorsz" : 1,
        "tl_id" : 950,
        "szavazat" : 333,
        "szavazat_szaz" : 38.81
      }, {
        "sorsz" : 5,
        "tl_id" : 942,
        "szavazat" : 51,
        "szavazat_szaz" : 5.94
      }, {
        "sorsz" : 3,
        "tl_id" : 951,
        "szavazat" : 36,
        "szavazat_szaz" : 4.2
      }, {
        "sorsz" : 4,
        "tl_id" : 954,
        "szavazat" : 11,
        "szavazat_szaz" : 1.28
      }, {
        "sorsz" : 2,
        "tl_id" : 955,
        "szavazat" : 2,
        "szavazat_szaz" : 0.23
      }, {
        "tl_id" : 947,
        "nemzkod" : "5",
        "szavazat" : 3,
        "szavazat_szaz" : 0.35
      }, {
        "tl_id" : 937,
        "nemzkod" : "9",
        "szavazat" : 0,
        "szavazat_szaz" : 0.0
      } ]
    }
  }, {
    "maz" : "14",
    "taz" : "034",
    "sorsz" : "029",
    "feldar" : 100.0,
    "egyeni_jkv" : {
      "allapot" : "3",
      "vp_osszes" : 1173,
      "szavazott_osszesen" : 849,
      "szavazott_osszesen_szaz" : 72.38,
      "vp_lakcim_szerint" : 1173,
      "megjel_lakcim_szerint" : 849,
      "megjel_lakcim_szerint_szaz" : 72.38,
      "szl_belyegtlen_urna" : 0,
      "szl_belyegzett_urna" : 848,
      "szl_elteres" : -1,
      "szl_ervenytelen" : 5,
      "szl_ervenytelen_szaz" : 0.59,
      "szl_ervenyes" : 843,
      "szl_ervenyes_szaz" : 99.41,
      "tetelek" : [ {
        "sorsz" : 5,
        "ej_id" : 71972,
        "szavazat" : 420,
        "szavazat_szaz" : 49.82
      }, {
        "sorsz" : 6,
        "ej_id" : 72007,
        "szavazat" : 332,
        "szavazat_szaz" : 39.38
      }, {
        "sorsz" : 2,
        "ej_id" : 72384,
        "szavazat" : 35,
        "szavazat_szaz" : 4.15
      }, {
        "sorsz" : 7,
        "ej_id" : 72539,
        "szavazat" : 22,
        "szavazat_szaz" : 2.61
      }, {
        "sorsz" : 4,
        "ej_id" : 72469,
        "szavazat" : 20,
        "szavazat_szaz" : 2.37
      }, {
        "sorsz" : 1,
        "ej_id" : 72547,
        "szavazat" : 11,
        "szavazat_szaz" : 1.3
      }, {
        "sorsz" : 3,
        "ej_id" : 72513,
        "szavazat" : 3,
        "szavazat_szaz" : 0.36
      } ]
    },
    "listas_jkv" : {
      "allapot" : "3",
      "vp_osszes" : 1173,
      "szavazott_osszesen" : 849,
      "szavazott_osszesen_szaz" : 72.38,
      "vp_lakcim_szerint" : 1173,
      "megjel_lakcim_szerint" : 849,
      "megjel_lakcim_szerint_szaz" : 72.38,
      "szl_belyegtlen_urna" : 0,
      "szl_belyegzett_urna" : 847,
      "szl_elteres" : 0,
      "szl_ervenytelen" : 3,
      "szl_ervenytelen_szaz" : 0.35,
      "szl_ervenyes" : 844,
      "szl_ervenyes_szaz" : 99.65,
      "partlistara" : {
        "vp_osszes" : 1163,
        "megjelent" : 840,
        "szl_belyegtlen_urna" : 0,
        "szl_belyegzett_urna" : 838,
        "szl_elteres" : -2,
        "szl_ervenytelen" : 2,
        "szl_ervenyes" : 836
      },
      "nemzetisegre" : {
        "vp_osszes" : 10,
        "megjelent" : 9,
        "szl_belyegtlen_urna" : 0,
        "szl_belyegzett_urna" : 9,
        "szl_elteres" : 0,
        "szl_ervenytelen" : 1,
        "szl_ervenyes" : 8
      },
      "tetelek" : [ {
        "sorsz" : 6,
        "tl_id" : 952,
        "szavazat" : 384,
        "szavazat_szaz" : 45.5
      }, {
        "sorsz" : 1,
        "tl_id" : 950,
        "szavazat" : 346,
        "szavazat_szaz" : 41.0
      }, {
        "sorsz" : 5,
        "tl_id" : 942,
        "szavazat" : 40,
        "szavazat_szaz" : 4.74
      }, {
        "sorsz" : 3,
        "tl_id" : 951,
        "szavazat" : 37,
        "szavazat_szaz" : 4.38
      }, {
        "sorsz" : 4,
        "tl_id" : 954,
        "szavazat" : 21,
        "szavazat_szaz" : 2.49
      }, {
        "sorsz" : 2,
        "tl_id" : 955,
        "szavazat" : 8,
        "szavazat_szaz" : 0.95
      }, {
        "tl_id" : 938,
        "nemzkod" : "10",
        "szavazat" : 1,
        "szavazat_szaz" : 0.12
      }, {
        "tl_id" : 947,
        "nemzkod" : "5",
        "szavazat" : 7,
        "szavazat_szaz" : 0.83
      } ]
    }
  }, {
    "maz" : "14",
    "taz" : "034",
    "sorsz" : "030",
    "feldar" : 100.0,
    "egyeni_jkv" : {
      "allapot" : "3",
      "vp_osszes" : 966,
      "szavazott_osszesen" : 718,
      "szavazott_osszesen_szaz" : 74.33,
      "vp_lakcim_szerint" : 966,
      "megjel_lakcim_szerint" : 718,
      "megjel_lakcim_szerint_szaz" : 74.33,
      "szl_belyegtlen_urna" : 0,
      "szl_belyegzett_urna" : 718,
      "szl_elteres" : 0,
      "szl_ervenytelen" : 8,
      "szl_ervenytelen_szaz" : 1.11,
      "szl_ervenyes" : 710,
      "szl_ervenyes_szaz" : 98.89,
      "tetelek" : [ {
        "sorsz" : 5,
        "ej_id" : 71972,
        "szavazat" : 356,
        "szavazat_szaz" : 50.14
      }, {
        "sorsz" : 6,
        "ej_id" : 72007,
        "szavazat" : 290,
        "szavazat_szaz" : 40.85
      }, {
        "sorsz" : 2,
        "ej_id" : 72384,
        "szavazat" : 26,
        "szavazat_szaz" : 3.66
      }, {
        "sorsz" : 4,
        "ej_id" : 72469,
        "szavazat" : 23,
        "szavazat_szaz" : 3.24
      }, {
        "sorsz" : 7,
        "ej_id" : 72539,
        "szavazat" : 10,
        "szavazat_szaz" : 1.41
      }, {
        "sorsz" : 1,
        "ej_id" : 72547,
        "szavazat" : 3,
        "szavazat_szaz" : 0.42
      }, {
        "sorsz" : 3,
        "ej_id" : 72513,
        "szavazat" : 2,
        "szavazat_szaz" : 0.28
      } ]
    },
    "listas_jkv" : {
      "allapot" : "3",
      "vp_osszes" : 966,
      "szavazott_osszesen" : 718,
      "szavazott_osszesen_szaz" : 74.33,
      "vp_lakcim_szerint" : 966,
      "megjel_lakcim_szerint" : 718,
      "megjel_lakcim_szerint_szaz" : 74.33,
      "szl_belyegtlen_urna" : 0,
      "szl_belyegzett_urna" : 718,
      "szl_elteres" : 0,
      "szl_ervenytelen" : 3,
      "szl_ervenytelen_szaz" : 0.42,
      "szl_ervenyes" : 715,
      "szl_ervenyes_szaz" : 99.58,
      "partlistara" : {
        "vp_osszes" : 962,
        "megjelent" : 715,
        "szl_belyegtlen_urna" : 0,
        "szl_belyegzett_urna" : 715,
        "szl_elteres" : 0,
        "szl_ervenytelen" : 3,
        "szl_ervenyes" : 712
      },
      "nemzetisegre" : {
        "vp_osszes" : 4,
        "megjelent" : 3,
        "szl_belyegtlen_urna" : 0,
        "szl_belyegzett_urna" : 3,
        "szl_elteres" : 0,
        "szl_ervenytelen" : 0,
        "szl_ervenyes" : 3
      },
      "tetelek" : [ {
        "sorsz" : 6,
        "tl_id" : 952,
        "szavazat" : 333,
        "szavazat_szaz" : 46.57
      }, {
        "sorsz" : 1,
        "tl_id" : 950,
        "szavazat" : 290,
        "szavazat_szaz" : 40.56
      }, {
        "sorsz" : 3,
        "tl_id" : 951,
        "szavazat" : 37,
        "szavazat_szaz" : 5.17
      }, {
        "sorsz" : 5,
        "tl_id" : 942,
        "szavazat" : 35,
        "szavazat_szaz" : 4.9
      }, {
        "sorsz" : 4,
        "tl_id" : 954,
        "szavazat" : 14,
        "szavazat_szaz" : 1.96
      }, {
        "sorsz" : 2,
        "tl_id" : 955,
        "szavazat" : 3,
        "szavazat_szaz" : 0.42
      }, {
        "tl_id" : 947,
        "nemzkod" : "5",
        "szavazat" : 3,
        "szavazat_szaz" : 0.42
      } ]
    }
  } ]
}
