{
  "header" : {
    "generated" : "2022-04-02T23:30:00",
    "vl_id" : 333,
    "nvv_id" : 352
  },
  "data" : {
    "maz" : "18",
    "taz" : "125",
    "szavazokorok" : [ {
      "sorszam" : "001",
      "szk_nev" : "Nemeskeresztúr, 001. számú szavazókör",
      "evk" : "03",
      "evk_nev" : "VAS megye, 03. számú OEVK",
      "cim" : " Nemeskeresztúr, Kossuth u. 71. (Önkormányzati Hivatal)",
      "akadaly" : "I",
      "szamlKijelolt" : "N",
      "atjKijelolt" : "I",
      "telepSzintu" : "I",
      "letszam" : {
        "indulo" : 237,
        "honos" : 231,
        "atjel" : 4,
        "atjelInnen" : 6,
        "osszesen" : 235
      }
    } ]
  }
}
