{
  "header" : {
    "generated" : "2022-04-02T23:30:00",
    "vl_id" : 333,
    "nvv_id" : 352
  },
  "data" : {
    "maz" : "01",
    "taz" : "011",
    "szavazokorok" : [ {
      "sorszam" : "001",
      "szk_nev" : "Budapest XI. kerület, 001. számú szavazókör",
      "evk" : "02",
      "evk_nev" : "BUDAPEST főváros, 02. számú OEVK",
      "cim" : "1111 Budapest 11, Bartók Béla út 32. (B32 galéria)",
      "akadaly" : "I",
      "szamlKijelolt" : "N",
      "atjKijelolt" : "N",
      "telepSzintu" : "N",
      "letszam" : {
        "indulo" : 741,
        "honos" : 686,
        "atjel" : 0,
        "atjelInnen" : 56,
        "osszesen" : 686
      }
    }, {
      "sorszam" : "002",
      "szk_nev" : "Budapest XI. kerület, 002. számú szavazókör",
      "evk" : "02",
      "evk_nev" : "BUDAPEST főváros, 02. számú OEVK",
      "cim" : "1118 Budapest 11, Köbölkút utca 27-29. (Ált. Isk.)",
      "akadaly" : "N",
      "szamlKijelolt" : "N",
      "atjKijelolt" : "N",
      "telepSzintu" : "N",
      "letszam" : {
        "indulo" : 839,
        "honos" : 770,
        "atjel" : 0,
        "atjelInnen" : 56,
        "osszesen" : 770
      }
    }, {
      "sorszam" : "003",
      "szk_nev" : "Budapest XI. kerület, 003. számú szavazókör",
      "evk" : "02",
      "evk_nev" : "BUDAPEST főváros, 02. számú OEVK",
      "cim" : "1118 Budapest 11, Köbölkút utca 27-29. (Ált. Isk.)",
      "akadaly" : "N",
      "szamlKijelolt" : "N",
      "atjKijelolt" : "N",
      "telepSzintu" : "N",
      "letszam" : {
        "indulo" : 743,
        "honos" : 704,
        "atjel" : 0,
        "atjelInnen" : 43,
        "osszesen" : 704
      }
    }, {
      "sorszam" : "004",
      "szk_nev" : "Budapest XI. kerület, 004. számú szavazókör",
      "evk" : "02",
      "evk_nev" : "BUDAPEST főváros, 02. számú OEVK",
      "cim" : "1118 Budapest 11, Köbölkút utca 27-29. (Ált. Isk.)",
      "akadaly" : "N",
      "szamlKijelolt" : "N",
      "atjKijelolt" : "N",
      "telepSzintu" : "N",
      "letszam" : {
        "indulo" : 816,
        "honos" : 750,
        "atjel" : 0,
        "atjelInnen" : 63,
        "osszesen" : 750
      }
    }, {
      "sorszam" : "005",
      "szk_nev" : "Budapest XI. kerület, 005. számú szavazókör",
      "evk" : "02",
      "evk_nev" : "BUDAPEST főváros, 02. számú OEVK",
      "cim" : "1111 Budapest 11, Köbölkút utca 27-29. (Ált. Isk.)",
      "akadaly" : "N",
      "szamlKijelolt" : "N",
      "atjKijelolt" : "N",
      "telepSzintu" : "N",
      "letszam" : {
        "indulo" : 809,
        "honos" : 754,
        "atjel" : 0,
        "atjelInnen" : 52,
        "osszesen" : 754
      }
    }, {
      "sorszam" : "006",
      "szk_nev" : "Budapest XI. kerület, 006. számú szavazókör",
      "evk" : "02",
      "evk_nev" : "BUDAPEST főváros, 02. számú OEVK",
      "cim" : "1114 Budapest 11, Bartók Béla út 27. (Ált. Isk.)",
      "akadaly" : "N",
      "szamlKijelolt" : "N",
      "atjKijelolt" : "N",
      "telepSzintu" : "N",
      "letszam" : {
        "indulo" : 876,
        "honos" : 801,
        "atjel" : 0,
        "atjelInnen" : 75,
        "osszesen" : 801
      }
    }, {
      "sorszam" : "007",
      "szk_nev" : "Budapest XI. kerület, 007. számú szavazókör",
      "evk" : "02",
      "evk_nev" : "BUDAPEST főváros, 02. számú OEVK",
      "cim" : "1117 Budapest 11, Bartók Béla út 27. (Ált. Isk.)",
      "akadaly" : "N",
      "szamlKijelolt" : "N",
      "atjKijelolt" : "N",
      "telepSzintu" : "N",
      "letszam" : {
        "indulo" : 810,
        "honos" : 731,
        "atjel" : 0,
        "atjelInnen" : 75,
        "osszesen" : 731
      }
    }, {
      "sorszam" : "008",
      "szk_nev" : "Budapest XI. kerület, 008. számú szavazókör",
      "evk" : "02",
      "evk_nev" : "BUDAPEST főváros, 02. számú OEVK",
      "cim" : "1114 Budapest 11, Bartók Béla út 27. (Ált. Isk.)",
      "akadaly" : "N",
      "szamlKijelolt" : "N",
      "atjKijelolt" : "N",
      "telepSzintu" : "N",
      "letszam" : {
        "indulo" : 716,
        "honos" : 669,
        "atjel" : 0,
        "atjelInnen" : 44,
        "osszesen" : 669
      }
    }, {
      "sorszam" : "009",
      "szk_nev" : "Budapest XI. kerület, 009. számú szavazókör",
      "evk" : "02",
      "evk_nev" : "BUDAPEST főváros, 02. számú OEVK",
      "cim" : "1114 Budapest 11, Bartók Béla út 27. (Ált. Isk.)",
      "akadaly" : "N",
      "szamlKijelolt" : "N",
      "atjKijelolt" : "N",
      "telepSzintu" : "N",
      "letszam" : {
        "indulo" : 749,
        "honos" : 693,
        "atjel" : 0,
        "atjelInnen" : 55,
        "osszesen" : 693
      }
    }, {
      "sorszam" : "010",
      "szk_nev" : "Budapest XI. kerület, 010. számú szavazókör",
      "evk" : "02",
      "evk_nev" : "BUDAPEST főváros, 02. számú OEVK",
      "cim" : "1111 Budapest 11, Egry József utca 3-11. (Széchenyi Gimn.)",
      "akadaly" : "I",
      "szamlKijelolt" : "N",
      "atjKijelolt" : "N",
      "telepSzintu" : "N",
      "letszam" : {
        "indulo" : 1078,
        "honos" : 988,
        "atjel" : 0,
        "atjelInnen" : 74,
        "osszesen" : 988
      }
    }, {
      "sorszam" : "011",
      "szk_nev" : "Budapest XI. kerület, 011. számú szavazókör",
      "evk" : "02",
      "evk_nev" : "BUDAPEST főváros, 02. számú OEVK",
      "cim" : "1111 Budapest 11, Egry József utca 3-11. (Széchenyi Gimn.)",
      "akadaly" : "N",
      "szamlKijelolt" : "N",
      "atjKijelolt" : "N",
      "telepSzintu" : "N",
      "letszam" : {
        "indulo" : 997,
        "honos" : 926,
        "atjel" : 0,
        "atjelInnen" : 67,
        "osszesen" : 926
      }
    }, {
      "sorszam" : "012",
      "szk_nev" : "Budapest XI. kerület, 012. számú szavazókör",
      "evk" : "02",
      "evk_nev" : "BUDAPEST főváros, 02. számú OEVK",
      "cim" : "1111 Budapest 11, Egry József utca 3-11. (Széchenyi Gimn.)",
      "akadaly" : "N",
      "szamlKijelolt" : "N",
      "atjKijelolt" : "N",
      "telepSzintu" : "N",
      "letszam" : {
        "indulo" : 845,
        "honos" : 790,
        "atjel" : 0,
        "atjelInnen" : 58,
        "osszesen" : 790
      }
    }, {
      "sorszam" : "013",
      "szk_nev" : "Budapest XI. kerület, 013. számú szavazókör",
      "evk" : "02",
      "evk_nev" : "BUDAPEST főváros, 02. számú OEVK",
      "cim" : "1111 Budapest 11, Egry József utca 3-11. (Széchenyi Gimn.)",
      "akadaly" : "N",
      "szamlKijelolt" : "N",
      "atjKijelolt" : "N",
      "telepSzintu" : "N",
      "letszam" : {
        "indulo" : 786,
        "honos" : 727,
        "atjel" : 0,
        "atjelInnen" : 51,
        "osszesen" : 727
      }
    }, {
      "sorszam" : "014",
      "szk_nev" : "Budapest XI. kerület, 014. számú szavazókör",
      "evk" : "02",
      "evk_nev" : "BUDAPEST főváros, 02. számú OEVK",
      "cim" : "1111 Budapest 11, Egry József utca 3-11. (Széchenyi Gimn.)",
      "akadaly" : "N",
      "szamlKijelolt" : "N",
      "atjKijelolt" : "N",
      "telepSzintu" : "N",
      "letszam" : {
        "indulo" : 968,
        "honos" : 912,
        "atjel" : 0,
        "atjelInnen" : 62,
        "osszesen" : 912
      }
    }, {
      "sorszam" : "015",
      "szk_nev" : "Budapest XI. kerület, 015. számú szavazókör",
      "evk" : "02",
      "evk_nev" : "BUDAPEST főváros, 02. számú OEVK",
      "cim" : "1117 Budapest 11, Bogdánfy utca 5/B. (Gimnázium)",
      "akadaly" : "N",
      "szamlKijelolt" : "N",
      "atjKijelolt" : "N",
      "telepSzintu" : "N",
      "letszam" : {
        "indulo" : 726,
        "honos" : 691,
        "atjel" : 0,
        "atjelInnen" : 35,
        "osszesen" : 691
      }
    }, {
      "sorszam" : "016",
      "szk_nev" : "Budapest XI. kerület, 016. számú szavazókör",
      "evk" : "02",
      "evk_nev" : "BUDAPEST főváros, 02. számú OEVK",
      "cim" : "1117 Budapest 11, Bogdánfy utca 5/B. (Gimnázium)",
      "akadaly" : "N",
      "szamlKijelolt" : "N",
      "atjKijelolt" : "N",
      "telepSzintu" : "N",
      "letszam" : {
        "indulo" : 783,
        "honos" : 730,
        "atjel" : 0,
        "atjelInnen" : 48,
        "osszesen" : 730
      }
    }, {
      "sorszam" : "017",
      "szk_nev" : "Budapest XI. kerület, 017. számú szavazókör",
      "evk" : "02",
      "evk_nev" : "BUDAPEST főváros, 02. számú OEVK",
      "cim" : "1117 Budapest 11, Baranyai utca 16-18. (Ált. Isk.)",
      "akadaly" : "I",
      "szamlKijelolt" : "N",
      "atjKijelolt" : "N",
      "telepSzintu" : "N",
      "letszam" : {
        "indulo" : 748,
        "honos" : 714,
        "atjel" : 0,
        "atjelInnen" : 44,
        "osszesen" : 714
      }
    }, {
      "sorszam" : "018",
      "szk_nev" : "Budapest XI. kerület, 018. számú szavazókör",
      "evk" : "02",
      "evk_nev" : "BUDAPEST főváros, 02. számú OEVK",
      "cim" : "1117 Budapest 11, Baranyai utca 16-18. (Ált. Isk.)",
      "akadaly" : "N",
      "szamlKijelolt" : "N",
      "atjKijelolt" : "N",
      "telepSzintu" : "N",
      "letszam" : {
        "indulo" : 879,
        "honos" : 834,
        "atjel" : 0,
        "atjelInnen" : 39,
        "osszesen" : 834
      }
    }, {
      "sorszam" : "019",
      "szk_nev" : "Budapest XI. kerület, 019. számú szavazókör",
      "evk" : "02",
      "evk_nev" : "BUDAPEST főváros, 02. számú OEVK",
      "cim" : "1117 Budapest 11, Baranyai utca 16-18. (Ált. Isk.)",
      "akadaly" : "N",
      "szamlKijelolt" : "N",
      "atjKijelolt" : "N",
      "telepSzintu" : "N",
      "letszam" : {
        "indulo" : 736,
        "honos" : 681,
        "atjel" : 0,
        "atjelInnen" : 46,
        "osszesen" : 681
      }
    }, {
      "sorszam" : "020",
      "szk_nev" : "Budapest XI. kerület, 020. számú szavazókör",
      "evk" : "02",
      "evk_nev" : "BUDAPEST főváros, 02. számú OEVK",
      "cim" : "1117 Budapest 11, Váli utca 1. (Gimnázium)",
      "akadaly" : "N",
      "szamlKijelolt" : "N",
      "atjKijelolt" : "N",
      "telepSzintu" : "N",
      "letszam" : {
        "indulo" : 827,
        "honos" : 770,
        "atjel" : 0,
        "atjelInnen" : 54,
        "osszesen" : 770
      }
    }, {
      "sorszam" : "021",
      "szk_nev" : "Budapest XI. kerület, 021. számú szavazókör",
      "evk" : "02",
      "evk_nev" : "BUDAPEST főváros, 02. számú OEVK",
      "cim" : "1117 Budapest 11, Váli utca 1. (Gimnázium)",
      "akadaly" : "N",
      "szamlKijelolt" : "N",
      "atjKijelolt" : "N",
      "telepSzintu" : "N",
      "letszam" : {
        "indulo" : 818,
        "honos" : 750,
        "atjel" : 0,
        "atjelInnen" : 63,
        "osszesen" : 750
      }
    }, {
      "sorszam" : "022",
      "szk_nev" : "Budapest XI. kerület, 022. számú szavazókör",
      "evk" : "02",
      "evk_nev" : "BUDAPEST főváros, 02. számú OEVK",
      "cim" : "1117 Budapest 11, Váli utca 1. (Gimnázium)",
      "akadaly" : "N",
      "szamlKijelolt" : "N",
      "atjKijelolt" : "N",
      "telepSzintu" : "N",
      "letszam" : {
        "indulo" : 690,
        "honos" : 655,
        "atjel" : 0,
        "atjelInnen" : 42,
        "osszesen" : 655
      }
    }, {
      "sorszam" : "023",
      "szk_nev" : "Budapest XI. kerület, 023. számú szavazókör",
      "evk" : "02",
      "evk_nev" : "BUDAPEST főváros, 02. számú OEVK",
      "cim" : "1117 Budapest 11, Váli utca 1. (Gimnázium)",
      "akadaly" : "N",
      "szamlKijelolt" : "N",
      "atjKijelolt" : "N",
      "telepSzintu" : "N",
      "letszam" : {
        "indulo" : 849,
        "honos" : 786,
        "atjel" : 0,
        "atjelInnen" : 56,
        "osszesen" : 786
      }
    }, {
      "sorszam" : "024",
      "szk_nev" : "Budapest XI. kerület, 024. számú szavazókör",
      "evk" : "02",
      "evk_nev" : "BUDAPEST főváros, 02. számú OEVK",
      "cim" : "1117 Budapest 11, Váli utca 1. (Gimnázium)",
      "akadaly" : "N",
      "szamlKijelolt" : "N",
      "atjKijelolt" : "N",
      "telepSzintu" : "N",
      "letszam" : {
        "indulo" : 819,
        "honos" : 760,
        "atjel" : 0,
        "atjelInnen" : 49,
        "osszesen" : 760
      }
    }, {
      "sorszam" : "025",
      "szk_nev" : "Budapest XI. kerület, 025. számú szavazókör",
      "evk" : "02",
      "evk_nev" : "BUDAPEST főváros, 02. számú OEVK",
      "cim" : "1117 Budapest 11, Baranyai utca 16-18. (Ált. Isk.)",
      "akadaly" : "N",
      "szamlKijelolt" : "N",
      "atjKijelolt" : "N",
      "telepSzintu" : "N",
      "letszam" : {
        "indulo" : 821,
        "honos" : 761,
        "atjel" : 0,
        "atjelInnen" : 48,
        "osszesen" : 761
      }
    }, {
      "sorszam" : "026",
      "szk_nev" : "Budapest XI. kerület, 026. számú szavazókör",
      "evk" : "02",
      "evk_nev" : "BUDAPEST főváros, 02. számú OEVK",
      "cim" : "1117 Budapest 11, Baranyai utca 16-18. (Ált. Isk.)",
      "akadaly" : "N",
      "szamlKijelolt" : "N",
      "atjKijelolt" : "N",
      "telepSzintu" : "N",
      "letszam" : {
        "indulo" : 929,
        "honos" : 873,
        "atjel" : 0,
        "atjelInnen" : 52,
        "osszesen" : 873
      }
    }, {
      "sorszam" : "027",
      "szk_nev" : "Budapest XI. kerület, 027. számú szavazókör",
      "evk" : "02",
      "evk_nev" : "BUDAPEST főváros, 02. számú OEVK",
      "cim" : "1117 Budapest 11, Baranyai utca 16-18. (Ált. Isk.)",
      "akadaly" : "N",
      "szamlKijelolt" : "N",
      "atjKijelolt" : "N",
      "telepSzintu" : "N",
      "letszam" : {
        "indulo" : 837,
        "honos" : 777,
        "atjel" : 0,
        "atjelInnen" : 58,
        "osszesen" : 777
      }
    }, {
      "sorszam" : "028",
      "szk_nev" : "Budapest XI. kerület, 028. számú szavazókör",
      "evk" : "02",
      "evk_nev" : "BUDAPEST főváros, 02. számú OEVK",
      "cim" : "1113 Budapest 11, Bocskai út 47-49. (Ált. Isk.)",
      "akadaly" : "I",
      "szamlKijelolt" : "N",
      "atjKijelolt" : "N",
      "telepSzintu" : "N",
      "letszam" : {
        "indulo" : 1044,
        "honos" : 981,
        "atjel" : 0,
        "atjelInnen" : 60,
        "osszesen" : 981
      }
    }, {
      "sorszam" : "029",
      "szk_nev" : "Budapest XI. kerület, 029. számú szavazókör",
      "evk" : "02",
      "evk_nev" : "BUDAPEST főváros, 02. számú OEVK",
      "cim" : "1113 Budapest 11, Aga utca 10. (Óvoda)",
      "akadaly" : "N",
      "szamlKijelolt" : "N",
      "atjKijelolt" : "N",
      "telepSzintu" : "N",
      "letszam" : {
        "indulo" : 812,
        "honos" : 757,
        "atjel" : 0,
        "atjelInnen" : 56,
        "osszesen" : 757
      }
    }, {
      "sorszam" : "030",
      "szk_nev" : "Budapest XI. kerület, 030. számú szavazókör",
      "evk" : "02",
      "evk_nev" : "BUDAPEST főváros, 02. számú OEVK",
      "cim" : "1113 Budapest 11, Aga utca 10. (Óvoda)",
      "akadaly" : "N",
      "szamlKijelolt" : "N",
      "atjKijelolt" : "N",
      "telepSzintu" : "N",
      "letszam" : {
        "indulo" : 766,
        "honos" : 730,
        "atjel" : 0,
        "atjelInnen" : 46,
        "osszesen" : 730
      }
    }, {
      "sorszam" : "031",
      "szk_nev" : "Budapest XI. kerület, 031. számú szavazókör",
      "evk" : "02",
      "evk_nev" : "BUDAPEST főváros, 02. számú OEVK",
      "cim" : "1113 Budapest 11, Bocskai út 47-49. (Ált. Isk.)",
      "akadaly" : "N",
      "szamlKijelolt" : "N",
      "atjKijelolt" : "N",
      "telepSzintu" : "N",
      "letszam" : {
        "indulo" : 1020,
        "honos" : 953,
        "atjel" : 0,
        "atjelInnen" : 57,
        "osszesen" : 953
      }
    }, {
      "sorszam" : "032",
      "szk_nev" : "Budapest XI. kerület, 032. számú szavazókör",
      "evk" : "02",
      "evk_nev" : "BUDAPEST főváros, 02. számú OEVK",
      "cim" : "1113 Budapest 11, Bocskai út 47-49. (Ált. Isk.)",
      "akadaly" : "N",
      "szamlKijelolt" : "N",
      "atjKijelolt" : "N",
      "telepSzintu" : "N",
      "letszam" : {
        "indulo" : 1115,
        "honos" : 1028,
        "atjel" : 0,
        "atjelInnen" : 82,
        "osszesen" : 1028
      }
    }, {
      "sorszam" : "033",
      "szk_nev" : "Budapest XI. kerület, 033. számú szavazókör",
      "evk" : "02",
      "evk_nev" : "BUDAPEST főváros, 02. számú OEVK",
      "cim" : "1113 Budapest 11, Bocskai út 47-49. (Ált. Isk.)",
      "akadaly" : "I",
      "szamlKijelolt" : "N",
      "atjKijelolt" : "N",
      "telepSzintu" : "I",
      "letszam" : {
        "indulo" : 954,
        "honos" : 894,
        "atjel" : 0,
        "atjelInnen" : 54,
        "osszesen" : 894
      }
    }, {
      "sorszam" : "034",
      "szk_nev" : "Budapest XI. kerület, 034. számú szavazókör",
      "evk" : "02",
      "evk_nev" : "BUDAPEST főváros, 02. számú OEVK",
      "cim" : "1113 Budapest 11, Bocskai út 47-49. (Ált. Isk.)",
      "akadaly" : "N",
      "szamlKijelolt" : "N",
      "atjKijelolt" : "N",
      "telepSzintu" : "N",
      "letszam" : {
        "indulo" : 891,
        "honos" : 839,
        "atjel" : 0,
        "atjelInnen" : 47,
        "osszesen" : 839
      }
    }, {
      "sorszam" : "035",
      "szk_nev" : "Budapest XI. kerület, 035. számú szavazókör",
      "evk" : "02",
      "evk_nev" : "BUDAPEST főváros, 02. számú OEVK",
      "cim" : "1118 Budapest 11, Zólyomi út 20-22. (Óvoda)",
      "akadaly" : "N",
      "szamlKijelolt" : "N",
      "atjKijelolt" : "N",
      "telepSzintu" : "N",
      "letszam" : {
        "indulo" : 835,
        "honos" : 785,
        "atjel" : 0,
        "atjelInnen" : 47,
        "osszesen" : 785
      }
    }, {
      "sorszam" : "036",
      "szk_nev" : "Budapest XI. kerület, 036. számú szavazókör",
      "evk" : "02",
      "evk_nev" : "BUDAPEST főváros, 02. számú OEVK",
      "cim" : "1118 Budapest 11, Zólyomi út 20-22. (Óvoda)",
      "akadaly" : "N",
      "szamlKijelolt" : "N",
      "atjKijelolt" : "N",
      "telepSzintu" : "N",
      "letszam" : {
        "indulo" : 766,
        "honos" : 721,
        "atjel" : 0,
        "atjelInnen" : 40,
        "osszesen" : 721
      }
    }, {
      "sorszam" : "037",
      "szk_nev" : "Budapest XI. kerület, 037. számú szavazókör",
      "evk" : "02",
      "evk_nev" : "BUDAPEST főváros, 02. számú OEVK",
      "cim" : "1112 Budapest 11, Érdi út 2. (Ált. Isk.)",
      "akadaly" : "I",
      "szamlKijelolt" : "N",
      "atjKijelolt" : "N",
      "telepSzintu" : "N",
      "letszam" : {
        "indulo" : 912,
        "honos" : 864,
        "atjel" : 0,
        "atjelInnen" : 44,
        "osszesen" : 864
      }
    }, {
      "sorszam" : "038",
      "szk_nev" : "Budapest XI. kerület, 038. számú szavazókör",
      "evk" : "02",
      "evk_nev" : "BUDAPEST főváros, 02. számú OEVK",
      "cim" : "1118 Budapest 11, Dayka Gábor utca 4/B. (Óvoda)",
      "akadaly" : "N",
      "szamlKijelolt" : "N",
      "atjKijelolt" : "N",
      "telepSzintu" : "N",
      "letszam" : {
        "indulo" : 863,
        "honos" : 805,
        "atjel" : 0,
        "atjelInnen" : 43,
        "osszesen" : 805
      }
    }, {
      "sorszam" : "039",
      "szk_nev" : "Budapest XI. kerület, 039. számú szavazókör",
      "evk" : "02",
      "evk_nev" : "BUDAPEST főváros, 02. számú OEVK",
      "cim" : "1118 Budapest 11, Dayka Gábor utca 4/B. (Óvoda)",
      "akadaly" : "N",
      "szamlKijelolt" : "N",
      "atjKijelolt" : "N",
      "telepSzintu" : "N",
      "letszam" : {
        "indulo" : 767,
        "honos" : 727,
        "atjel" : 0,
        "atjelInnen" : 32,
        "osszesen" : 727
      }
    }, {
      "sorszam" : "040",
      "szk_nev" : "Budapest XI. kerület, 040. számú szavazókör",
      "evk" : "02",
      "evk_nev" : "BUDAPEST főváros, 02. számú OEVK",
      "cim" : "1118 Budapest 11, Dayka Gábor utca 4/B. (Óvoda)",
      "akadaly" : "N",
      "szamlKijelolt" : "N",
      "atjKijelolt" : "N",
      "telepSzintu" : "N",
      "letszam" : {
        "indulo" : 974,
        "honos" : 910,
        "atjel" : 0,
        "atjelInnen" : 61,
        "osszesen" : 910
      }
    }, {
      "sorszam" : "041",
      "szk_nev" : "Budapest XI. kerület, 041. számú szavazókör",
      "evk" : "02",
      "evk_nev" : "BUDAPEST főváros, 02. számú OEVK",
      "cim" : "1112 Budapest 11, Érdi út 2. (Ált. Isk.)",
      "akadaly" : "I",
      "szamlKijelolt" : "N",
      "atjKijelolt" : "N",
      "telepSzintu" : "N",
      "letszam" : {
        "indulo" : 977,
        "honos" : 933,
        "atjel" : 0,
        "atjelInnen" : 41,
        "osszesen" : 933
      }
    }, {
      "sorszam" : "042",
      "szk_nev" : "Budapest XI. kerület, 042. számú szavazókör",
      "evk" : "02",
      "evk_nev" : "BUDAPEST főváros, 02. számú OEVK",
      "cim" : "1112 Budapest 11, Érdi út 2. (Ált. Isk.)",
      "akadaly" : "N",
      "szamlKijelolt" : "N",
      "atjKijelolt" : "N",
      "telepSzintu" : "N",
      "letszam" : {
        "indulo" : 921,
        "honos" : 865,
        "atjel" : 0,
        "atjelInnen" : 48,
        "osszesen" : 865
      }
    }, {
      "sorszam" : "043",
      "szk_nev" : "Budapest XI. kerület, 043. számú szavazókör",
      "evk" : "02",
      "evk_nev" : "BUDAPEST főváros, 02. számú OEVK",
      "cim" : "1112 Budapest 11, Érdi út 2. (Ált. Isk.)",
      "akadaly" : "N",
      "szamlKijelolt" : "N",
      "atjKijelolt" : "N",
      "telepSzintu" : "N",
      "letszam" : {
        "indulo" : 838,
        "honos" : 769,
        "atjel" : 0,
        "atjelInnen" : 57,
        "osszesen" : 769
      }
    }, {
      "sorszam" : "044",
      "szk_nev" : "Budapest XI. kerület, 044. számú szavazókör",
      "evk" : "02",
      "evk_nev" : "BUDAPEST főváros, 02. számú OEVK",
      "cim" : "1118 Budapest 11, Csiki-hegyek utca 13-15. (Ált. Isk.)",
      "akadaly" : "I",
      "szamlKijelolt" : "N",
      "atjKijelolt" : "N",
      "telepSzintu" : "N",
      "letszam" : {
        "indulo" : 977,
        "honos" : 921,
        "atjel" : 0,
        "atjelInnen" : 48,
        "osszesen" : 921
      }
    }, {
      "sorszam" : "045",
      "szk_nev" : "Budapest XI. kerület, 045. számú szavazókör",
      "evk" : "02",
      "evk_nev" : "BUDAPEST főváros, 02. számú OEVK",
      "cim" : "1118 Budapest 11, Csiki-hegyek utca 13-15. (Ált. Isk.)",
      "akadaly" : "I",
      "szamlKijelolt" : "N",
      "atjKijelolt" : "N",
      "telepSzintu" : "N",
      "letszam" : {
        "indulo" : 1162,
        "honos" : 1103,
        "atjel" : 0,
        "atjelInnen" : 52,
        "osszesen" : 1103
      }
    }, {
      "sorszam" : "046",
      "szk_nev" : "Budapest XI. kerület, 046. számú szavazókör",
      "evk" : "02",
      "evk_nev" : "BUDAPEST főváros, 02. számú OEVK",
      "cim" : "1118 Budapest 11, Csiki-hegyek utca 13-15. (Ált. Isk.)",
      "akadaly" : "I",
      "szamlKijelolt" : "N",
      "atjKijelolt" : "N",
      "telepSzintu" : "N",
      "letszam" : {
        "indulo" : 953,
        "honos" : 901,
        "atjel" : 0,
        "atjelInnen" : 55,
        "osszesen" : 901
      }
    }, {
      "sorszam" : "047",
      "szk_nev" : "Budapest XI. kerület, 047. számú szavazókör",
      "evk" : "02",
      "evk_nev" : "BUDAPEST főváros, 02. számú OEVK",
      "cim" : "1118 Budapest 11, Beregszász út 10. (Öveges Szakgimn. és SZKI)",
      "akadaly" : "N",
      "szamlKijelolt" : "N",
      "atjKijelolt" : "N",
      "telepSzintu" : "N",
      "letszam" : {
        "indulo" : 1128,
        "honos" : 1069,
        "atjel" : 0,
        "atjelInnen" : 54,
        "osszesen" : 1069
      }
    }, {
      "sorszam" : "048",
      "szk_nev" : "Budapest XI. kerület, 048. számú szavazókör",
      "evk" : "02",
      "evk_nev" : "BUDAPEST főváros, 02. számú OEVK",
      "cim" : "1118 Budapest 11, Törökugrató utca 15. (Ált. Isk.)",
      "akadaly" : "N",
      "szamlKijelolt" : "N",
      "atjKijelolt" : "N",
      "telepSzintu" : "N",
      "letszam" : {
        "indulo" : 821,
        "honos" : 770,
        "atjel" : 0,
        "atjelInnen" : 43,
        "osszesen" : 770
      }
    }, {
      "sorszam" : "049",
      "szk_nev" : "Budapest XI. kerület, 049. számú szavazókör",
      "evk" : "02",
      "evk_nev" : "BUDAPEST főváros, 02. számú OEVK",
      "cim" : "1118 Budapest 11, Törökugrató utca 15. (Ált. Isk.)",
      "akadaly" : "N",
      "szamlKijelolt" : "N",
      "atjKijelolt" : "N",
      "telepSzintu" : "N",
      "letszam" : {
        "indulo" : 862,
        "honos" : 831,
        "atjel" : 0,
        "atjelInnen" : 27,
        "osszesen" : 831
      }
    }, {
      "sorszam" : "050",
      "szk_nev" : "Budapest XI. kerület, 050. számú szavazókör",
      "evk" : "02",
      "evk_nev" : "BUDAPEST főváros, 02. számú OEVK",
      "cim" : "1118 Budapest 11, Törökugrató utca 15. (Ált. Isk.)",
      "akadaly" : "N",
      "szamlKijelolt" : "N",
      "atjKijelolt" : "N",
      "telepSzintu" : "N",
      "letszam" : {
        "indulo" : 733,
        "honos" : 699,
        "atjel" : 0,
        "atjelInnen" : 29,
        "osszesen" : 699
      }
    }, {
      "sorszam" : "051",
      "szk_nev" : "Budapest XI. kerület, 051. számú szavazókör",
      "evk" : "02",
      "evk_nev" : "BUDAPEST főváros, 02. számú OEVK",
      "cim" : "1118 Budapest 11, Törökugrató utca 15. (Ált. Isk.)",
      "akadaly" : "N",
      "szamlKijelolt" : "N",
      "atjKijelolt" : "N",
      "telepSzintu" : "N",
      "letszam" : {
        "indulo" : 791,
        "honos" : 762,
        "atjel" : 0,
        "atjelInnen" : 25,
        "osszesen" : 762
      }
    }, {
      "sorszam" : "052",
      "szk_nev" : "Budapest XI. kerület, 052. számú szavazókör",
      "evk" : "02",
      "evk_nev" : "BUDAPEST főváros, 02. számú OEVK",
      "cim" : "1118 Budapest 11, Törökugrató utca 15. (Ált. Isk.)",
      "akadaly" : "N",
      "szamlKijelolt" : "N",
      "atjKijelolt" : "N",
      "telepSzintu" : "N",
      "letszam" : {
        "indulo" : 762,
        "honos" : 741,
        "atjel" : 0,
        "atjelInnen" : 22,
        "osszesen" : 741
      }
    }, {
      "sorszam" : "053",
      "szk_nev" : "Budapest XI. kerület, 053. számú szavazókör",
      "evk" : "02",
      "evk_nev" : "BUDAPEST főváros, 02. számú OEVK",
      "cim" : "1118 Budapest 11, Csiki-hegyek utca 13-15. (Ált. Isk.)",
      "akadaly" : "I",
      "szamlKijelolt" : "N",
      "atjKijelolt" : "N",
      "telepSzintu" : "N",
      "letszam" : {
        "indulo" : 860,
        "honos" : 820,
        "atjel" : 0,
        "atjelInnen" : 37,
        "osszesen" : 820
      }
    }, {
      "sorszam" : "054",
      "szk_nev" : "Budapest XI. kerület, 054. számú szavazókör",
      "evk" : "02",
      "evk_nev" : "BUDAPEST főváros, 02. számú OEVK",
      "cim" : "1118 Budapest 11, Csiki-hegyek utca 13-15. (Ált. Isk.)",
      "akadaly" : "I",
      "szamlKijelolt" : "N",
      "atjKijelolt" : "N",
      "telepSzintu" : "N",
      "letszam" : {
        "indulo" : 821,
        "honos" : 783,
        "atjel" : 0,
        "atjelInnen" : 34,
        "osszesen" : 783
      }
    }, {
      "sorszam" : "055",
      "szk_nev" : "Budapest XI. kerület, 055. számú szavazókör",
      "evk" : "02",
      "evk_nev" : "BUDAPEST főváros, 02. számú OEVK",
      "cim" : "1118 Budapest 11, Csiki-hegyek utca 13-15. (Ált. Isk.)",
      "akadaly" : "I",
      "szamlKijelolt" : "N",
      "atjKijelolt" : "N",
      "telepSzintu" : "N",
      "letszam" : {
        "indulo" : 748,
        "honos" : 717,
        "atjel" : 0,
        "atjelInnen" : 22,
        "osszesen" : 717
      }
    }, {
      "sorszam" : "056",
      "szk_nev" : "Budapest XI. kerület, 056. számú szavazókör",
      "evk" : "02",
      "evk_nev" : "BUDAPEST főváros, 02. számú OEVK",
      "cim" : "1118 Budapest 11, Csiki-hegyek utca 13-15. (Ált. Isk.)",
      "akadaly" : "I",
      "szamlKijelolt" : "N",
      "atjKijelolt" : "N",
      "telepSzintu" : "N",
      "letszam" : {
        "indulo" : 683,
        "honos" : 658,
        "atjel" : 0,
        "atjelInnen" : 24,
        "osszesen" : 658
      }
    }, {
      "sorszam" : "057",
      "szk_nev" : "Budapest XI. kerület, 057. számú szavazókör",
      "evk" : "02",
      "evk_nev" : "BUDAPEST főváros, 02. számú OEVK",
      "cim" : "1118 Budapest 11, Törökugrató utca 15. (Ált. Isk.)",
      "akadaly" : "N",
      "szamlKijelolt" : "N",
      "atjKijelolt" : "N",
      "telepSzintu" : "N",
      "letszam" : {
        "indulo" : 1041,
        "honos" : 1032,
        "atjel" : 0,
        "atjelInnen" : 41,
        "osszesen" : 1032
      }
    }, {
      "sorszam" : "058",
      "szk_nev" : "Budapest XI. kerület, 058. számú szavazókör",
      "evk" : "02",
      "evk_nev" : "BUDAPEST főváros, 02. számú OEVK",
      "cim" : "1118 Budapest 11, Törökugrató utca 15. (Ált. Isk.)",
      "akadaly" : "N",
      "szamlKijelolt" : "N",
      "atjKijelolt" : "N",
      "telepSzintu" : "N",
      "letszam" : {
        "indulo" : 1013,
        "honos" : 958,
        "atjel" : 0,
        "atjelInnen" : 52,
        "osszesen" : 958
      }
    }, {
      "sorszam" : "059",
      "szk_nev" : "Budapest XI. kerület, 059. számú szavazókör",
      "evk" : "02",
      "evk_nev" : "BUDAPEST főváros, 02. számú OEVK",
      "cim" : "1112 Budapest 11, Menyecske utca 2. (Ált. Isk.)",
      "akadaly" : "I",
      "szamlKijelolt" : "N",
      "atjKijelolt" : "N",
      "telepSzintu" : "N",
      "letszam" : {
        "indulo" : 1080,
        "honos" : 1079,
        "atjel" : 0,
        "atjelInnen" : 60,
        "osszesen" : 1079
      }
    }, {
      "sorszam" : "060",
      "szk_nev" : "Budapest XI. kerület, 060. számú szavazókör",
      "evk" : "02",
      "evk_nev" : "BUDAPEST főváros, 02. számú OEVK",
      "cim" : "1118 Budapest 11, Beregszász út 10. (Öveges Szakgimn. és SZKI)",
      "akadaly" : "N",
      "szamlKijelolt" : "N",
      "atjKijelolt" : "N",
      "telepSzintu" : "N",
      "letszam" : {
        "indulo" : 1235,
        "honos" : 1169,
        "atjel" : 0,
        "atjelInnen" : 80,
        "osszesen" : 1169
      }
    }, {
      "sorszam" : "061",
      "szk_nev" : "Budapest XI. kerület, 061. számú szavazókör",
      "evk" : "02",
      "evk_nev" : "BUDAPEST főváros, 02. számú OEVK",
      "cim" : "1118 Budapest 11, Beregszász út 10. (Öveges Szakgimn. és SZKI)",
      "akadaly" : "N",
      "szamlKijelolt" : "N",
      "atjKijelolt" : "N",
      "telepSzintu" : "N",
      "letszam" : {
        "indulo" : 1132,
        "honos" : 1067,
        "atjel" : 0,
        "atjelInnen" : 60,
        "osszesen" : 1067
      }
    }, {
      "sorszam" : "062",
      "szk_nev" : "Budapest XI. kerület, 062. számú szavazókör",
      "evk" : "02",
      "evk_nev" : "BUDAPEST főváros, 02. számú OEVK",
      "cim" : "1112 Budapest 11, Menyecske utca 2. (Ált. Isk.)",
      "akadaly" : "I",
      "szamlKijelolt" : "N",
      "atjKijelolt" : "N",
      "telepSzintu" : "N",
      "letszam" : {
        "indulo" : 1059,
        "honos" : 1014,
        "atjel" : 0,
        "atjelInnen" : 38,
        "osszesen" : 1014
      }
    }, {
      "sorszam" : "063",
      "szk_nev" : "Budapest XI. kerület, 063. számú szavazókör",
      "evk" : "02",
      "evk_nev" : "BUDAPEST főváros, 02. számú OEVK",
      "cim" : "1112 Budapest 11, Menyecske utca 2. (Ált. Isk.)",
      "akadaly" : "N",
      "szamlKijelolt" : "N",
      "atjKijelolt" : "N",
      "telepSzintu" : "N",
      "letszam" : {
        "indulo" : 949,
        "honos" : 912,
        "atjel" : 0,
        "atjelInnen" : 30,
        "osszesen" : 912
      }
    }, {
      "sorszam" : "064",
      "szk_nev" : "Budapest XI. kerület, 064. számú szavazókör",
      "evk" : "02",
      "evk_nev" : "BUDAPEST főváros, 02. számú OEVK",
      "cim" : "1112 Budapest 11, Menyecske utca 2. (Ált. Isk.)",
      "akadaly" : "N",
      "szamlKijelolt" : "N",
      "atjKijelolt" : "N",
      "telepSzintu" : "N",
      "letszam" : {
        "indulo" : 809,
        "honos" : 762,
        "atjel" : 0,
        "atjelInnen" : 39,
        "osszesen" : 762
      }
    }, {
      "sorszam" : "065",
      "szk_nev" : "Budapest XI. kerület, 065. számú szavazókör",
      "evk" : "02",
      "evk_nev" : "BUDAPEST főváros, 02. számú OEVK",
      "cim" : "1112 Budapest 11, Menyecske utca 2. (Ált. Isk.)",
      "akadaly" : "N",
      "szamlKijelolt" : "N",
      "atjKijelolt" : "N",
      "telepSzintu" : "N",
      "letszam" : {
        "indulo" : 1018,
        "honos" : 980,
        "atjel" : 0,
        "atjelInnen" : 25,
        "osszesen" : 980
      }
    }, {
      "sorszam" : "066",
      "szk_nev" : "Budapest XI. kerület, 066. számú szavazókör",
      "evk" : "02",
      "evk_nev" : "BUDAPEST főváros, 02. számú OEVK",
      "cim" : "1115 Budapest 11, Bartók Béla út 141. (Ált. Isk.)",
      "akadaly" : "N",
      "szamlKijelolt" : "N",
      "atjKijelolt" : "N",
      "telepSzintu" : "N",
      "letszam" : {
        "indulo" : 757,
        "honos" : 711,
        "atjel" : 0,
        "atjelInnen" : 39,
        "osszesen" : 711
      }
    }, {
      "sorszam" : "067",
      "szk_nev" : "Budapest XI. kerület, 067. számú szavazókör",
      "evk" : "02",
      "evk_nev" : "BUDAPEST főváros, 02. számú OEVK",
      "cim" : "1115 Budapest 11, Keveháza utca 2. (Ált. Isk.)",
      "akadaly" : "N",
      "szamlKijelolt" : "N",
      "atjKijelolt" : "N",
      "telepSzintu" : "N",
      "letszam" : {
        "indulo" : 931,
        "honos" : 883,
        "atjel" : 0,
        "atjelInnen" : 46,
        "osszesen" : 883
      }
    }, {
      "sorszam" : "068",
      "szk_nev" : "Budapest XI. kerület, 068. számú szavazókör",
      "evk" : "02",
      "evk_nev" : "BUDAPEST főváros, 02. számú OEVK",
      "cim" : "1114 Budapest 11, Bartók Béla út 141. (Ált. Isk.)",
      "akadaly" : "N",
      "szamlKijelolt" : "N",
      "atjKijelolt" : "N",
      "telepSzintu" : "N",
      "letszam" : {
        "indulo" : 720,
        "honos" : 670,
        "atjel" : 0,
        "atjelInnen" : 37,
        "osszesen" : 670
      }
    }, {
      "sorszam" : "069",
      "szk_nev" : "Budapest XI. kerület, 069. számú szavazókör",
      "evk" : "02",
      "evk_nev" : "BUDAPEST főváros, 02. számú OEVK",
      "cim" : "1115 Budapest 11, Bartók Béla út 141. (Ált. Isk.)",
      "akadaly" : "N",
      "szamlKijelolt" : "N",
      "atjKijelolt" : "N",
      "telepSzintu" : "N",
      "letszam" : {
        "indulo" : 756,
        "honos" : 706,
        "atjel" : 0,
        "atjelInnen" : 34,
        "osszesen" : 706
      }
    }, {
      "sorszam" : "070",
      "szk_nev" : "Budapest XI. kerület, 070. számú szavazókör",
      "evk" : "02",
      "evk_nev" : "BUDAPEST főváros, 02. számú OEVK",
      "cim" : "1119 Budapest 11, Mérnök utca 39. (SZÁMALK)",
      "akadaly" : "I",
      "szamlKijelolt" : "N",
      "atjKijelolt" : "N",
      "telepSzintu" : "N",
      "letszam" : {
        "indulo" : 1025,
        "honos" : 952,
        "atjel" : 0,
        "atjelInnen" : 72,
        "osszesen" : 952
      }
    }, {
      "sorszam" : "071",
      "szk_nev" : "Budapest XI. kerület, 071. számú szavazókör",
      "evk" : "02",
      "evk_nev" : "BUDAPEST főváros, 02. számú OEVK",
      "cim" : "1119 Budapest 11, Mérnök utca 39. (SZÁMALK)",
      "akadaly" : "I",
      "szamlKijelolt" : "N",
      "atjKijelolt" : "N",
      "telepSzintu" : "N",
      "letszam" : {
        "indulo" : 755,
        "honos" : 727,
        "atjel" : 0,
        "atjelInnen" : 38,
        "osszesen" : 727
      }
    }, {
      "sorszam" : "072",
      "szk_nev" : "Budapest XI. kerület, 072. számú szavazókör",
      "evk" : "02",
      "evk_nev" : "BUDAPEST főváros, 02. számú OEVK",
      "cim" : "1119 Budapest 11, Mérnök utca 39. (SZÁMALK)",
      "akadaly" : "I",
      "szamlKijelolt" : "N",
      "atjKijelolt" : "N",
      "telepSzintu" : "N",
      "letszam" : {
        "indulo" : 650,
        "honos" : 615,
        "atjel" : 0,
        "atjelInnen" : 32,
        "osszesen" : 615
      }
    }, {
      "sorszam" : "073",
      "szk_nev" : "Budapest XI. kerület, 073. számú szavazókör",
      "evk" : "02",
      "evk_nev" : "BUDAPEST főváros, 02. számú OEVK",
      "cim" : "1115 Budapest 11, Keveháza utca 2. (Ált. Isk.)",
      "akadaly" : "N",
      "szamlKijelolt" : "N",
      "atjKijelolt" : "N",
      "telepSzintu" : "N",
      "letszam" : {
        "indulo" : 895,
        "honos" : 862,
        "atjel" : 0,
        "atjelInnen" : 33,
        "osszesen" : 862
      }
    }, {
      "sorszam" : "074",
      "szk_nev" : "Budapest XI. kerület, 074. számú szavazókör",
      "evk" : "02",
      "evk_nev" : "BUDAPEST főváros, 02. számú OEVK",
      "cim" : "1115 Budapest 11, Keveháza utca 2. (Ált. Isk.)",
      "akadaly" : "N",
      "szamlKijelolt" : "N",
      "atjKijelolt" : "N",
      "telepSzintu" : "N",
      "letszam" : {
        "indulo" : 1031,
        "honos" : 979,
        "atjel" : 0,
        "atjelInnen" : 50,
        "osszesen" : 979
      }
    }, {
      "sorszam" : "075",
      "szk_nev" : "Budapest XI. kerület, 075. számú szavazókör",
      "evk" : "02",
      "evk_nev" : "BUDAPEST főváros, 02. számú OEVK",
      "cim" : "1115 Budapest 11, Keveháza utca 2. (Ált. Isk.)",
      "akadaly" : "N",
      "szamlKijelolt" : "N",
      "atjKijelolt" : "N",
      "telepSzintu" : "N",
      "letszam" : {
        "indulo" : 885,
        "honos" : 855,
        "atjel" : 0,
        "atjelInnen" : 36,
        "osszesen" : 855
      }
    }, {
      "sorszam" : "076",
      "szk_nev" : "Budapest XI. kerület, 076. számú szavazókör",
      "evk" : "02",
      "evk_nev" : "BUDAPEST főváros, 02. számú OEVK",
      "cim" : "1119 Budapest 11, Mérnök utca 39. (SZÁMALK)",
      "akadaly" : "I",
      "szamlKijelolt" : "N",
      "atjKijelolt" : "N",
      "telepSzintu" : "N",
      "letszam" : {
        "indulo" : 664,
        "honos" : 627,
        "atjel" : 0,
        "atjelInnen" : 33,
        "osszesen" : 627
      }
    }, {
      "sorszam" : "077",
      "szk_nev" : "Budapest XI. kerület, 077. számú szavazókör",
      "evk" : "02",
      "evk_nev" : "BUDAPEST főváros, 02. számú OEVK",
      "cim" : "1119 Budapest 11, Mérnök utca 39. (SZÁMALK)",
      "akadaly" : "I",
      "szamlKijelolt" : "I",
      "atjKijelolt" : "N",
      "telepSzintu" : "N",
      "letszam" : {
        "indulo" : 626,
        "honos" : 597,
        "atjel" : 0,
        "atjelInnen" : 30,
        "osszesen" : 597
      }
    }, {
      "sorszam" : "078",
      "szk_nev" : "Budapest XI. kerület, 078. számú szavazókör",
      "evk" : "18",
      "evk_nev" : "BUDAPEST főváros, 18. számú OEVK",
      "cim" : "1117 Budapest 11, Sopron út 50. (Ált. Isk.)",
      "akadaly" : "N",
      "szamlKijelolt" : "N",
      "atjKijelolt" : "N",
      "telepSzintu" : "N",
      "letszam" : {
        "indulo" : 1043,
        "honos" : 988,
        "atjel" : 0,
        "atjelInnen" : 57,
        "osszesen" : 988
      }
    }, {
      "sorszam" : "079",
      "szk_nev" : "Budapest XI. kerület, 079. számú szavazókör",
      "evk" : "18",
      "evk_nev" : "BUDAPEST főváros, 18. számú OEVK",
      "cim" : "1117 Budapest 11, Sopron út 50. (Ált. Isk.)",
      "akadaly" : "N",
      "szamlKijelolt" : "N",
      "atjKijelolt" : "N",
      "telepSzintu" : "N",
      "letszam" : {
        "indulo" : 1200,
        "honos" : 1111,
        "atjel" : 0,
        "atjelInnen" : 88,
        "osszesen" : 1111
      }
    }, {
      "sorszam" : "080",
      "szk_nev" : "Budapest XI. kerület, 080. számú szavazókör",
      "evk" : "18",
      "evk_nev" : "BUDAPEST főváros, 18. számú OEVK",
      "cim" : "1117 Budapest 11, Sopron út 50. (Ált. Isk.)",
      "akadaly" : "N",
      "szamlKijelolt" : "N",
      "atjKijelolt" : "N",
      "telepSzintu" : "N",
      "letszam" : {
        "indulo" : 1177,
        "honos" : 1110,
        "atjel" : 0,
        "atjelInnen" : 71,
        "osszesen" : 1110
      }
    }, {
      "sorszam" : "081",
      "szk_nev" : "Budapest XI. kerület, 081. számú szavazókör",
      "evk" : "18",
      "evk_nev" : "BUDAPEST főváros, 18. számú OEVK",
      "cim" : "1117 Budapest 11, Sopron út 50. (Ált. Isk.)",
      "akadaly" : "N",
      "szamlKijelolt" : "N",
      "atjKijelolt" : "N",
      "telepSzintu" : "N",
      "letszam" : {
        "indulo" : 1211,
        "honos" : 1156,
        "atjel" : 0,
        "atjelInnen" : 56,
        "osszesen" : 1156
      }
    }, {
      "sorszam" : "082",
      "szk_nev" : "Budapest XI. kerület, 082. számú szavazókör",
      "evk" : "18",
      "evk_nev" : "BUDAPEST főváros, 18. számú OEVK",
      "cim" : "1117 Budapest 11, Sopron út 50. (Ált. Isk.)",
      "akadaly" : "N",
      "szamlKijelolt" : "N",
      "atjKijelolt" : "N",
      "telepSzintu" : "N",
      "letszam" : {
        "indulo" : 1085,
        "honos" : 1023,
        "atjel" : 0,
        "atjelInnen" : 51,
        "osszesen" : 1023
      }
    }, {
      "sorszam" : "083",
      "szk_nev" : "Budapest XI. kerület, 083. számú szavazókör",
      "evk" : "18",
      "evk_nev" : "BUDAPEST főváros, 18. számú OEVK",
      "cim" : "1117 Budapest 11, Sopron út 50. (Ált. Isk.)",
      "akadaly" : "N",
      "szamlKijelolt" : "N",
      "atjKijelolt" : "N",
      "telepSzintu" : "N",
      "letszam" : {
        "indulo" : 823,
        "honos" : 767,
        "atjel" : 0,
        "atjelInnen" : 53,
        "osszesen" : 767
      }
    }, {
      "sorszam" : "084",
      "szk_nev" : "Budapest XI. kerület, 084. számú szavazókör",
      "evk" : "18",
      "evk_nev" : "BUDAPEST főváros, 18. számú OEVK",
      "cim" : "1119 Budapest 11, Fogócska utca 4. (Ált. Isk.)",
      "akadaly" : "I",
      "szamlKijelolt" : "N",
      "atjKijelolt" : "N",
      "telepSzintu" : "N",
      "letszam" : {
        "indulo" : 828,
        "honos" : 783,
        "atjel" : 0,
        "atjelInnen" : 42,
        "osszesen" : 783
      }
    }, {
      "sorszam" : "085",
      "szk_nev" : "Budapest XI. kerület, 085. számú szavazókör",
      "evk" : "18",
      "evk_nev" : "BUDAPEST főváros, 18. számú OEVK",
      "cim" : "1119 Budapest 11, Fogócska utca 4. (Ált. Isk.)",
      "akadaly" : "I",
      "szamlKijelolt" : "N",
      "atjKijelolt" : "N",
      "telepSzintu" : "N",
      "letszam" : {
        "indulo" : 1095,
        "honos" : 1056,
        "atjel" : 0,
        "atjelInnen" : 56,
        "osszesen" : 1056
      }
    }, {
      "sorszam" : "086",
      "szk_nev" : "Budapest XI. kerület, 086. számú szavazókör",
      "evk" : "18",
      "evk_nev" : "BUDAPEST főváros, 18. számú OEVK",
      "cim" : "1116 Budapest 11, Bükköny utca 2-4. (GAMESZ)",
      "akadaly" : "I",
      "szamlKijelolt" : "N",
      "atjKijelolt" : "N",
      "telepSzintu" : "N",
      "letszam" : {
        "indulo" : 1049,
        "honos" : 986,
        "atjel" : 0,
        "atjelInnen" : 63,
        "osszesen" : 986
      }
    }, {
      "sorszam" : "087",
      "szk_nev" : "Budapest XI. kerület, 087. számú szavazókör",
      "evk" : "18",
      "evk_nev" : "BUDAPEST főváros, 18. számú OEVK",
      "cim" : "1116 Budapest 11, Kiskőrös utca 1. (Ált. Isk.)",
      "akadaly" : "N",
      "szamlKijelolt" : "N",
      "atjKijelolt" : "N",
      "telepSzintu" : "N",
      "letszam" : {
        "indulo" : 745,
        "honos" : 714,
        "atjel" : 0,
        "atjelInnen" : 22,
        "osszesen" : 714
      }
    }, {
      "sorszam" : "088",
      "szk_nev" : "Budapest XI. kerület, 088. számú szavazókör",
      "evk" : "18",
      "evk_nev" : "BUDAPEST főváros, 18. számú OEVK",
      "cim" : "1116 Budapest 11, Gyékényes utca 45-47. (Albertfalvi Köz. Ház)",
      "akadaly" : "N",
      "szamlKijelolt" : "N",
      "atjKijelolt" : "N",
      "telepSzintu" : "N",
      "letszam" : {
        "indulo" : 746,
        "honos" : 709,
        "atjel" : 0,
        "atjelInnen" : 34,
        "osszesen" : 709
      }
    }, {
      "sorszam" : "089",
      "szk_nev" : "Budapest XI. kerület, 089. számú szavazókör",
      "evk" : "18",
      "evk_nev" : "BUDAPEST főváros, 18. számú OEVK",
      "cim" : "1116 Budapest 11, Gyékényes utca 45-47. (Albertfalvi Köz. Ház)",
      "akadaly" : "N",
      "szamlKijelolt" : "N",
      "atjKijelolt" : "N",
      "telepSzintu" : "N",
      "letszam" : {
        "indulo" : 1050,
        "honos" : 987,
        "atjel" : 0,
        "atjelInnen" : 68,
        "osszesen" : 987
      }
    }, {
      "sorszam" : "090",
      "szk_nev" : "Budapest XI. kerület, 090. számú szavazókör",
      "evk" : "18",
      "evk_nev" : "BUDAPEST főváros, 18. számú OEVK",
      "cim" : "1116 Budapest 11, Bükköny utca 9. (Óvoda)",
      "akadaly" : "I",
      "szamlKijelolt" : "N",
      "atjKijelolt" : "N",
      "telepSzintu" : "N",
      "letszam" : {
        "indulo" : 697,
        "honos" : 673,
        "atjel" : 0,
        "atjelInnen" : 21,
        "osszesen" : 673
      }
    }, {
      "sorszam" : "091",
      "szk_nev" : "Budapest XI. kerület, 091. számú szavazókör",
      "evk" : "18",
      "evk_nev" : "BUDAPEST főváros, 18. számú OEVK",
      "cim" : "1116 Budapest 11, Bükköny utca 9. (Óvoda)",
      "akadaly" : "I",
      "szamlKijelolt" : "N",
      "atjKijelolt" : "N",
      "telepSzintu" : "N",
      "letszam" : {
        "indulo" : 954,
        "honos" : 909,
        "atjel" : 0,
        "atjelInnen" : 41,
        "osszesen" : 909
      }
    }, {
      "sorszam" : "092",
      "szk_nev" : "Budapest XI. kerület, 092. számú szavazókör",
      "evk" : "18",
      "evk_nev" : "BUDAPEST főváros, 18. számú OEVK",
      "cim" : "1116 Budapest 11, Bükköny utca 9. (Óvoda)",
      "akadaly" : "I",
      "szamlKijelolt" : "N",
      "atjKijelolt" : "N",
      "telepSzintu" : "N",
      "letszam" : {
        "indulo" : 631,
        "honos" : 602,
        "atjel" : 0,
        "atjelInnen" : 24,
        "osszesen" : 602
      }
    }, {
      "sorszam" : "093",
      "szk_nev" : "Budapest XI. kerület, 093. számú szavazókör",
      "evk" : "18",
      "evk_nev" : "BUDAPEST főváros, 18. számú OEVK",
      "cim" : "1116 Budapest 11, Bükköny utca 9. (Óvoda)",
      "akadaly" : "I",
      "szamlKijelolt" : "N",
      "atjKijelolt" : "N",
      "telepSzintu" : "N",
      "letszam" : {
        "indulo" : 778,
        "honos" : 730,
        "atjel" : 0,
        "atjelInnen" : 35,
        "osszesen" : 730
      }
    }, {
      "sorszam" : "094",
      "szk_nev" : "Budapest XI. kerület, 094. számú szavazókör",
      "evk" : "18",
      "evk_nev" : "BUDAPEST főváros, 18. számú OEVK",
      "cim" : "1116 Budapest 11, Kiskőrös utca 1. (Ált. Isk.)",
      "akadaly" : "N",
      "szamlKijelolt" : "N",
      "atjKijelolt" : "N",
      "telepSzintu" : "N",
      "letszam" : {
        "indulo" : 1093,
        "honos" : 1046,
        "atjel" : 0,
        "atjelInnen" : 35,
        "osszesen" : 1046
      }
    }, {
      "sorszam" : "095",
      "szk_nev" : "Budapest XI. kerület, 095. számú szavazókör",
      "evk" : "18",
      "evk_nev" : "BUDAPEST főváros, 18. számú OEVK",
      "cim" : "1116 Budapest 11, Kiskőrös utca 1. (Ált. Isk.)",
      "akadaly" : "N",
      "szamlKijelolt" : "N",
      "atjKijelolt" : "N",
      "telepSzintu" : "N",
      "letszam" : {
        "indulo" : 1106,
        "honos" : 1033,
        "atjel" : 0,
        "atjelInnen" : 58,
        "osszesen" : 1033
      }
    }, {
      "sorszam" : "096",
      "szk_nev" : "Budapest XI. kerület, 096. számú szavazókör",
      "evk" : "18",
      "evk_nev" : "BUDAPEST főváros, 18. számú OEVK",
      "cim" : "1119 Budapest 11, Fogócska utca 4. (Ált. Isk.)",
      "akadaly" : "I",
      "szamlKijelolt" : "N",
      "atjKijelolt" : "N",
      "telepSzintu" : "N",
      "letszam" : {
        "indulo" : 755,
        "honos" : 717,
        "atjel" : 0,
        "atjelInnen" : 31,
        "osszesen" : 717
      }
    }, {
      "sorszam" : "097",
      "szk_nev" : "Budapest XI. kerület, 097. számú szavazókör",
      "evk" : "18",
      "evk_nev" : "BUDAPEST főváros, 18. számú OEVK",
      "cim" : "1119 Budapest 11, Bikszádi utca 11-15. (Ált. Isk.)",
      "akadaly" : "I",
      "szamlKijelolt" : "N",
      "atjKijelolt" : "N",
      "telepSzintu" : "N",
      "letszam" : {
        "indulo" : 819,
        "honos" : 774,
        "atjel" : 0,
        "atjelInnen" : 29,
        "osszesen" : 774
      }
    }, {
      "sorszam" : "098",
      "szk_nev" : "Budapest XI. kerület, 098. számú szavazókör",
      "evk" : "18",
      "evk_nev" : "BUDAPEST főváros, 18. számú OEVK",
      "cim" : "1119 Budapest 11, Bikszádi utca 11-15. (Ált. Isk.)",
      "akadaly" : "I",
      "szamlKijelolt" : "N",
      "atjKijelolt" : "N",
      "telepSzintu" : "N",
      "letszam" : {
        "indulo" : 833,
        "honos" : 799,
        "atjel" : 0,
        "atjelInnen" : 37,
        "osszesen" : 799
      }
    }, {
      "sorszam" : "099",
      "szk_nev" : "Budapest XI. kerület, 099. számú szavazókör",
      "evk" : "18",
      "evk_nev" : "BUDAPEST főváros, 18. számú OEVK",
      "cim" : "1119 Budapest 11, Bikszádi utca 11-15. (Ált. Isk.)",
      "akadaly" : "I",
      "szamlKijelolt" : "N",
      "atjKijelolt" : "N",
      "telepSzintu" : "N",
      "letszam" : {
        "indulo" : 993,
        "honos" : 937,
        "atjel" : 0,
        "atjelInnen" : 42,
        "osszesen" : 937
      }
    }, {
      "sorszam" : "100",
      "szk_nev" : "Budapest XI. kerület, 100. számú szavazókör",
      "evk" : "18",
      "evk_nev" : "BUDAPEST főváros, 18. számú OEVK",
      "cim" : "1119 Budapest 11, Bikszádi utca 61-63. (Ált. Isk.)",
      "akadaly" : "I",
      "szamlKijelolt" : "N",
      "atjKijelolt" : "N",
      "telepSzintu" : "N",
      "letszam" : {
        "indulo" : 1059,
        "honos" : 1002,
        "atjel" : 0,
        "atjelInnen" : 51,
        "osszesen" : 1002
      }
    }, {
      "sorszam" : "101",
      "szk_nev" : "Budapest XI. kerület, 101. számú szavazókör",
      "evk" : "18",
      "evk_nev" : "BUDAPEST főváros, 18. számú OEVK",
      "cim" : "1119 Budapest 11, Bikszádi utca 61-63. (Ált. Isk.)",
      "akadaly" : "I",
      "szamlKijelolt" : "N",
      "atjKijelolt" : "N",
      "telepSzintu" : "N",
      "letszam" : {
        "indulo" : 874,
        "honos" : 827,
        "atjel" : 0,
        "atjelInnen" : 34,
        "osszesen" : 827
      }
    }, {
      "sorszam" : "102",
      "szk_nev" : "Budapest XI. kerület, 102. számú szavazókör",
      "evk" : "18",
      "evk_nev" : "BUDAPEST főváros, 18. számú OEVK",
      "cim" : "1119 Budapest 11, Bikszádi utca 61-63. (Ált. Isk.)",
      "akadaly" : "I",
      "szamlKijelolt" : "N",
      "atjKijelolt" : "N",
      "telepSzintu" : "N",
      "letszam" : {
        "indulo" : 751,
        "honos" : 719,
        "atjel" : 0,
        "atjelInnen" : 25,
        "osszesen" : 719
      }
    }, {
      "sorszam" : "103",
      "szk_nev" : "Budapest XI. kerület, 103. számú szavazókör",
      "evk" : "18",
      "evk_nev" : "BUDAPEST főváros, 18. számú OEVK",
      "cim" : "1119 Budapest 11, Bikszádi utca 61-63. (Ált. Isk.)",
      "akadaly" : "I",
      "szamlKijelolt" : "N",
      "atjKijelolt" : "N",
      "telepSzintu" : "N",
      "letszam" : {
        "indulo" : 686,
        "honos" : 664,
        "atjel" : 0,
        "atjelInnen" : 24,
        "osszesen" : 664
      }
    }, {
      "sorszam" : "104",
      "szk_nev" : "Budapest XI. kerület, 104. számú szavazókör",
      "evk" : "18",
      "evk_nev" : "BUDAPEST főváros, 18. számú OEVK",
      "cim" : "1119 Budapest 11, Fogócska utca 4. (Ált. Isk.)",
      "akadaly" : "I",
      "szamlKijelolt" : "N",
      "atjKijelolt" : "N",
      "telepSzintu" : "N",
      "letszam" : {
        "indulo" : 754,
        "honos" : 738,
        "atjel" : 0,
        "atjelInnen" : 37,
        "osszesen" : 738
      }
    }, {
      "sorszam" : "105",
      "szk_nev" : "Budapest XI. kerület, 105. számú szavazókör",
      "evk" : "18",
      "evk_nev" : "BUDAPEST főváros, 18. számú OEVK",
      "cim" : "1119 Budapest 11, Fogócska utca 4. (Ált. Isk.)",
      "akadaly" : "I",
      "szamlKijelolt" : "N",
      "atjKijelolt" : "N",
      "telepSzintu" : "N",
      "letszam" : {
        "indulo" : 701,
        "honos" : 666,
        "atjel" : 0,
        "atjelInnen" : 30,
        "osszesen" : 666
      }
    }, {
      "sorszam" : "106",
      "szk_nev" : "Budapest XI. kerület, 106. számú szavazókör",
      "evk" : "18",
      "evk_nev" : "BUDAPEST főváros, 18. számú OEVK",
      "cim" : "1119 Budapest 11, Fogócska utca 4. (Ált. Isk.)",
      "akadaly" : "I",
      "szamlKijelolt" : "N",
      "atjKijelolt" : "N",
      "telepSzintu" : "N",
      "letszam" : {
        "indulo" : 801,
        "honos" : 771,
        "atjel" : 0,
        "atjelInnen" : 31,
        "osszesen" : 771
      }
    }, {
      "sorszam" : "107",
      "szk_nev" : "Budapest XI. kerület, 107. számú szavazókör",
      "evk" : "18",
      "evk_nev" : "BUDAPEST főváros, 18. számú OEVK",
      "cim" : "1116 Budapest 11, Kiskőrös utca 1. (Ált. Isk.)",
      "akadaly" : "N",
      "szamlKijelolt" : "N",
      "atjKijelolt" : "N",
      "telepSzintu" : "N",
      "letszam" : {
        "indulo" : 875,
        "honos" : 834,
        "atjel" : 0,
        "atjelInnen" : 28,
        "osszesen" : 834
      }
    }, {
      "sorszam" : "108",
      "szk_nev" : "Budapest XI. kerület, 108. számú szavazókör",
      "evk" : "18",
      "evk_nev" : "BUDAPEST főváros, 18. számú OEVK",
      "cim" : "1116 Budapest 11, Kiskőrös utca 1. (Ált. Isk.)",
      "akadaly" : "N",
      "szamlKijelolt" : "N",
      "atjKijelolt" : "N",
      "telepSzintu" : "N",
      "letszam" : {
        "indulo" : 830,
        "honos" : 800,
        "atjel" : 0,
        "atjelInnen" : 29,
        "osszesen" : 800
      }
    }, {
      "sorszam" : "109",
      "szk_nev" : "Budapest XI. kerület, 109. számú szavazókör",
      "evk" : "18",
      "evk_nev" : "BUDAPEST főváros, 18. számú OEVK",
      "cim" : "1116 Budapest 11, Kecskeméti J. utca 14. (Ált. Isk.)",
      "akadaly" : "N",
      "szamlKijelolt" : "N",
      "atjKijelolt" : "N",
      "telepSzintu" : "N",
      "letszam" : {
        "indulo" : 976,
        "honos" : 949,
        "atjel" : 0,
        "atjelInnen" : 28,
        "osszesen" : 949
      }
    }, {
      "sorszam" : "110",
      "szk_nev" : "Budapest XI. kerület, 110. számú szavazókör",
      "evk" : "18",
      "evk_nev" : "BUDAPEST főváros, 18. számú OEVK",
      "cim" : "1116 Budapest 11, Kecskeméti J. utca 14. (Ált. Isk.)",
      "akadaly" : "N",
      "szamlKijelolt" : "N",
      "atjKijelolt" : "N",
      "telepSzintu" : "N",
      "letszam" : {
        "indulo" : 1052,
        "honos" : 1026,
        "atjel" : 0,
        "atjelInnen" : 30,
        "osszesen" : 1026
      }
    }, {
      "sorszam" : "111",
      "szk_nev" : "Budapest XI. kerület, 111. számú szavazókör",
      "evk" : "18",
      "evk_nev" : "BUDAPEST főváros, 18. számú OEVK",
      "cim" : "1116 Budapest 11, Kecskeméti J. utca 14. (Ált. Isk.)",
      "akadaly" : "N",
      "szamlKijelolt" : "N",
      "atjKijelolt" : "N",
      "telepSzintu" : "N",
      "letszam" : {
        "indulo" : 811,
        "honos" : 792,
        "atjel" : 0,
        "atjelInnen" : 19,
        "osszesen" : 792
      }
    }, {
      "sorszam" : "112",
      "szk_nev" : "Budapest XI. kerület, 112. számú szavazókör",
      "evk" : "18",
      "evk_nev" : "BUDAPEST főváros, 18. számú OEVK",
      "cim" : "1116 Budapest 11, Kecskeméti J. utca 14. (Ált. Isk.)",
      "akadaly" : "N",
      "szamlKijelolt" : "N",
      "atjKijelolt" : "N",
      "telepSzintu" : "N",
      "letszam" : {
        "indulo" : 1199,
        "honos" : 1152,
        "atjel" : 0,
        "atjelInnen" : 50,
        "osszesen" : 1152
      }
    }, {
      "sorszam" : "113",
      "szk_nev" : "Budapest XI. kerület, 113. számú szavazókör",
      "evk" : "18",
      "evk_nev" : "BUDAPEST főváros, 18. számú OEVK",
      "cim" : "1112 Budapest 11, Kamaraerdei út 16. (Szoc. Otthon)",
      "akadaly" : "I",
      "szamlKijelolt" : "N",
      "atjKijelolt" : "N",
      "telepSzintu" : "N",
      "letszam" : {
        "indulo" : 1076,
        "honos" : 1010,
        "atjel" : 0,
        "atjelInnen" : 40,
        "osszesen" : 1010
      }
    }, {
      "sorszam" : "114",
      "szk_nev" : "Budapest XI. kerület, 114. számú szavazókör",
      "evk" : "18",
      "evk_nev" : "BUDAPEST főváros, 18. számú OEVK",
      "cim" : "1119 Budapest 11, Mérnök utca 39. (SZÁMALK)",
      "akadaly" : "I",
      "szamlKijelolt" : "N",
      "atjKijelolt" : "N",
      "telepSzintu" : "N",
      "letszam" : {
        "indulo" : 840,
        "honos" : 805,
        "atjel" : 0,
        "atjelInnen" : 35,
        "osszesen" : 805
      }
    }, {
      "sorszam" : "115",
      "szk_nev" : "Budapest XI. kerület, 115. számú szavazókör",
      "evk" : "02",
      "evk_nev" : "BUDAPEST főváros, 02. számú OEVK",
      "cim" : "1118 Budapest 11, Csiki-hegyek utca 13-15. (Ált. Isk.)",
      "akadaly" : "I",
      "szamlKijelolt" : "N",
      "atjKijelolt" : "I",
      "telepSzintu" : "N",
      "letszam" : {
        "indulo" : 0,
        "honos" : 0,
        "atjel" : 6139,
        "atjelInnen" : 0,
        "osszesen" : 6139
      }
    } ]
  }
}
